Workbook
Name highlightssports: Enums!$D$911:$D$942
Name highlightsbigday: Enums!$D$1151:$D$1165
Name highlightscoastal: Enums!$D$802:$D$832
Name highlightsimaginative: Enums!$D$1019:$D$1033
Name playgrounds: Enums!$D$268:$D$274
Name highlightsseasonal: Enums!$D$1188:$D$1212
Name historical: Enums!$D$361:$D$368
Name highlightshistorical: Enums!$D$1081:$D$1101
Name indoorenergy: Enums!$D$370:$D$375
Name transport: Enums!$D$389:$D$394
Name highlightsgardens: Enums!$D$841:$D$862
Name learning: Enums!$D$338:$D$343
Name coffeeshop: Enums!$D$403:$D$407
Name sportyactivity: Enums!$D$276:$D$290
Name waterbasedfun: Enums!$D$309:$D$318
Name imaginativeplay: Enums!$D$327:$D$330
Name bigdayout: Enums!$D$396:$D$401
Name indoorentertainment: Enums!$D$377:$D$387
Name highlightswalks: Enums!$D$741:$D$759
Name highlightstransport: Enums!$D$1140:$D$1149
Name highlightslearning: Enums!$D$1011:$D$1024
Name highlightsnature: Enums!$D$782:$D$800
Name sensory: Enums!$D$332:$D$336
Name highlightsdiscovery: Enums!$D$1074:$D$1079
Name coastaladventure: Enums!$D$247:$D$258
Name animalencounters: Enums!$D$351:$D$359
Name highlightsindoorenergy: Enums!$D$1128:$D$1138
Name highlightsfamilydining: Enums!$D$1178:$D$1186
Name familydining: Enums!$D$409:$D$412
Name museums: Enums!$D$345:$D$349
Name highlightscoffee: Enums!$D$1167:$D$1176
Name highlightssensory: Enums!$D$1035
Name highlightsindoorentertainment: Enums!$D$1037:$D$1057
Name highlightswaterfun: Enums!$D$963:$D$994
Name natureexploration: Enums!$D$236:$D$245
Name highlightsplaygrounds: Enums!$D$864:$D$909
Name highlightscreative: Enums!$D$996:$D$1017
Name seasonal: Enums!$D$293:$D$302
Name creativeplay: Enums!$D$320:$D$325
Name greenspaces: Enums!$D$228:$D$234
Name highlightsgreenspace: Enums!$D$761:$D$780
Name highlightswheels: Enums!$D$944:$D$961
Name scenicwalks: Enums!$D$214:$D$226
Name curatedoutdoor: Enums!$D$260:$D$266
Name highlightsanimals: Enums!$D$1103:$D$1126
Name wheelsroutes: Enums!$D$304:$D$307

Sheet Venues
A1: Essential Info | E1: Venue Descriptors | G1: Venue Address | N1: Venue Opening Days / Times | AI1: Venue Ticketing Types & Costs | BA1: Facilities | BF1: Age Suitability | BM1: Useful Info | BP1: Additional Details | BW1: Admin Panel
N2: Same Opening Daily | Q2: Daily Opening / Closing Times | AF2: Exceptions | AI2: Cost? | AJ2: Ticket Needed? | AK2: How to Book | AL2: Ticket Types | AM2: Baby Tickets | AO2: Child Tickets | AQ2: Young Child Tickets | AS2: Older Child Tickets | AU2: Adult Tickets | AW2: Concession Tickets | AY2: Group Tickets
A3: Opportunity Type | B3: Venue Setting | C3: Venue Setting (More specifically) | D3: Venue Name | E3: How would you group it? | F3: Description | G3: Address | H3: Address line 2 | I3: City/Town | J3: Postcode | K3: Latitude | L3: Longitude | M3: Country | N3: Which days of the week are they open? | O3: Same start & end times across all days? | P3: Daily Opening Time | Q3: Daily Closing Time | R3: Monday Opening Time | S3: Monday Closing Time | T3: Tuesday Opening Time | U3: Tuesday Closing Time | V3: Wednesday Opening Time | W3: Wednesday Closing Time | X3: Thursday Opening Time | Y3: Thursday Closing Time | Z3: Friday Opening Time | AA3: Friday Closing Time | AB3: Saturday Opening Time | AC3: Saturday Closing Time | AD3: Sunday Opening Time | AE3: Sunday Closing Time | AF3: Opening exclusions (not open on) | AG3: Bank Holidays | AH3: Seasonal Opening | AI3: Is there an Entry Cost? | AJ3: Ticketing Requirements | AK3: Booking Types | AL3: Ticketing Types | AM3: Baby Ticket Definition | AN3: Baby Ticket Price | AO3: Fixed Child Ticket Definition | AP3: Fixed Child Ticket Price | AQ3: Young Child Ticket Definition | AR3: Young Child Ticket Price | AS3: Older Child Ticket Definition | AT3: Older Child Ticket Price | AU3: Adult Ticket Definition | AV3: Adult Ticket Price | AW3: Concession Ticket Definition | AX3: Concession Ticket Price | AY3: Group Ticket Definition | AZ3: Group Ticket Price | BA3: Parking Provision | BB3: General Facilities | BC3: Kids Facilities | BD3: Parent Facilities | BE3: Dog Facilities | BF3: <1s | BG3: 1-2yrs | BH3: 3-4yrs | BI3: 5-7yrs | BJ3: 8-12yrs | BK3: 13+yrs | BL3: Adults | BM3: Inside or Outside | BN3: Weather Suitability | BO3: Estimated Time to Spend | BP3: Interest Tags | BQ3: Seasonal Tag | BR3: Seasonal Highlights | BS3: Attractions (Highlights) | BT3: Extra Kit | BU3: Images (Venues Folder) | BV3: Photo Contributor | BW3: Record ID | BX3: Developer Action | BY3: Added to Queue | BZ3: Upload Batch No. | CA3: Proposed Version | CB3: Change Summary | CC3: AWS Action Complete? | CD3: Return to WORKING? | CE3: Cancel Removal?
A4: opportunity_type | B4: venue_opportunity_theme | C4: venue_opportunity_theme_variant | D4: venue_name | E4: venue_activity_group | F4: venue_description | G4: venue_address_line_1 | H4: venue_address_line_2 | I4: venue_city | J4: venue_postcode | K4: latitude | L4: longitude | M4: venue_country | N4: venue_schedule_pattern | O4: venue_fixed_daily_timings | P4: venue_fixed_timings_start_time | Q4: venue_fixed_timings_end_time | R4: venue_mixed_timings_monday_start_time | S4: venue_mixed_timings_monday_end_time | T4: venue_mixed_timings_tuesday_start_time | U4: venue_mixed_timings_tuesday_end_time | V4: venue_mixed_timings_wednesday_start_time | W4: venue_mixed_timings_wednesday_end_time | X4: venue_mixed_timings_thursday_start_time | Y4: venue_mixed_timings_thursday_end_time | Z4: venue_mixed_timings_friday_start_time | AA4: venue_mixed_timings_friday_end_time | AB4: venue_mixed_timings_saturday_start_time | AC4: venue_mixed_timings_saturday_end_time | AD4: venue_mixed_timings_sunday_start_time | AE4: venue_mixed_timings_sunday_end_time | AF4: venue_opening_exclusions | AG4: venue_bank_holiday_opening | AH4: venue_seasonal_opening_hours | AI4: venue_entry_cost | AJ4: ticketing_requirement | AK4: venue_booking_type | AL4: ticketing_variants | AM4: ticket_variant_definition_baby | AN4: ticket_variant_baby_price | AO4: ticket_variant_definition_fixed_child | AP4: ticket_variant_fixed_child_price | AQ4: ticket_variant_definition_young_child | AR4: ticket_variant_young_child_price | AS4: ticket_variant_definition_older_child | AT4: ticket_variant_older_child_price | AU4: ticket_variant_definition_adult | AV4: ticket_variant_adult_price | AW4: ticket_variant_definition_concession | AX4: ticket_variant_concession_price | AY4: ticket_variant_definition_group | AZ4: ticket_variant_group_price | BA4: venue_parking_provision | BB4: venue_general_facilities | BC4: venue_child_facilities | BD4: venue_adult_facilities | BE4: venue_dog_facilities | BF4: venue_age_suitability_under_1_s | BG4: venue_age_suitability_1_to_2_years | BH4: venue_age_suitability_3_to_4_years | BI4: venue_age_suitability_5_to_7_years | BJ4: venue_age_suitability_8_to_12_years | BK4: venue_age_suitability_over_13_years | BL4: venue_age_suitability_adults | BM4: venue_physical_setting | BN4: venue_detailed_weather_suitability | BO4: venue_estimated_duration | BP4: venue_interest_tags | BQ4: venue_seasonal_tag | BR4: venue_seasonal_highlights | BS4: venue_attractions | BT4: venue_extra_kit | BU4: image | BV4: contributor_first_name | BW4: record_id | BX4: developer_action | BY4: added_to_queue_at | BZ4: admin_version | CA4: queued_version | CB4: change_summary | CC4: actioned_in_aws | CD4: return_to_working | CE4: cancel_removal
A5: venue | B5: Playgrounds & Adventure Parks | C5: Local park | D5: Sandy Bay Park | E5: Low Effort, Simple Reset | F5: Sandy Bay at Devon Cliffs is a full holiday-park setting rather than a casual public play stop, so it’s most useful for families staying on site or using bookable facilities. The appeal is having beach access, accommodation, food and entertainment wrapped into one place, which can take a lot of planning pressure off. For day visitors, check access carefully before adding it as a general directory option. | G5: Sandy Bay | I5: Exmouth | J5: EX8 5BT | K5: 50.610061 | L5: -3.3661206 | N5: Monday, Tuesday, Wednesday, Thursday, Friday, Saturday, Sunday | O5: TRUE | P5: 0 | Q5: 1 | R5: - | S5: - | T5: - | U5: - | V5: - | W5: - | X5: - | Y5: - | Z5: - | AA5: - | AB5: - | AC5: - | AD5: - | AE5: - | AF5: - | AG5: Open | AI5: FALSE | AJ5: FALSE | AK5: Open (Free) Access | AM5: - | AN5: - | AO5: - | AP5: - | AQ5: - | AR5: - | AS5: - | AT5: - | AU5: - | AV5: - | AW5: - | AX5: - | AY5: - | AZ5: - | BA5: Paid Car Park, Members Car Park, Bike racks / bays | BF5: FALSE | BG5: TRUE | BH5: TRUE | BI5: TRUE | BJ5: FALSE | BK5: FALSE | BL5: FALSE | BM5: Outside | BN5: Sunshine, Overcast / cloudy, Dry & mild, Dry & cold, Dry & warm, Dry & hot, Windy (> X mph) | BO5: Under 30mins, 30-60mins | BP5: sandy beach, rock pooling, swimming, red cliffs, Jurassic Coast, paddling, café, South West Coast Path | BS5: Basket / nest swings, Sensory play features, Towers and platforms, Climbing frames | BT5: Sand toys | BU5: Sandy Bay Park.JPG | BV5: This weekend! | BW5: VEN-00166 | BX5: CREATE | BY5: 46314.322 | CA5: 1 | CC5: FALSE | CD5: FALSE
A6: venue | B6: Museums & Discovery | C6: Science & Discovery, Child-Focused Discovery | D6: Jurassic Discovery | E6: Special Day Out | F6: Step back 65 million years at Jurassic Discovery in Seaton, where life-sized roaring animatronic dinosaurs (from the Natural History Museum in London) bring the prehistoric world to life. Explore the immersive 'Last Day of the Dinosaurs' exhibition, complete a Dino Detective trail and discover real prehistoric finds in the Leon Garner Fossil Collection, all of which make for a fun jurrasic themed outing. Younger children will be able to burn off energy in the three-level dinosaur-themed soft play and may like to try fossil digging in the Jurassic Garden, while older dinosaur enthusiasts can get stuck into the science, fossils and story of the dinosaurs' extinction which is thoughtfully provided in different, engaging ways throughout the site. It's a great rainy-day option or an educational outing during the school holidays, with enough to work for and entertain different ages. It's not a whole day outing for older children, but you could easily combine it with a longer soft play stretch, a trip on the Seaton Tramway or a wander along the seafront or around the Wetlands. Prices vary depending on whether you'd like to book tickets to the exhibition only, or combine this with the softplay and during half-term holidays the closing time extends to 17:30, so there's more time to fit in a visit, or one of their seasonal activities too. | G6: Jurassic Discovery | H6: The Underfleet | I6: Seaton | J6: Ex12 2WD | K6: 50.705907 | L6: -3.0678618 | N6: Monday, Tuesday, Wednesday, Thursday, Friday, Saturday, Sunday | O6: FALSE | P6: - | Q6: - | R6: 0.39583333 | S6: 0.64583333 | T6: 0.39583333 | U6: 0.64583333 | V6: 0.39583333 | W6: 0.64583333 | X6: 0.39583333 | Y6: 0.64583333 | Z6: 0.39583333 | AA6: 0.64583333 | AB6: 0.39583333 | AC6: 0.72916667 | AD6: 0.39583333 | AE6: 0.72916667 | AF6: Closed 25.12.2026, 26.12.2026 | AG6: Open | AH6: FALSE | AI6: TRUE | AJ6: TRUE | AK6: Pay on Arrival, Advance Book | AL6: Baby, (Fixed) Child, Adult, Group | AM6: Under 2 | AN6: 0 | AO6: 2-15 | AP6: 9.75-15.00 | AQ6: - | AR6: - | AS6: - | AT6: - | AU6: 16+ | AV6: 12.95-14.00 | AW6: - | AX6: - | AY6: Family 2 Adults 2 Children over 2 | AZ6: 43 | BA6: Paid Car Park | BB6: Toilets, Disabled toilets, Baby changing, Highchairs, Picnic Benches, Indoor Seating, Outdoor Seating, Water Refill | BC6: Colouring, Ice creams, Activity Sheets or Signs, Activity trail, Treasure hunt, Children’s trail, Sandpit, Children's Menu, Indoor Play Space | BD6: Hot Drinks, Comfy Seating / Sofas, WiFi, Hot & Cold food, Clear Sightlines, Snacks, Sweet treats, Outdoor terrace | BF6: FALSE | BG6: TRUE | BH6: TRUE | BI6: TRUE | BJ6: TRUE | BK6: TRUE | BL6: FALSE | BM6: Mixed | BN6: Stormy / heavy rain / thunderstorms, Windy (> X mph), Raining / wet, Overcast / cloudy, Dry & mild, Dry & cold, Dry & warm, Snow / sleet / ice | BO6: 1-2hrs | BP6: Dinosaurs, History, Activities, soft Play, Dinosaurs, Fossils, Palaeontology, Prehistoric life, Natural history, Geology, Science, Dinosaur skeletons, Extinction, Animatronics, Interactive exhibitions, Fossil hunting, Soft play, Indoor play, Educational activities | BS6: Nature and the environment, History brought to life | BU6: Jurrasic Discovery Centre.jpeg | BV6: Venue (Richard) | BW6: VEN-00292 | BX6: CREATE | BY6: 46311.725 | CA6: 1 | CC6: FALSE | CD6: FALSE
A7: venue | B7: Soft Play & Indoor Active Play | C7: Toddler Play Space, Soft Play Centre | D7: Wild Things Play Project | E7: Energy Burner, Low Effort | F7: Wild Things Play Project brings a natural, imaginative feel to indoor play, with wooden scandi-style climbing frames, sand play, sensory spaces, a crafty corner and a dedicated under-3s area, all set inside Drake Circus. The space is designed for ages 0–7, and the natural materials offer a welcome change from the usual bright hues of soft-place centres; there are no screens and the woodland-inspired feel makes it feel more appealing when you need to spend a morning or afternoon inside. Children with additional needs are well catered for, with wheelchair-friendly access throughout and a genuinely inclusive design ethos. The café does proper food too; Wild Breakfast, toasties, jacket potatoes, Nourish Bowls, barista coffee and homemade cakes, so you can enjoy something nice to eat while your children play. It's on the upper level of Drake Circus, which means parking is straightforward and there's no weather dependency to factor in at all. Blue light card-holders get 10% discount on the prices, and memberships are available if you think you'll be a regular visitor and want your money to go a bit further. | G7: 1 Charles Street | H7: Drake Circus | I7: Plymouth | J7: PL1 1EA | K7: 50.372553 | L7: -4.1385538 | N7: Monday, Tuesday, Wednesday, Thursday, Friday, Saturday, Sunday | O7: FALSE | P7: - | Q7: - | R7: 0.41666667 | S7: 0.75 | T7: 0.41666667 | U7: 0.75 | V7: 0.41666667 | W7: 0.75 | X7: 0.41666667 | Y7: 0.75 | Z7: 0.41666667 | AA7: 0.75 | AB7: 0.41666667 | AC7: 0.75 | AD7: 0.4375 | AE7: 0.6875 | AI7: FALSE | AJ7: FALSE | AK7: Advance Book, Pay On Arrival, Memberships | AL7: Baby, Young Child, Older Child, Adult | AM7: 0-2 | AN7: 3-7.5 | AO7: - | AP7: - | AQ7: 46115 | AR7: 9.5 | AS7: 46208 | AT7: 9.95 | AU7: 16+ | AV7: 2.5 | AW7: - | AX7: - | AY7: - | AZ7: - | BA7: Paid Car Park | BB7: Toilets, Baby changing, Disabled toilets, Highchairs, Indoor Seating | BC7: Children's Menu, Ride on Vehicles, Ice creams, Sandpit, Colouring | BD7: Hot Drinks, Hot & Cold food, Snacks, Sweet treats | BF7: TRUE | BG7: TRUE | BH7: TRUE | BI7: TRUE | BJ7: FALSE | BK7: FALSE | BL7: FALSE | BM7: Inside | BN7: Raining / wet, Windy (> X mph), Snow / sleet / ice, Overcast / cloudy, Stormy / heavy rain / thunderstorms, Dry & mild, Dry & cold | BO7: 1-2hrs | BP7: sand play, sandpit, sensory play, soft play, free play, climbing, imaginary world, barista coffee, rope bridges, hide and seek | BS7: Tunnels and crawl spaces, Clear sightlines, Seating for adults, Café or refreshment area, Separate toddler area, Age-zoned play areas, Soft climbing structures | BU7: Wild Things Play Project.jpeg | BV7: Chase Richard (Email) | BW7: VEN-00277 | BX7: CREATE | BY7: 46311.685 | BZ7: 1 | CA7: 1 | CC7: FALSE | CD7: FALSE
A8: venue | B8: Sensory or Calming Experiences | C8: Soothing Environment, Light-touch Sensory | D8: Little Sands Indoor Beach Play | E8: Low Effort, Simple Reset | F8: The idea of Little Sands is disarmingly charming — a clean, gated indoor sandpit in the centre of Sidbury village, open whatever the weather, with good coffee on the side — and it solves a problem that parents of pre-schoolers know well: somewhere calm enough to actually sit down, with something genuinely absorbing for small children to do right in front of you. For this, it's perfect! The sandpit uses clean play-grade sand and is exclusively for children aged five and under, which keeps the energy level manageable, and the café serves locally roasted coffee, milkshakes and cakes within clear sightlines of the play area throughout. Adult entry includes a free coffee, which tells you quite a lot about who this was designed for and how seriously they've thought about the parent experience! Special morning sessions for children two and under run on certain days, which is worth knowing before visiting with a baby (best to check the website for these as they don't run to a regular timetable). | G8: Fore Street | H8: Sidbury | I8: Sidmouth | J8: EX10 0SD | K8: 50.719781 | L8: -3.2205286 | N8: Monday, Tuesday, Wednesday, Thursday, Friday, Saturday | O8: FALSE | P8: - | Q8: - | R8: 0.39583333 | S8: 0.66666667 | T8: 0.39583333 | U8: 0.66666667 | V8: 0.39583333 | W8: 0.66666667 | X8: 0.39583333 | Y8: 0.66666667 | Z8: 0.39583333 | AA8: 0.66666667 | AB8: 0.39583333 | AC8: 0.5 | AD8: - | AE8: - | AI8: TRUE | AJ8: TRUE | AK8: Advance Book, Pay On Arrival | AL8: (Fixed) Child, Adult | AM8: - | AN8: - | AO8: 0-5 | AP8: 5 | AQ8: - | AR8: - | AS8: - | AT8: - | AU8: 18+ | AV8: 5 | AW8: - | AX8: - | AY8: - | AZ8: - | BA8: Free Car Park | BB8: Toilets, Baby changing, Indoor Seating | BC8: Sandpit, Children's Menu, Indoor Play Space | BD8: Hot Drinks, Comfy Seating / Sofas, Snacks, Sweet treats, Clear Sightlines | BF8: TRUE | BG8: TRUE | BH8: TRUE | BI8: FALSE | BJ8: FALSE | BK8: FALSE | BL8: FALSE | BM8: Inside | BN8: Raining / wet, Windy (> X mph), Snow / sleet / ice, Overcast / cloudy, Stormy / heavy rain / thunderstorms, Dry & mild, Dry & cold | BO8: 30-60mins, 1-2hrs | BP8: digger toys, ice cream shop, play area, toddler-friendly, slide, sand toys, sand play, sandpit, indoor beach, tasty cakes, treats, good coffee | BS8: Tactile materials, Sensory toys or games | BT8: Sand toys | BU8: Little Sands.jpeg | BV8: Provider Instagram | BW8: VEN-00275 | BX8: CREATE | BY8: 46311.682 | BZ8: 1 | CA8: 1 | CC8: FALSE | CD8: FALSE
A9: venue | B9: Nature & Wildlife Exploration | C9: Nature Reserve, Wildlife Hotspot | D9: Seaton Wetlands | E9: Under the Radar | F9: Seaton Wetlands is one of the easiest places in East Devon to make wildlife feel accessible for children, with level trails, boardwalks, bird hides, pond-dipping platforms and wide estuary views across the Axe Valley. The reserve is made up of several connected wetland areas, including Seaton Marshes, Black Hole Marsh, Colyford Common and Stafford Marsh, each offering something slightly different to discover. Black Hole Marsh is a particular highlight for birdwatching, with lagoons, viewing hides and opportunities to spot wading birds and other wildlife throughout the seasons. The appeal is in slowing down and noticing things in a fairly low-effort, low-key way: birds moving across the water, dragonflies in warmer months, reeds, mudflats and little changes in the landscape as you explore. The generally flat paths make much of the reserve manageable for families with pushchairs, balance bikes and young cyclists, although cycling access varies between sections. Children can enjoy peering through viewing windows, spotting wildlife from the hides or following the trails between different habitats, while older children with an interest in birds, nature or photography will find plenty to keep them engaged. There's enough variety to make a longer outing of it, but it's equally lovely for a shorter wander without needing to cover the whole reserve. | G9: Colyford Road | H9: Seaton | J9: EX12 2DF | K9: 50.718201 | L9: -3.0651216 | N9: Monday, Tuesday, Wednesday, Thursday, Friday, Sunday, Saturday | O9: TRUE | P9: 0 | Q9: 1 | R9: - | S9: - | T9: - | U9: - | V9: - | W9: - | X9: - | Y9: - | Z9: - | AA9: - | AB9: - | AC9: - | AD9: - | AE9: - | AG9: Open | AI9: FALSE | AJ9: FALSE | AK9: Open (Free) Access | AM9: - | AN9: - | AO9: - | AP9: - | AQ9: - | AR9: - | AS9: - | AT9: - | AU9: - | AV9: - | AW9: - | AX9: - | AY9: - | AZ9: - | BA9: Free Car Park | BB9: BYO Picnic, Picnic Benches, Bench Seating, Buggy Friendly, Disabled toilets, Toilets, Service Dogs Only | BC9: Activity trail | BD9: Clear Sightlines | BF9: TRUE | BG9: TRUE | BH9: TRUE | BI9: TRUE | BJ9: TRUE | BK9: TRUE | BL9: TRUE | BM9: Outside | BN9: Windy (> X mph), Sunshine, Snow / sleet / ice, Overcast / cloudy, Dry & mild, Dry & cold, Dry & warm, Dry & hot | BO9: 30-60mins, 1-2hrs | BP9: Wetlands, Nature reserve, Bird hides, Birdwatching, Pond dipping, Boardwalks, Level trails, Wildlife spotting, Dragonflies, Butterflies, Wading birds, Water birds, Reeds, Mudflats, Estuary, River Axe, Nature walk, Pushchair-friendly paths, Wheelchair-friendly paths, Seaton, Black Hole Marsh, Colyford Common, Stafford Marsh | BQ9: Springtime, Summer, Autumn colours, Autumn | BR9: Birdsong, "Returning swallows, swifts (birds)", Butterflies, Seabird Colonies, Kingfisher Spotting, Starling Murmurations, Autumn Leaves, Migrating Birds | BS9: Guided outdoor learning prompts, Marked Trails, Immersive natural surroundings, Quiet or low-intervention spaces, Climbing Logs or balance beams | BT9: XC Buggy, Binoculars | BU9: Seaton Wetlands.jpg | BV9: Claire (website) | BW9: VEN-00287 | BX9: CREATE | BY9: 46311.666 | BZ9: 1 | CA9: 1 | CC9: FALSE | CD9: FALSE
A10: venue | B10: Coastal Adventures | C10: Harbour or Village Beach | D10: Lyme Regis Harbour | E10: Simple Reset | F10: Wander Lyme Regis' historic harbour, where fishing boats bob beside the famous Cobb harbour wall. It's a great spot to try crabbing, watch the boats coming and going or explore the little marine aquarium, while older adventurers might enjoy a fishing trip or kayaking and paddleboarding from the nearby beach. Walk along the Cobb for views across Lyme Bay, then head to the sandy beach for a paddle or ice cream, but remember it's a working harbour so keep a close eye on smaller children as there's usually a lot of marine activity. | G10: Cobb Road | I10: Lyme Regis | J10: DT7 3JJ | K10: 50.720211 | L10: -2.9410291 | N10: Monday, Tuesday, Wednesday, Thursday, Friday, Sunday, Saturday | O10: TRUE | P10: 0 | Q10: 1 | R10: - | S10: - | T10: - | U10: - | V10: - | W10: - | X10: - | Y10: - | Z10: - | AA10: - | AB10: - | AC10: - | AD10: - | AE10: - | AF10: - | AG10: Open | AI10: FALSE | AJ10: FALSE | AK10: Open (Free) Access | AM10: - | AN10: - | AO10: - | AP10: - | AQ10: - | AR10: - | AS10: - | AT10: - | AU10: - | AV10: - | AW10: - | AX10: - | AY10: - | AZ10: - | BA10: Paid Car Park | BB10: BYO Picnic, Buggy Friendly, Bench Seating, Dogs Allowed | BD10: Clear Sightlines, Drinks stand, Snacks | BE10: Dogs On Leads | BF10: TRUE | BG10: TRUE | BH10: TRUE | BI10: TRUE | BJ10: TRUE | BK10: TRUE | BL10: TRUE | BM10: Outside | BN10: Sunshine, Overcast / cloudy, Dry & mild, Dry & cold, Dry & warm, Dry & hot | BO10: 30-60mins | BP10: crabbing, harbour walls, boats, fishing boats, harbour activity, fishermen, Harbours, Fishing boats, Crabbing, Marine life, Maritime history, Boat watching, Boat trips, Fishing, Kayaking, Paddleboarding, Watersports, Seaside exploring | BQ10: Summer | BS10: Crabbing, Harbour, Coastal Wildlife, Toilets nearby, Beach Cafe, Slipway, Kayaking / SUP, Equipment Hire | BT10: Infant / toddler carrier, Sling / baby carrier, Buckets & nets, Fishing rods & bait | BU10: Lyme Regis Harbour.jpg | BV10: Claire | BW10: VEN-00291 | BX10: CREATE | BY10: 46311.657 | BZ10: 1 | CA10: 1 | CC10: FALSE | CD10: FALSE
A11: venue | B11: Water Activities | C11: Lido, Swimming Pool | D11: Shoalstone Seawater Pool | E11: Moment of Peace, Wilder Adventure | F11: For a summer swim with a difference, Shoalstone's enormous 53m seawater pool sits right on the coast overlooking Torbay. It's free to use, but they run reliant on donations, so if you can, a contribution of £8.50 per family, or £3 per swimmer is gretly appreciated. There's a shallow end for little swimmers and plenty of room for older children to practise their lengths, splash about or enjoy a refreshing dip without swimming in the open sea. The water is unheated, so expect a bracing plunge! Make a morning or afternoon of it with a picnic on the grassy terraces, rockpooling along the shore or lunch at the poolside bistro. Entry is free, with donations welcomed. The pool generally opens May–September, with lifeguards during designated summer hours (the facilities are seasonal too). Access involves steps or a steep ramp, so it's less convenient with buggies or if you're unable to navigate steps or steep slopes. It's worth checking conditions and pool closures before travelling, as water levels can vary quite a bit with the tides. There's a grassy picnic area nearby so it works well for a simpler, water-based outing and snack stop combined. | G11: Shoalstone Seawater Pool | H11: Berry Head Road | I11: Brixham | J11: TQ5 9FT | K11: 50.401356 | L11: -3.4987912 | N11: Monday, Tuesday, Wednesday, Thursday, Friday, Saturday, Sunday | O11: TRUE | AH11: TRUE | AI11: FALSE | AJ11: FALSE | AK11: Open (Free) Access | AM11: - | AN11: - | AO11: - | AP11: - | AQ11: - | AR11: - | AS11: - | AT11: - | AU11: - | AV11: - | AW11: - | AX11: - | AY11: - | AZ11: - | BA11: Paid Car Park | BB11: Toilets, Showers / changing facilities, BYO Picnic, Dogs Allowed, Indoor Seating, Water Refill | BF11: FALSE | BG11: FALSE | BH11: TRUE | BI11: TRUE | BJ11: TRUE | BK11: TRUE | BL11: TRUE | BM11: Outside | BN11: Sunshine, Dry & warm, Dry & hot, Dry & mild | BP11: Outdoor swimming, Seawater swimming, Sea pools, Swimming, Rockpooling, Marine life, Coastal exploring, Cold Water Swimming, Sea Swimming, Plunge Pools | BS11: Deep water or plunge pools, Natural Swimming Spots, Lifeguarded areas (where applicable), Wildlife spotting | BT11: Swimming kit, Towels, Water shoes, Dry bags, Wetsuits, Change of clothes | BU11: Brixham Sea Pool.JPG | BV11: Claire | BW11: VEN-00290 | BX11: CREATE | BY11: 46311.654 | BZ11: 1 | CA11: 1 | CC11: FALSE | CD11: FALSE
A12: venue | B12: Water Activities | C12: On The Water, Watersports | D12: "Duck Pond" Exmouth | E12: Moment of Peace | F12: The “Duck Pond” is the locals’ name for a sheltered part of the Exe Estuary by Exmouth Recreation Ground, where the water feels calmer and more contained than the open seafront, making it a popular spot for paddleboarding and watersports. It is not actually a pond, but an estuary pocket with mud, shallow water, birds, boats and big views across the river. For families, the interest is in the setting and the sheltered water: watching the tide, spotting birds, seeing paddleboarders or watersports activity, walking along the estuary edge and using the nearby Recreation Ground as breathing space. It works best as a small local add-on rather than a destination on its own, unless you’re bringing a SUP, kayak or kiteboard. Check tide times before heading down, as the mudflats are exposed at low tide and you may have a long walk out to reach the water if you time it wrong. | G12: The Royal Avenue | I12: Exmouth | J12: EX8 1DG | K12: 50.621595 | L12: -3.4173185 | N12: Monday, Tuesday, Wednesday, Thursday, Friday, Saturday, Sunday | O12: TRUE | P12: 0 | Q12: 1 | R12: - | S12: - | T12: - | U12: - | V12: - | W12: - | X12: - | Y12: - | Z12: - | AA12: - | AB12: - | AC12: - | AD12: - | AE12: - | AG12: Open | AI12: FALSE | AJ12: FALSE | AK12: Open (Free) Access | AM12: - | AN12: - | AO12: - | AP12: - | AQ12: - | AR12: - | AS12: - | AT12: - | AU12: - | AV12: - | AW12: - | AX12: - | AY12: - | AZ12: - | BA12: Paid Car Park, Bike racks / bays, Disabled parking bays | BB12: BYO Picnic, Bench Seating, Buggy Friendly, Dogs Allowed | BD12: Clear Sightlines | BE12: Dogs On Leads, Poo Bins | BF12: FALSE | BG12: FALSE | BH12: FALSE | BI12: TRUE | BJ12: TRUE | BK12: TRUE | BL12: TRUE | BM12: Outside | BN12: Sunshine, Overcast / cloudy, Dry & warm, Dry & hot, Dry & mild | BO12: 1-2hrs, 30-60mins | BP12: Exe Estuary, Estuary walk, Sheltered water, Shallow water, Paddleboarding, SUP, Kayaking, Kiteboarding, Watersports, Boats, Tides, Mudflats, Birdwatching, Water birds, River views, Big views, Recreation Ground, Flat paths, Scooters, Teen activity, Local walk, Exmouth, Imperial Road, Coastal town | BQ12: Summer | BR12: Migrating Birds, Seabird Colonies, Marine Wildlife Spotting | BS12: Paddling spots, Sheltered or shaded options, Predictable tides or flow, Wildlife spotting, River access for small boats or paddleboards, Paddleboarding | BT12: Towels, Water shoes, Tide timetable, Dry bags, Wetsuit Boots | BU12: Duck Pond Exmouth.JPG | BV12: Claire | BW12: VEN-00288 | BX12: CREATE | BY12: 46311.632 | BZ12: 1 | CA12: 1 | CC12: FALSE | CD12: FALSE
A13: venue | B13: Family Dining | C13: Family Eateries | D13: Cow & Cacao Café at Darts Farm | F13: The more indulgent side of eating at Darts Farm, anchored around the farm's own bean-to-bar chocolatier and homemade seasonal gelato, it's a particularly tasty stop! The menu runs from smoothie bowls, banana bread and wood-fired eggs at breakfast through to sourdough pizzas, Darts burgers and seasonal fish at lunch, with homemade waffles, gelato-stuffed croissants and artisan pastries filling the gaps. The Terrace Bar alongside overlooks the Exe Estuary and hosts live music sessions on summer evenings. Dogs are welcome in the bar seating area but, like The Yard, it's walk-in only and it's a popular local spot that gets busy, so arriving early on sunny weekends is worth considering. It probably suits older children better who are happy to sit and enjoy the dining experience, as there's little to keep younger children occupied unless you plan ahead of bring bits — but paired with a trip to their park and animal pens, can work well together. | G13: Darts Farm Shopping Village | H13: Topsham | I13: Clyst St George | J13: EX3 0QH | K13: 50.685768 | L13: -3.4490059 | N13: Monday, Tuesday, Wednesday, Thursday, Friday, Saturday, Sunday | O13: FALSE | P13: - | Q13: - | R13: 0.375 | S13: 0.70833333 | T13: 0.375 | U13: 0.70833333 | V13: 0.375 | W13: 0.70833333 | X13: 0.375 | Y13: 0.70833333 | Z13: 0.375 | AA13: 0.70833333 | AB13: 0.375 | AC13: 0.70833333 | AD13: 0.39583333 | AE13: 0.66666667 | AF13: Closed Easter Sunday | AG13: Open | AI13: FALSE | AJ13: FALSE | AK13: Pay On Arrival, Advance Book | BA13: Free Car Park | BB13: Toilets, Disabled toilets, Baby changing, Buggy Friendly, Highchairs, Indoor Seating, Service Dogs Only | BC13: Colouring, Ice creams, Children's Menu | BD13: Hot Drinks, Comfy Seating / Sofas, WiFi, Hot & Cold food, Sweet treats, Snacks, Giftshop | BF13: TRUE | BG13: TRUE | BH13: TRUE | BI13: TRUE | BJ13: TRUE | BK13: TRUE | BL13: TRUE | BM13: Inside | BN13: Raining / wet, Windy (> X mph), Snow / sleet / ice, Overcast / cloudy, Sunshine, Stormy / heavy rain / thunderstorms, Dry & mild, Dry & cold, Dry & warm, Dry & hot | BO13: 30-60mins, 1-2hrs | BP13: Chocolate, Chocolatier, Chocolate making, Bean-to-bar chocolate, Artisan chocolate, Chocolate truffles, Gelato, Ice cream, Seasonal ice cream flavours, Chocolate tasting, Sweet treats, Desserts, Sourdough pizza, Wood-fired pizza, Burgers, Brunch, Smoothie bowls, Açaí bowls, Food lovers, Local produce, Darts Farm, Topsham, Farm Shop | BS13: Children’s menu, Flexible seating for families, Space for children to move a little, Play area or outdoor play space, On-site grounds to explore, Farm animals or gardens | BU13: Cow and Cacao.JPG | BV13: Lois | BW13: VEN-00175 | BX13: CREATE | BY13: 46311.5 | BZ13: 1 | CA13: 1 | CC13: FALSE | CD13: FALSE
A14: venue | B14: Family Dining | C14: Family Eateries | D14: The Yard at Darts Farm | F14: The more casual, all-day dining option at Darts Farm — a hearty, no-fuss restaurant in the courtyard serving Darts Farm breakfasts, sandwiches, salads, daily specials, homemade cakes and cream teas. It's the kind of place that works for a proper sit-down after the farm walk, a midway break during a shop, or a fuel stop at the end of an Exe Estuary Trail ride. The outdoor courtyard seating suits families with children who need a bit of room, and well-behaved dogs are welcome outside. Walk-in only though — no bookings — so on busy weekend mornings it's worth arriving with a bit of patience, or getting there early, or timing your visit slightly off peak. To access the cafe you walk through the farm shop, so be prepared! | G14: Darts Farm Shopping Village | H14: Topsham | I14: Clyst St George | J14: EX3 0QH | K14: 50.685768 | L14: -3.4490059 | N14: Monday, Tuesday, Wednesday, Thursday, Friday, Saturday, Sunday | O14: FALSE | P14: - | Q14: - | R14: 0.33333333 | S14: 0.70833333 | T14: 0.33333333 | U14: 0.70833333 | V14: 0.33333333 | W14: 0.70833333 | X14: 0.33333333 | Y14: 0.70833333 | Z14: 0.33333333 | AA14: 0.70833333 | AB14: 0.33333333 | AC14: 0.70833333 | AD14: 0.39583333 | AE14: 0.66666667 | AF14: Closed Easter Sunday | AG14: Open | AI14: FALSE | AJ14: FALSE | AK14: Pay On Arrival, Advance Book | BA14: Free Car Park | BB14: Toilets, Disabled toilets, Baby changing, Buggy Friendly, Highchairs, Indoor Seating, Service Dogs Only | BC14: Colouring, Ice creams, Children's Menu, "Indoor games (puzzles, boards)" | BD14: Hot Drinks, Comfy Seating / Sofas, WiFi, Hot & Cold food, Sweet treats, Snacks, Giftshop | BF14: TRUE | BG14: TRUE | BH14: TRUE | BI14: TRUE | BJ14: TRUE | BK14: TRUE | BL14: TRUE | BM14: Inside | BN14: Raining / wet, Windy (> X mph), Snow / sleet / ice, Overcast / cloudy, Sunshine, Stormy / heavy rain / thunderstorms, Dry & mild, Dry & cold, Dry & warm, Dry & hot | BO14: 30-60mins, 1-2hrs | BP14: Farmhouse breakfasts, Full English breakfast, Pancakes, Breakfast outings, Brunch, Lunch, Homemade cakes, Scones, Cream teas, Sandwiches, Seasonal food, Local produce, Farm-to-table food, Family meals, Food lovers, Darts Farm, Topsham, Farm Shop | BS14: Children’s menu, Flexible seating for families, Space for children to move a little, "Relaxed, family-welcoming feel", Farm animals or gardens, On-site grounds to explore | BU14: The Yard Darts Farm.JPG | BV14: Lois | BW14: VEN-00174 | BX14: CREATE | BY14: 46311.383 | BZ14: 1 | CA14: 1 | CC14: FALSE | CD14: FALSE
A15: venue | B15: Creative Activities | C15: Creative Artwork | D15: Something Lovely Pottery | E15: Moment of Peace | F15: A small creative courtyard just off the high street and a short walk from the Ham car park — this pottery painting studio is run by a Sidmouth mum who set the whole thing up after doing pottery with her own children on holiday and wanting to bring the same thing home. The space has over 100 ceramic pieces to choose from, all priced individually so children can be pointed toward a budget without any awkwardness, and the paint colours, brushes, dabbers, stamps and silk tools are all laid out clearly on the table. What makes it different from a standard pottery café is both the atmosphere — genuinely calm and unhurried — and the people running it, who are genuinely good at drawing in children who are nervous or unsure of themselves. A dedicated keepsake studio is available for baby handprints and footprints, with the owner painting the finished piece after the session. Everything is kiln-fired and collected a few weeks later, or posted for a small fee. Selley's coffee shop is directly alongside in the same courtyard. | G15: Something Lovely | H15: Libra Court | I15: Sidmouth | J15: EX10 8AJ | K15: 50.678677 | L15: -3.2370658 | N15: Tuesday, Wednesday, Friday, Saturday, Sunday | O15: FALSE | P15: - | Q15: - | R15: - | S15: - | T15: 0.4375 | U15: 0.66666667 | V15: 0.4375 | W15: 0.66666667 | X15: - | Y15: - | Z15: 0.4375 | AA15: 0.66666667 | AB15: 0.4375 | AC15: 0.66666667 | AD15: 0.47916667 | AE15: 0.625 | AI15: FALSE | AJ15: FALSE | AK15: Advance Book | AL15: (Fixed) Child, Adult | AM15: - | AN15: - | AO15: 1-15 | AP15: £6.00-30.00 | AQ15: - | AR15: - | AS15: - | AT15: - | AU15: 16+ | AV15: £6.00-30.00 | AW15: - | AX15: - | AY15: - | AZ15: - | BA15: Paid Car Park | BB15: Toilets, Baby changing, Indoor Seating, Buggy Friendly, Dogs Allowed, Highchairs, Parties | BD15: Comfy Seating / Sofas, Snacks, Hot Drinks, Sweet treats | BE15: Dogs On Leads | BF15: TRUE | BG15: TRUE | BH15: TRUE | BI15: TRUE | BJ15: TRUE | BK15: TRUE | BL15: TRUE | BM15: Inside | BN15: Raining / wet, Windy (> X mph), Snow / sleet / ice, Overcast / cloudy, Stormy / heavy rain / thunderstorms, Dry & mild, Dry & cold | BO15: 1-2hrs | BP15: pottery painting, small studio, calm environment, | BS15: Take-home creations, Open-ended creativity, "Pottery, ceramics or clay", Painting or brushwork, Imaginative freedom, "Calm, focused spaces", Creative studios, "Informal, welcoming environments", "Messy, hands-on crafts" | BU15: Something Lovely Pottery.JPG | BV15: Claire?? | BW15: VEN-00203 | BX15: CREATE | BY15: 46310.814 | BZ15: 1 | CA15: 1 | CC15: FALSE | CD15: FALSE
A16: venue | B16: Soft Play & Indoor Active Play | C16: Play Cafe | D16: Family Garden Exeter | E16: Simple Reset, Under the Radar | F16: Family Garden Exeter CIC is a small, peaceful family space that feels like a hidden gem in an unlikely setting. Inside, the room is bright, colourful and thoughtfully arranged, with wooden toys, books, dolls’ houses, baby toys, soft seating and gentle play areas that invite little children to potter, explore and make their own play without the noise or intensity of a bigger soft play venue. Its charm is in how calm and friendly it feels: grown-ups can sit close by with a genuinely good drink or something sweet, while babies, toddlers and preschoolers move between toys, books, imaginative play and cosy corners. It is especially lovely for busy or tired parents who want somewhere welcoming, creative and low-pressure, where children are happily occupied but the whole visit still feels peaceful. There are multiple rooms children can explore, and lots of space to run around without feeling awkward - the staff are genuinely friendly and welcoming too, and the whole place feels like the sort of hidden gem you wish you'd found sooner! | G16: Family Garden | H16: 80 Merrivale Road | I16: Exeter | J16: EX4 1PT | K16: 50.71733 | L16: -3.5502076 | N16: Monday, Tuesday, Wednesday, Thursday, Friday | O16: FALSE | R16: 0.41666667 | S16: 0.54166667 | T16: 0.41666667 | U16: 0.54166667 | V16: 0.41666667 | W16: 0.54166667 | X16: 0.41666667 | Y16: 0.54166667 | Z16: 0.41666667 | AA16: 0.5 | AB16: - | AC16: - | AD16: - | AE16: - | AH16: TRUE | AI16: TRUE | AJ16: FALSE | AK16: Pay On Arrival | AL16: Group | AM16: - | AN16: - | AO16: - | AP16: - | AQ16: - | AR16: - | AS16: - | AT16: - | AU16: - | AV16: - | AW16: - | AX16: - | AY16: 1 adult, 4 children | AZ16: £2.50-£4.50 | BA16: On-street / nearby parking | BB16: Toilets, Baby changing, Buggy Friendly, Indoor Seating, Water Refill | BC16: Colouring, "Indoor games (puzzles, boards)", Indoor Play Space, Clues / games | BD16: Hot Drinks, Clear Sightlines, Snacks, Sweet treats | BF16: TRUE | BG16: TRUE | BH16: TRUE | BI16: FALSE | BJ16: FALSE | BK16: FALSE | BL16: FALSE | BM16: Inside | BN16: Raining / wet, Windy (> X mph), Snow / sleet / ice, Overcast / cloudy, Stormy / heavy rain / thunderstorms, Sunshine, Dry & mild, Dry & hot, Dry & warm, Dry & cold | BO16: 30-60mins, 1-2hrs | BP16: indoor play space, wooden toys, creative space, imaginary place, role play, relaxed coffee spot, Family hub, Play café, Baby group, Toddler play, Preschool play, Wooden toys, Imaginative play, Dolls’ house, Books, Baby toys, Sensory play, Calm play, Gentle play, Creative space, Cosy corners, Soft seating, Parent and child, Sweet treats, Hot drinks, Friendly space, Low-pressure outing | BS16: Enclosed space, Clear sightlines, Seating for adults, Calm or quieter zones, Café or refreshment area, Separate toddler area | BU16: Family Garden Exeter.jpg | BV16: Rochelle | BW16: VEN-00285 | BX16: CREATE | BY16: 46309.629 | BZ16: 1 | CA16: 1 | CC16: FALSE | CD16: FALSE
A17: venue | B17: Gardens & Curated Outdoor Spaces | C17: Landscaped Garden | D17: Torre Abbey Park | E17: Energy Burner | F17: Torre Abbey Park sits close to the Riviera International Centre, the seafront and other family facilities and acts as a natural extension of a beach visit when children need to run around on grass rather than sand. It is more of a useful pause-and-link space than a destination park: somewhere to break up a visit to Waves, the Aqua Lounge, Torre Abbey Sands or the seafront without needing to move the whole family far. The gardens and open space give children a chance to reset between indoor swimming, food and beach time, while the setting keeps practical things like toilets, cafés and nearby activities within easy reach. | G17: Torre Abbey Park | H17: Torbay Road | I17: Torquay | J17: TQ2 5DG | K17: 50.463455 | L17: -3.5372739 | N17: Monday, Tuesday, Wednesday, Thursday, Friday, Saturday, Sunday | O17: FALSE | P17: 0 | Q17: 24:00 | R17: - | S17: - | T17: - | U17: - | V17: - | W17: - | X17: - | Y17: - | Z17: - | AA17: - | AB17: - | AC17: - | AD17: - | AE17: - | AF17: - | AI17: FALSE | AJ17: FALSE | AK17: Open (Free) Access | AM17: - | AN17: - | AO17: - | AP17: - | AQ17: - | AR17: - | AS17: - | AT17: - | AU17: - | AV17: - | AW17: - | AX17: - | AY17: - | AZ17: - | BB17: Picnic Benches, BYO Picnic, Dogs Allowed | BF17: FALSE | BG17: TRUE | BH17: TRUE | BI17: TRUE | BJ17: FALSE | BK17: FALSE | BL17: FALSE | BM17: Outside | BN17: Sunshine, Overcast / cloudy, Dry & warm, Dry & hot, Dry & mild | BO17: Under 30mins | BP17: open green space, tennis, pitch and putt golf, lawn bowls, Italian gardens, pond, fountain, outdoor play equipment, coastal views, medieval history, Agatha Christie, outdoor cinema, open air theatre, seaside park | BS17: Seasonal foliage, Seasonal or curated displays, Room to run freely, Open sightlines | BU17: Riveria Gardens.jpg | BV17: Sophie | BW17: VEN-00160 | BX17: UPDATE | BY17: 46309.612 | CA17: 3 | CC17: FALSE | CD17: FALSE
A18: venue | B18: Green Open Spaces | C18: Country Park | D18: Decoy Park | E18: Energy Burner, Simple Reset | F18: Decoy Country Park gives families lots of options for a lively outdoor trip: lake, woodland, wildlife, play area, picnic space, a splashpad in warmer months and boats that can be hired and taken out on the lake. It’s useful when you want more than a playground but less effort than a big day out, because children can move between climbing, walking, water play and snack stops, and the site isn't vast so nothing is a long walk from the car park. Bikes can be ridden around the trails which are sheltered and shaded, and have the usual large logs and fallen trees to clamber over. The splashpad is the summer make-or-break and runs on a timed daily system, so check it’s running before building the visit around it or prepare to be flexible and move between other options. | G18: 38 Decoy Road | I18: Newton Abbot | J18: TQ12 1DP | K18: 50.521153 | L18: -3.6001516 | N18: Monday, Tuesday, Thursday, Wednesday, Friday, Saturday, Sunday | O18: FALSE | P18: - | Q18: - | R18: 0.375 | S18: 0.75 | T18: 0.375 | U18: 0.75 | V18: 0.375 | W18: 0.75 | X18: 0.375 | Y18: 0.75 | Z18: 0.375 | AA18: 0.75 | AB18: 0.41666667 | AC18: 0.66666667 | AD18: 0.41666667 | AE18: 0.66666667 | AI18: FALSE | AJ18: FALSE | AK18: Open (Free) Access | AM18: - | AN18: - | AO18: - | AP18: - | AQ18: - | AR18: - | AS18: - | AT18: - | AU18: - | AV18: - | AW18: - | AX18: - | AY18: - | AZ18: - | BA18: Paid Car Park, Disabled parking bays | BB18: Toilets, Bench Seating, Dogs Allowed, Picnic Benches, Disabled toilets, Outdoor Seating, BYO Picnic, Pushchair Friendly | BC18: Ice creams, Activity trail | BD18: Hot Drinks, Snacks, Sweet treats | BE18: Poo Bins, Dogs On Leads | BF18: TRUE | BG18: TRUE | BH18: TRUE | BI18: TRUE | BJ18: TRUE | BK18: TRUE | BL18: TRUE | BM18: Outside | BN18: Dry & hot, Dry & warm, Dry & cold, Dry & mild, Overcast / cloudy, Sunshine | BO18: Under 30mins, 30-60mins, 1-2hrs, 2-3hrs | BP18: splashpad, water jets, tipping buckets, outdoor play equipment, zip wire, swings, climbing frame, slides, lake walk, duck feeding, wildlife spotting, kingfishers, BMX track, kayak hire | BQ18: Summer | BR18: Watersports Hire, Seasonal water fun, Fungi, "Berries, Nuts, Conkers", Autumn Leaves, Migrating Birds, Butterflies, Dragonflies & Damselflies | BS18: Climbable trees, Play equipment, Marked Trails, "Natural play features (logs, slopes, rocks)", "Bridges (wooden, stone, suspension)", Scenic backdrops, Countryside views, Room to run freely, Ponds or lakes | BT18: Towels, Swimming kit, Water shoes, XC Buggy, Sling / baby carrier, Infant / toddler carrier | BU18: Decoy Park.jpg | BV18: Lois | BW18: VEN-00042 | BX18: REMOVE | BY18: 46297.651 | CA18: 2 | CB18: Removal requested | CC18: FALSE | CE18: FALSE
A19: venue | B19: Playgrounds & Adventure Parks | C19: Local park | D19: Phear Park Playpark | E19: Simple Reset, Moment of Peace, Low Effort, Energy Burner | F19: Phear Park Play Park sits within a much bigger green park, making it more flexible than a standalone playground as it gives you lots of options in close proximity. Children can use the play area, then spill into open space, trees, paths and nearby park facilities if they still have energy. The park itself caters mainly to children ages 8 and under, but with basketball courts alongside it, and in eyeshot of the main park, it can easily work for mixed ages. | G19: Phear Park | H19: Withycombe Road | I19: Exmouth | J19: EX8 1TJ | K19: 50.624905 | L19: -3.4040576 | N19: Monday, Tuesday, Wednesday, Thursday, Friday, Saturday, Sunday | O19: FALSE | P19: 0 | Q19: 24:00 | R19: - | S19: - | T19: - | U19: - | V19: - | W19: - | X19: - | Y19: - | Z19: - | AA19: - | AB19: - | AC19: - | AI19: FALSE | AJ19: FALSE | AK19: Open (Free) Access | AM19: - | AN19: - | AO19: - | AP19: - | AQ19: - | AR19: - | AS19: - | AT19: - | AU19: - | AV19: - | AW19: - | AX19: - | AY19: - | AZ19: - | BA19: Free Car Park, Bike racks / bays, On-street / nearby parking | BB19: Dogs Allowed, Bench Seating, BYO Picnic, Pushchair Friendly | BC19: Zip Line, "Swings, Slides, Climbing Frames", Outdoor play equipment | BD19: Clear Sightlines | BF19: TRUE | BG19: TRUE | BH19: TRUE | BI19: TRUE | BJ19: TRUE | BK19: FALSE | BL19: FALSE | BM19: Outside | BN19: Sunshine, Overcast / cloudy, Dry & mild, Dry & cold, Dry & warm, Dry & hot, Windy (> X mph) | BO19: Under 30mins, 30-60mins, 1-2hrs, 2-3hrs | BP19: swings, slides, climbing frame | BS19: Climbing frames, Zip wires, Mixed-difficulty zones, Clear sightlines for adults, Towers and platforms | BU19: Phear Park Play Park.JPG | BV19: Lois | BW19: VEN-00104 | BX19: REMOVE | BY19: 46297.65 | CA19: 2 | CB19: Removal requested | CC19: FALSE | CE19: FALSE
A20: venue | B20: Green Open Spaces | C20: Urban Green Space | D20: Northernhay Gardens | E20: Simple Reset | F20: The oldest public open space in England, laid out in 1612, which is a fact worth telling older children before you arrive because it changes how they look at the place. Set just behind the High Street beside Rougemont Castle, the gardens are free, open from early morning until dusk and make a natural breathing space in the middle of a city visit without needing to go anywhere. What gives Northernhay its particular character is the way the everyday park; lawns, paths, flowerbeds, benches — sits right up against visible stretches of Roman and Saxon city wall that are genuinely ancient and touchable. Sculptures are scattered throughout, including the 1878 Deer Stalker and the 1923 War Memorial by local sculptor John Angel, and children who like history trails will find the Exeter history information boards a good thread to follow around the garden. Local legend has it the gardens were also used for witch hangings in the 1800s, which might be interesting to certain older children with a history fascination. | G20: Northernhay | I20: Exeter | J20: EX4 3SA | K20: 50.726493 | L20: -3.5316579 | N20: Monday, Tuesday, Wednesday, Thursday, Friday, Saturday, Sunday | O20: FALSE | P20: 07:30 | Q20: 18:00 | R20: - | S20: - | T20: - | U20: - | V20: - | W20: - | X20: - | Y20: - | Z20: - | AA20: - | AB20: - | AC20: - | AD20: - | AE20: - | AI20: FALSE | AJ20: FALSE | AK20: Open (Free) Access | AM20: - | AN20: - | AO20: - | AP20: - | AQ20: - | AR20: - | AS20: - | AT20: - | AU20: - | AV20: - | AW20: - | AX20: - | AY20: - | AZ20: - | BA20: Paid Car Park | BB20: Bench Seating, BYO Picnic, Wheelchair Friendly, Buggy Friendly, Dogs Allowed, Pushchair Friendly | BE20: Poo Bins, Dogs On Leads | BF20: TRUE | BG20: TRUE | BH20: TRUE | BI20: TRUE | BJ20: TRUE | BK20: FALSE | BL20: FALSE | BM20: Outside | BN20: Sunshine, Overcast / cloudy, Dry & warm, Dry & hot | BO20: Under 30mins | BP20: ancient history, Roman history, Roman walls, Saxon history, city walls, sculptures, statues, war memorial, history trail, archaeology, medieval history, Civil War, oldest public park, picnicking, open green space, autumn colour, blossom, city exploring, witch legend, local legend | BQ20: Springtime | BR20: Daffodills, Seasonal Flowers | BS20: Room to run freely, Scenic backdrops | BU20: Northernhay Gardens.JPG | BV20: Lois | BW20: VEN-00283 | BX20: CREATE | BY20: 46293.543 | BZ20: 1 | CA20: 1 | CC20: FALSE | CD20: FALSE
A21: venue | B21: Animal Encounters | C21: Animal Park or Zoo, Animal Sanctuary, Bird of Prey Centre, Farm or Smallholding | D21: Totnes Rare Breeds Farm | E21: Special Day Out | F21: A small, family-run petting farm beside the South Devon Steam Railway at Littlehempston, dedicated to the conservation of rare and endangered breeds, and genuinely one of those places where the intimacy of the setting is one of it's charms. Most enclosures can be entered rather than just viewed through a fence, which means children are cuddling guinea pigs, feeding Golden Guernsey goats and Welsh Mountain sheep, and — if the timing works out — being introduced to the rescue owls by the keeper who looks after them personally and gives demonstrations that children tend to talk about for the rest of the day. The animal collection includes red squirrels, donkeys, rare breed pigs, waterfowl, aviaries and more, all managed by a team of volunteers who know each animal well and are genuinely happy to take their time with curious children. The Garden Café alongside serves lovely made-to-order food and overlooks the steam railway. A wristband system allow you to come and go throughout the day rather than having to commit to a fixed visit length too. There's no parking on site, which is the main thing to plan ahead for, but the farm is an easy walk from Totnes train station where there is a paid car park. Wheelchair and buggy friendly across the whole site. | G21: Totnes rare breeds farm | H21: Riverside Station | I21: Totnes | J21: TQ96LZ | N21: Monday, Tuesday, Wednesday, Thursday, Friday, Saturday, Sunday | O21: TRUE | P21: 10:00 | Q21: 16:00 | R21: - | S21: - | T21: - | U21: - | V21: - | W21: - | X21: - | Y21: - | Z21: - | AA21: - | AB21: - | AC21: - | AD21: - | AE21: - | AF21: We are open March through to November | AH21: TRUE | AI21: TRUE | AJ21: FALSE | AK21: Pay on Arrival, Memberships | AL21: (Fixed) Child, Adult, Group, Baby, Concession | AM21: 0-2 | AN21: 0 | AO21: 3-15 | AP21: 8.5 | AQ21: - | AR21: - | AS21: - | AT21: - | AU21: 15+ | AV21: 10 | AW21: Over 60 | AX21: 9.5 | AY21: 2 adults 2 children | AZ21: 35 | BA21: Paid Car Park | BB21: Toilets, Disabled toilets, Baby changing, Picnic Benches, Highchairs, Indoor Seating, Outdoor Seating, Water Refill, Wheelchair Friendly, Buggy Friendly, Pushchair Friendly | BC21: Ice creams, Children's Menu | BD21: Hot Drinks, Hot & Cold food, Snacks, Sweet treats | BF21: TRUE | BG21: TRUE | BH21: TRUE | BI21: TRUE | BJ21: TRUE | BK21: FALSE | BL21: FALSE | BM21: Outside | BN21: Sunshine, Overcast / cloudy, Dry & mild, Dry & cold, Dry & warm | BO21: 1-2hrs, 2-3hrs | BP21: animal petting, rare breeds, animals, goats, owls, shetland ponies, pony grooming, reptiles, Ball Python, Giant Rex rabbit, Angora Goats and Shetland Ponies, chickens, ducks, welsh mountain sheep, small animals, guinea pigs, chicks, ducklings, chinchillas, tortoise, rabbits | BQ21: Summer, Springtime | BS21: Hands-on Petting, Animal feeding, Close-up viewing, Keeper talks, Animal Experience Day, Multiple species, Animal Sanctuary, Rare or exotic animals, Conservation, Baby animals (seasonal) | BU21: Totnes Rare Breeds Farm.JPG | BV21: Provider | BW21: VEN-00230 | BX21: CREATE | BY21: 46291.571 | BZ21: 1 | CA21: 1 | CC21: FALSE | CD21: FALSE
A22: venue | B22: A Big Day Out | C22: Themepark | D22: Crealy Themepark | E22: Special Day Out | F22: Crealy is the big, high-energy Devon themepark day: rides, indoor play, water rides, animals, live shows and enough variety to fill a full family day. It works especially well for mixed ages because there are outdoor rides and larger attractions, but also substantial indoor areas, soft play and toddler-friendly spaces if the weather turns or younger children need a reset. It is not a low-effort outing — and worth remembering that you'll want to plan around height restrictions, food, queues, naps and energy dips being on a larger site with full-throttle stimulation in every direction — but it promises something for everyone, and some genuinely high-adrenaline rides to keep things interesting for the braver visitors! | G22: Crealy Theme Park & Resort | H22: Sidmouth Road | I22: Clyst St Mary | J22: EX5 1DR | K22: 50.705683 | L22: -3.4161189 | N22: Monday, Tuesday, Wednesday, Thursday, Friday, Saturday, Sunday | O22: TRUE | P22: 0.41666667 | Q22: 0.70833333 | R22: - | S22: - | T22: - | U22: - | V22: - | W22: - | X22: - | Y22: - | Z22: - | AA22: - | AB22: - | AC22: - | AD22: - | AE22: - | AF22: Seasonal Opening Times (10:30-16:30 out of peak summer season) | AH22: TRUE | AI22: TRUE | AJ22: TRUE | AK22: Advance Book, Pay On Arrival, Memberships | AL22: Young Child, Older Child, Adult, Group | AM22: - | AN22: - | AO22: - | AP22: - | AQ22: 1-2.5 | AR22: 0 | AS22: 2.5-16 | AT22: £23.25-£27.13 | AU22: 16+ | AV22: £23.25-£27.13 | AW22: - | AX22: - | AY22: Mixed Family Tickets (Online only) | AZ22: - | BA22: Free Car Park | BB22: Toilets, Disabled toilets, Baby changing, Picnic Benches, BYO Picnic, Indoor Seating, Outdoor Seating, Dogs Allowed, Water Refill, Pushchair Friendly | BC22: Ice creams, Children's Menu, "Swings, Slides, Climbing Frames", Outdoor play equipment, Indoor Play Space | BD22: Hot Drinks, Hot & Cold food, Snacks, Drinks stand, Sweet treats, Giftshop | BF22: FALSE | BG22: FALSE | BH22: TRUE | BI22: TRUE | BJ22: TRUE | BK22: TRUE | BL22: TRUE | BM22: Mixed | BN22: Sunshine, Overcast / cloudy, Dry & mild, Dry & cold, Dry & warm, Dry & hot, Windy (> X mph) | BO22: 2-3hrs, 4+ hours, Whole Day | BP22: theme park, rollercoaster, water rides, log flume, drop tower, inverted ride, Sooty, Sooty Land, live shows, meet and greet, soft play, indoor play, adventure play, farm animals, zoo animals, meerkats, alpacas, Shetland ponies, tortoises, go karts, driving school, seasonal events, Halloween, all weather | BQ22: Christmas, Halloween, Summer | BS22: Rides & attractions, Animals or animal experiences, Live shows or performances, Immersive or themed environments, Play or activity zones, Iconic structures or rides, Water features, "Themed trails (e.g. Halloween, Christmas, Easter)" | BU22: Crealy.JPG | BV22: Suz Ox | BW22: VEN-00159 | BX22: CREATE | BY22: 46288.65 | BZ22: 1 | CA22: 1 | CC22: FALSE | CD22: FALSE
A23: venue | B23: Creative Activities | C23: Creative Artwork | D23: China Blue Pottery | E23: Moment of Peace | F23: A pottery painting studio, lifestyle store and café on Station Road in Totnes that includes considerably more than a standard pottery café. The ceramic studio is the biggest of its kind in the South West, with hundreds of pieces to choose from; everything from fairy tale figures and robots to mugs, bowls and dog bowls that can be painted with professional glazes that are then kiln-fired and either collected or posted home. Everything is individually priced, so there's usually something for each budget. For families who won't be around long enough to collect, there's also a Paint & Go option using poster paints where children take their piece home the same day, which is worth knowing about before you choose your ceramic. Alongside the painting, pot throwing on a wheel, clay modelling workshops and baby hand and footprint keepsakes can be booked. It's not a small or quiet setting; two floors of painting tables that feel fairly busy as the pottery studio is situated within the wider store area and nearby to the Deli & Kitchen, but the sheer variety of choice is the main draw if you've got a creative child with something very specific in mind to paint. | G23: China Blue | H23: Station Road | I23: Totnes | J23: TQ9 5JR | K23: 50.434076 | L23: -3.6878953 | N23: Monday, Tuesday, Wednesday, Thursday, Friday, Saturday, Sunday | O23: FALSE | P23: - | Q23: - | R23: 0.375 | S23: 0.70833333 | T23: 0.375 | U23: 0.70833333 | V23: 0.375 | W23: 0.70833333 | X23: 0.375 | Y23: 0.70833333 | Z23: 0.375 | AA23: 0.70833333 | AB23: 0.375 | AC23: 0.70833333 | AD23: 0.41666667 | AE23: 0.66666667 | AI23: FALSE | AJ23: FALSE | AK23: Advance Book, Pay On Arrival | AL23: (Fixed) Child, Adult | AM23: - | AN23: - | AO23: 0-16 | AP23: 3-30 | AQ23: - | AR23: - | AS23: - | AT23: - | AU23: 17+ | AV23: 3-30 | AW23: - | AX23: - | AY23: - | AZ23: - | BA23: Free Car Park | BB23: Toilets, Disabled toilets, Baby changing, Indoor Seating | BD23: Hot Drinks, Snacks, Sweet treats, Giftshop, Hot & Cold food | BF23: FALSE | BG23: FALSE | BH23: FALSE | BI23: TRUE | BJ23: TRUE | BK23: TRUE | BL23: TRUE | BM23: Inside | BN23: Raining / wet, Windy (> X mph), Overcast / cloudy, Stormy / heavy rain / thunderstorms, Snow / sleet / ice | BO23: 1-2hrs | BP23: pottery, pottery painting, ceramics, clay, glazing, creative artwork, painting | BS23: "Messy, hands-on crafts", Take-home creations, Open-ended creativity, Drop-in creative tables, "Pottery, ceramics or clay", Painting or brushwork, Imaginative freedom, Creative studios, "Informal, welcoming environments" | BU23: China Blue.JPG | BV23: Lois | BW23: VEN-00231 | BX23: CREATE | BY23: 46287.876 | BZ23: 1 | CA23: 1 | CC23: FALSE | CD23: FALSE
A24: venue | B24: Green Open Spaces | C24: Urban Green Space | D24: Hillcrest Community Nature Reserve | E24: Simple Reset | F24: A small urban woodland tucked into the Withycombe Raleigh part of Exmouth, managed by the Wild East Devon rangers as a community nature reserve and one of the more quietly pleasant green spaces in the town for children who like poking about in trees rather than heading straight for the beach. The reserve acts as a wildlife corridor through the town, with winding paths through woodland and scrub, butterflies in season and the kind of unhurried, slightly wild feel that's harder to find than it should be in a seaside town. It's a simple outing rather than a destination — boots or wellies are sensible, paths are uneven and there are no facilities — but Wild East Devon run seasonal family events here, including autumn crafts mornings during half term, which are worth checking for before visiting. Free to enter year-round, and accessible from both the railway and bus station without needing a car. | I24: Exmouth | J24: EX8 4DX | K24: 50.632736 | L24: -3.3901188 | N24: Monday, Tuesday, Wednesday, Thursday, Friday, Saturday, Sunday | O24: TRUE | P24: 0 | Q24: 24:00 | R24: - | S24: - | T24: - | U24: - | V24: - | W24: - | X24: - | Y24: - | Z24: - | AA24: - | AB24: - | AC24: - | AD24: - | AE24: - | AF24: - | AI24: FALSE | AJ24: FALSE | AK24: Open (Free) Access | AM24: - | AN24: - | AO24: - | AP24: - | AQ24: - | AR24: - | AS24: - | AT24: - | AU24: - | AV24: - | AW24: - | AX24: - | AY24: - | AZ24: - | BA24: On-street / nearby parking | BB24: Pushchair Friendly | BE24: Poo Bins, Dogs On Leads | BF24: FALSE | BG24: FALSE | BH24: TRUE | BI24: TRUE | BJ24: TRUE | BK24: FALSE | BL24: FALSE | BM24: Outside | BN24: Windy (> X mph), Sunshine, Overcast / cloudy, Stormy / heavy rain / thunderstorms, Dry & mild, Dry & cold, Dry & warm, Dry & hot | BO24: Under 30mins | BP24: nature reserve, green open space, space to run | BQ24: Springtime | BR24: Wildflower Meadows, Butterflies, Autumn Leaves, Sledging Spot | BS24: Meadows or wild grass, Room to run freely, Open sightlines, Rolling landscapes, Grassy banks, Climbable trees, Football or Rugby Posts | BU24: Hillcrest Nature Reserve.JPG | BV24: Lois | BW24: VEN-00274 | BX24: CREATE | BY24: 46287.856 | BZ24: 1 | CA24: 1 | CC24: FALSE | CD24: FALSE
A25: venue | B25: Transport & Engineering | C25: Trains & Railways, Working Transport Hubs | D25: South Devon Miniature Railway | E25: Simple Reset | F25: A small but charming 7.25-inch gauge miniature railway tucked into the award-winning gardens behind Buckfastleigh station, run by volunteers alongside the South Devon heritage railway. The ride is a half-mile loop through flower borders and woodland that loops it's way around the station car park. It's gentle, short and perfectly pitched at younger children who love trains but won't sit still for a full heritage steam journey but would love the excitment of a ride. The locomotive is a diesel named Greenie, well-maintained and much-loved by its volunteer crew and it's the kind of simple thing that makes a Buckfastleigh morning feel complete rather than rushed — the gardens have picnic benches alongside the miniature railway station, which gives parents somewhere to settle while children watch, play or wait for another go. The station itself has a café, toilets and a children's play area, and the Otter and Butterfly Sanctuary is a two-minute walk away, making the two a natural pairing. The miniature railway runs every weekend (weather-dependant) between April and October but this can (very occasionally) miss a week, so it's worth double-checking ahead for a specific date if it's a special occasion and the visit is centred on a ride. | G25: The Station | H25: Dart Bridge Road | I25: Buckfastleigh | J25: TQ11 0DZ | K25: 50.482455 | L25: -3.7677327 | N25: Saturday, Sunday | O25: FALSE | P25: - | Q25: - | R25: - | S25: - | T25: - | U25: - | V25: - | W25: - | X25: - | Y25: - | Z25: - | AA25: - | AB25: 0.5 | AC25: 0.66666667 | AD25: 0.5 | AE25: 0.66666667 | AI25: FALSE | AJ25: TRUE | AK25: Pay On Arrival | AL25: (Fixed) Child, Adult, Baby | AM25: 0-2 | AN25: 0 | AO25: 3-17 | AP25: 1.5 | AQ25: - | AR25: - | AS25: - | AT25: - | AU25: 18+ | AV25: 2.5 | AW25: - | AX25: - | AY25: - | AZ25: - | BA25: Free Car Park | BB25: Toilets, Disabled toilets, BYO Picnic, Dogs Allowed, Picnic Benches, Bench Seating, Outdoor Seating, Baby changing, Pushchair Friendly | BC25: "Swings, Slides, Climbing Frames", Ice creams | BD25: Hot Drinks, Snacks, Drinks stand, Sweet treats, Clear Sightlines | BE25: Dogs On Leads | BF25: TRUE | BG25: TRUE | BH25: TRUE | BI25: TRUE | BJ25: FALSE | BK25: FALSE | BL25: FALSE | BM25: Outside | BN25: Sunshine, Overcast / cloudy, Dry & mild, Dry & cold, Dry & warm | BO25: 30-60mins | BP25: miniature railway, stream trains, trains, locomotives, heritage railways, model railway | BQ25: Summer | BS25: Trains and locomotives, Vintage vehicles, Rides or journeys, Vehicles in operation, Engineering features | BU25: South Devon Miniature Railway.JPG | BV25: Lois | BW25: VEN-00271 | BX25: CREATE | BY25: 46287.737 | BZ25: 1 | CA25: 1 | CC25: FALSE | CD25: FALSE
A26: venue | B26: Playgrounds & Adventure Parks | C26: Local park | D26: Brixington Park | E26: Energy Burner | F26: A well-loved neighbourhood park in the Brixington area of Exmouth, redesigned and revamped in 2020 with the help of local children; the result is a genuinely lovely lifeboat-themed play area which gives a nod to Exmouth's maritime heritage and the RNLI presence in the area. With trampolines, zip wire, slides, monkey bars, climbing frames, group swings and all the usual smaller park equipment, it also has plenty of open green space alongside for running around, ball games, picnics and sports. It gets busy after school on weekdays (owing to being close to the local Primary School), but tends to be quiet at weekends — it works well for mixed ages owing to the variety of equipment and, with on-street parking closeby on all sides, it works as an easy stop-off when you're in the area or passing through and need a fresh-air stop. | G26: The Marles | I26: Exmouth | J26: EX8 4NU | K26: 50.635489 | L26: -3.3959323 | N26: Monday, Tuesday, Wednesday, Thursday, Friday, Saturday, Sunday | O26: TRUE | P26: 0 | Q26: 24:00 | R26: - | S26: - | T26: - | U26: - | V26: - | W26: - | X26: - | Y26: - | Z26: - | AA26: - | AB26: - | AC26: - | AD26: - | AE26: - | AI26: FALSE | AJ26: FALSE | AK26: Open (Free) Access | AM26: - | AN26: - | AO26: - | AP26: - | AQ26: - | AR26: - | AS26: - | AT26: - | AU26: - | AV26: - | AW26: - | AX26: - | AY26: - | AZ26: - | BA26: On-street / nearby parking | BB26: BYO Picnic, Bench Seating, Dogs Allowed, Pushchair Friendly | BC26: Zip Line, "Swings, Slides, Climbing Frames", Outdoor play equipment | BD26: Clear Sightlines | BE26: Dogs On Leads, Poo Bins | BF26: FALSE | BG26: TRUE | BH26: TRUE | BI26: TRUE | BJ26: TRUE | BK26: FALSE | BL26: FALSE | BM26: Outside | BN26: Windy (> X mph), Sunshine, Overcast / cloudy, Dry & mild, Dry & cold, Dry & warm | BO26: Under 30mins, 30-60mins | BP26: RNLI, parks, zip lines, slides, balance elements, swings, accessible park, basketball courts, football goals | BS26: Climbing frames, Balance elements, Stepping obstacles, Towers and platforms, Slides, Fireman's poles, Zip wires, Fort-style structures, Mixed-difficulty zones, Enclosed adventure zones, Swings, Basket / nest swings, Log balance trail, Open grass / running space, Inclusive swings, Wheelchair accessible equipment | BU26: Brixington Park.jpg | BV26: Lois | BW26: VEN-00182 | BX26: CREATE | BY26: 46287.705 | BZ26: 1 | CA26: 1 | CC26: FALSE | CD26: FALSE
A27: venue | B27: Sporty Activities | C27: Outdoor Pitch | D27: Exe Footgolf | E27: Energy Burner | F27: Football golf — crazy golf-style fun but played with a football into oversized holes — on an 18-hole course open from Easter to the end of October half term. It takes around 90 minutes to play the full course and is something that can work well for all ages from around five upward given the two ball sizes that are available to use. The obstacles on the fairways add fun variety and the course itself has lovely views of the surrounding countryside; this combined with the stone-baked pizzas, burgers, hot dogs and pasties cater well for spectators, and there are soft drinks, ice creams and a licensed bar available too. Dogs are welcome on leads, and the course is accessible (it's grassy, so better suited to a XC buggy.) There isn't much shade, so that's worth bearing in mind on a hot, sunny day, there's very limited shelter, so it's almost definitely better as a dry-weather option. Advance booking isn't required, but it's recommended on busier days (holidays, weekends). | G27: Exmouth Road | H27: Exton | I27: Exeter | J27: EX3 0PU | K27: 50.665397 | L27: -3.4347296 | N27: Saturday | O27: TRUE | P27: 0.41666667 | Q27: 0.70833333 | R27: - | S27: - | T27: - | U27: - | V27: - | W27: - | X27: - | Y27: - | Z27: - | AA27: - | AB27: - | AC27: - | AD27: - | AE27: - | AF27: Seasonal - Open Easter to the Oct half term (24th Oct) | AH27: TRUE | AI27: TRUE | AJ27: TRUE | AK27: Advance Book, Pay On Arrival | AM27: - | AN27: - | AO27: 0-17 | AP27: 7 | AQ27: - | AR27: - | AS27: - | AT27: - | AU27: 18+ | AV27: 10 | AW27: - | AX27: - | AY27: - | AZ27: - | BA27: Free Car Park, Bike racks / bays | BB27: Toilets, BYO Picnic, Picnic Benches, Dogs Allowed, Outdoor Seating | BC27: Ice creams, Children's Menu, Outdoor play equipment | BD27: Snacks, Clear Sightlines, Hot & Cold food, Hot Drinks | BE27: Dogs On Leads | BF27: FALSE | BG27: FALSE | BH27: FALSE | BI27: TRUE | BJ27: TRUE | BK27: TRUE | BL27: TRUE | BM27: Outside | BN27: Sunshine, Overcast / cloudy, Dry & mild, Dry & cold, Dry & warm | BO27: 30-60mins, 1-2hrs | BP27: footgolf, football golf, adventure golf, competitive play, family competition, outdoor activity, countryside views, pizza | BS27: Early access introduction, Skill progression, Confidence building, Coordination & balance, Strength & agility, Friendly competition, Outdoor pitches, Ball Sports | BU27: Exe Footgolf.JPG | BV27: Lois | BW27: VEN-00168 | BX27: CREATE | BY27: 46287.695 | BZ27: 1 | CA27: 1 | CC27: FALSE | CD27: FALSE
A28: venue | B28: Cafés & Coffee Stops | C28: Cafés with Outdoor Space, Quiet Cafés, Library or Reading Nook | D28: Cuppa Cabin | E28: Simple Reset, Low Effort | F28: A genuinely one-of-a-kind café tucked within the Greenvalley Nursery site on the Exmouth Road at Ebford, made up of a cluster of themed sheds, summerhouses and outdoor spaces filled with books, plants, artwork, repurposed curiosities and things to look at around every corner. Children find it endlessly distracting in the best possible way! There's a dedicated kids' shed with drawing materials, fancy dress, puzzles and a second-hand book shelf to browse and browse and a visual richness that keeps younger children occupied while adults actually get to drink their coffee. The food is homemade and genuinely good — soups, pasties, cakes and brownies — with strong vegan, gluten-free and dairy-free options. The menu isn't extensive, but what's there is fresh and delicious. It's an unhurried, relaxed place with no rush-along feeling, which makes it useful for families who want a proper pause rather than a quick pit stop. Dogs are also welcome throughout, and with plenty of shade in the cabins, it makes for a lovely outing. | G28: Greenvalley Nursery | H28: Exmouth Road | I28: Ebford | J28: EX3 0GA | K28: 50.680998 | L28: -3.4446204 | N28: Tuesday, Wednesday, Thursday, Friday, Saturday | O28: TRUE | P28: 0.33333333 | Q28: 0.66666667 | R28: - | S28: - | T28: - | U28: - | V28: - | W28: - | X28: - | Y28: - | Z28: - | AA28: - | AB28: - | AC28: - | AD28: - | AE28: - | AF28: Seasonal opening | AH28: TRUE | AI28: FALSE | AJ28: FALSE | AK28: Open (Free) Access, Advance Book | AM28: - | AN28: - | AO28: - | AP28: - | AQ28: - | AR28: - | AS28: - | AT28: - | AU28: - | AV28: - | AW28: - | AX28: - | AY28: - | AZ28: - | BA28: Free Car Park | BB28: Toilets, Baby changing, Bench Seating, Indoor Seating, Dogs Allowed, Outdoor Seating, Pushchair Friendly | BC28: Colouring, Ice creams, "Indoor games (puzzles, boards)" | BD28: Hot Drinks, Comfy Seating / Sofas, Hot & Cold food, Snacks, Sweet treats, Outdoor terrace | BF28: TRUE | BG28: TRUE | BH28: TRUE | BI28: TRUE | BJ28: TRUE | BK28: TRUE | BL28: TRUE | BM28: Mixed | BN28: Raining / wet, Windy (> X mph), Sunshine, Overcast / cloudy, Dry & mild, Dry & cold, Dry & warm, Dry & hot | BO28: 30-60mins, 1-2hrs, Under 30mins | BP28: quirky café, themed sheds, drawing, browsing, second-hand books, homemade cakes, vegan options, gluten-free options, outdoor seating, dog friendly, workshops and events, nursery setting, countryside feel | BQ28: Summer | BS28: Toy corner or play table, Colouring, Book swap or exchange library | BU28: Cuppa Cabin.JPG | BV28: Lois | BW28: VEN-00169 | BX28: CREATE | BY28: 46287.687 | BZ28: 1 | CA28: 1 | CC28: FALSE | CD28: FALSE
A29: venue | B29: Coastal Adventures | C29: Sheltered Cove or Bay, Sandy Beach | D29: Anstey's Cove | E29: Under the Radar, Wilder Adventure | F29: Anstey’s Cove is a small, sheltered Torquay cove between the busier seafront and Babbacombe side, with shingle, clear water and a more tucked-away coastal feel. Reaching the beach involves steps, a slope and a steep route back from the car park, so the access will need to factor into the decision rather than being a simple background detail. Once there, the cove lends itself to paddling, sitting, watching the water and exploring a quieter pocket of the English Riviera, with the café nearby helping make the stop easier to stretch if you haven't come prepared. | G29: Antsy's Cove | H29: Anstey's Cove Road | I29: Torquay | J29: TQ1 2JE | K29: 50.470689 | L29: -3.5021286 | N29: Monday, Tuesday, Wednesday, Thursday, Friday, Saturday, Sunday | O29: TRUE | P29: 0 | Q29: 24:00 | R29: - | S29: - | T29: - | U29: - | V29: - | W29: - | X29: - | Y29: - | Z29: - | AA29: - | AB29: - | AC29: - | AD29: - | AE29: - | AF29: Open | AI29: FALSE | AJ29: FALSE | AK29: Open (Free) Access | AM29: - | AN29: - | AO29: - | AP29: - | AQ29: - | AR29: - | AS29: - | AT29: - | AU29: - | AV29: - | AW29: - | AX29: - | AY29: - | AZ29: - | BA29: Paid Car Park | BB29: BYO Picnic, Dogs Allowed | BD29: Drinks stand, Snacks, Hot Drinks | BF29: TRUE | BG29: TRUE | BH29: TRUE | BI29: TRUE | BJ29: TRUE | BK29: TRUE | BL29: TRUE | BM29: Outside | BN29: Sunshine, Dry & warm, Dry & hot, Dry & mild | BO29: 1-2hrs, 2-3hrs | BP29: rock pooling, swimming, snorkelling, coves & inlets, rock formations, cliffs & headlands, woodland walks, coastal wildlife, butterflies, coastal views, South West Coast Path, kayaking, paddleboarding, dog friendly | BS29: Rockpools, Shell or seaglass collecting, Crabbing, Coastal Wildlife, Dog Friendly - off lead all year | BT29: Sling / baby carrier, Infant / toddler carrier, Towels, Water shoes, Tide timetable, Buckets & nets, Snorkel & Mask, Wetsuit Boots, Fishing rods & bait | BU29: Antsys Cove.jpg | BV29: Gemma | BW29: VEN-00164 | BX29: CREATE | BY29: 46287.686 | BZ29: 1 | CA29: 1 | CC29: FALSE | CD29: FALSE
A30: venue | B30: Coastal Adventures | C30: Sandy Beach | D30: Mattiscombe Sands | E30: Energy Burner, Special Day Out, Wilder Adventure, Under the Radar | F30: A small, remote and genuinely beautiful sandy bay just south of Start Point in the South Hams, accessible via a 10–15 minute walk down a steep path from the Start Point car park. At low tide the beach opens out with fine sand, rock pools along the fringes, a small stream, boulders to climb and caves to explore. The water is clear and calm in settled weather, making it good for swimming and paddleboarding in summer, and seals are regularly spotted from the beach and nearby rocks. The sense of having found somewhere special makes the walk worthwhile, but the steep path and no-facilities situation means it's genuinely one for prepared families who are comfortable carrying what they need and setting up for the day, rather than spontaneous visits. Low tide significantly changes how much beach there is to use, and the coastal path setting gives older children more of a sense of discovery, making it a brilliant option for a slightly more varied and interesting beach trip. There are no lifeguards and there's no café at the beach so stock up on snacks - and while there are basic porta-cabin toilets at the car park, these close early so plan ahead. | G30: Mattiscombe Sands | H30: Stokenham | I30: Kingsbridge | J30: TQ7 2ET | K30: 50.22065 | L30: -3.6600211 | N30: Monday, Tuesday, Wednesday, Thursday, Friday, Saturday, Sunday | O30: TRUE | P30: 0 | Q30: 24:00 | R30: - | S30: - | T30: - | U30: - | V30: - | W30: - | X30: - | Y30: - | Z30: - | AA30: - | AB30: - | AC30: - | AD30: - | AE30: - | AF30: Open | AI30: FALSE | AJ30: FALSE | AK30: Open (Free) Access | AM30: - | AN30: - | AO30: - | AP30: - | AQ30: - | AR30: - | AS30: - | AT30: - | AU30: - | AV30: - | AW30: - | AX30: - | AY30: - | AZ30: - | BA30: Paid Car Park | BB30: Dogs Allowed, BYO Picnic | BF30: TRUE | BG30: TRUE | BH30: TRUE | BI30: TRUE | BJ30: TRUE | BK30: TRUE | BL30: TRUE | BM30: Outside | BN30: Sunshine, Dry & warm, Dry & hot, Dry & mild | BO30: 1-2hrs, 2-3hrs, 4+ hours | BP30: sandy beach, rock pooling, caves, boulders, scrambling, stream, swimming, paddleboarding, seal spotting, coastal walking, South West Coast Path, Start Point, Jurassic Coast, dog friendly, seals, metal detecting, sandy beach, rocks to climb | BQ30: Summer | BS30: Rockpools, Diggable sand (Sandcastles), Streams or channels, Coastal Wildlife, Kayaking / SUP, Bodyboarding, Swimming, Dog Friendly - off lead all year | BT30: Sturdy footwear, Infant / toddler carrier, Sling / baby carrier, Towels, Water shoes, Beach toys, Sand toys, Tide timetable, Buckets & nets | BU30: Mattiscombe Sands.jpeg | BV30: Gemma | BW30: VEN-00162 | BX30: CREATE | BY30: 46287.674 | BZ30: 1 | CA30: 1 | CC30: FALSE | CD30: FALSE
A31: venue | B31: Indoor Entertainment | C31: Laser Tag | D31: Tenpin Laser Tag | E31: Energy Burner | F31: Tenpin Laser Tag is a great activity choice when children are too old for soft play but still need to move and want something exciting to perk up a wet or dreary day. It’s a small indoor arena with LED lighting, sound effects, a smoke machine and infrared guns, so expect noise, a dark maze-feel, running about and a bit of competitive chaos. Brilliant fun for kids that love playing team based games, or in small group (min 2 people) and want to play 1:1. One to avoid for children who dislike dark, loud or high-energy spaces, and is worth check booking slots before heading over during peak party season, but there's lots to keep everyone occupied if it's a spontaneous trip and you need to wait for another booking to finish; bookings are usually 30mins long and a small discount is applied if you book for 2 x 30mins. There isn't an age limit as such, it's based on height; children need to be over 4ft (120cm) to play. | G31: 3 - 4 Havenbanks Retail Park | H31: Water Lane | I31: Exeter | J31: EX2 8BY | K31: 50.71621 | L31: -3.5310634 | N31: Monday, Tuesday, Wednesday, Thursday, Friday, Saturday, Sunday | O31: FALSE | P31: - | Q31: - | R31: 0.41666667 | S31: 24:00 | T31: 0.41666667 | U31: 24:00 | V31: 0.41666667 | W31: 24:00 | X31: 0.41666667 | Y31: 24:00 | Z31: 0.41666667 | AA31: 0.041666667 | AB31: 0.41666667 | AC31: 0.041666667 | AD31: 0.41666667 | AE31: 24:00 | AF31: - | AI31: TRUE | AJ31: TRUE | AK31: Advance Book, Pay On Arrival | AL31: (Fixed) Child | AM31: - | AN31: - | AO31: 7-16 | AP31: 6 | AQ31: - | AR31: - | AS31: - | AT31: - | AU31: - | AV31: - | AW31: - | AX31: - | AY31: - | AZ31: - | BA31: Paid Car Park, Disabled parking bays | BB31: Toilets, Disabled toilets, Indoor Seating, Pushchair Friendly | BC31: Ice creams, Clues / games, Children's Menu, "Swings, Slides, Climbing Frames" | BD31: Hot Drinks, Clear Sightlines, Hot & Cold food, Snacks, Sweet treats, WiFi | BF31: FALSE | BG31: FALSE | BH31: FALSE | BI31: FALSE | BJ31: TRUE | BK31: TRUE | BL31: FALSE | BM31: Inside | BN31: Raining / wet, Windy (> X mph), Snow / sleet / ice, Overcast / cloudy, Stormy / heavy rain / thunderstorms, Dry & cold | BO31: Under 30mins, 30-60mins | BP31: laser tag, flashing lights, smoke machine, hunter games, team games, laser tag, team battles, multi-player arena | BS31: Laser tag, Bar / licensed venue, Café or restaurant, Immersive experience | BU31: Tenpin Laser Tag.JPG | BV31: Lois | BW31: VEN-00152 | BX31: CREATE | BY31: 46287.666 | BZ31: 1 | CA31: 1 | CC31: FALSE | CD31: FALSE
A32: venue | B32: Indoor Entertainment | C32: Bowling | D32: Tenpin Bowling | E32: Simple Reset | F32: Tenpin Bowling is a safe bet at Marsh Barton when you need an indoor activity that mixed ages can all do together. It gives enough structure to fill a rainy afternoon, birthday meet-up or post-school treat, without needing everyone to have the same skill level. Younger children can usually join in with lighter balls and help from adults, while older ones get the competition. There are 15+ lanes, so although it's worth calling ahead if you have specific timings in mind, it's unlikely to be a frustrating wait as the arcade/food setup means you can stretch the visit if people are still going or need to kill some time before a lane becomes available. | G32: 3 - 4 Havenbanks Retail Park | H32: Water Lane | I32: Exeter | J32: EX2 8BY | K32: 50.71621 | L32: -3.5310634 | N32: Monday, Tuesday, Wednesday, Thursday, Friday, Saturday, Sunday | O32: FALSE | P32: - | Q32: - | R32: 0.41666667 | S32: 24:00 | T32: 0.41666667 | U32: 24:00 | V32: 0.41666667 | W32: 24:00 | X32: 0.41666667 | Y32: 24:00 | Z32: 0.41666667 | AA32: 0.041666667 | AB32: 0.41666667 | AC32: 0.041666667 | AD32: 0.41666667 | AE32: 24:00 | AF32: - | AI32: TRUE | AJ32: FALSE | AK32: Advance Book, Pay On Arrival | AL32: Adult, (Fixed) Child | AM32: - | AN32: - | AO32: 0-15 | AP32: 8.5 | AQ32: - | AR32: - | AS32: - | AT32: - | AU32: 16+ | AV32: 9.95 | AW32: - | AX32: - | AY32: - | AZ32: - | BA32: Paid Car Park, Disabled parking bays | BB32: Toilets, Disabled toilets, Indoor Seating | BC32: Ice creams, Clues / games, Children's Menu | BD32: Hot Drinks, Clear Sightlines, Hot & Cold food, Snacks, Sweet treats, WiFi | BF32: FALSE | BG32: FALSE | BH32: FALSE | BI32: TRUE | BJ32: TRUE | BK32: TRUE | BL32: TRUE | BM32: Inside | BN32: Raining / wet, Windy (> X mph), Snow / sleet / ice, Overcast / cloudy, Stormy / heavy rain / thunderstorms, Dry & cold | BO32: 30-60mins, 1-2hrs | BP32: bowling, team games, ten-pin bowling, lane bumpers, bowling ramps | BS32: Bowling lanes, Bar / licensed venue, Private hire / party packages | BU32: Tenpin Bowling.JPG | BV32: Lois | BW32: VEN-00127 | BX32: UPDATE | BY32: 46287.666 | CA32: 2 | CC32: FALSE | CD32: FALSE
A33: venue | B33: Water Activities | C33: River Beach, Paddle Spot | D33: Cherry Brook River Beach | E33: Simple Reset, Under the Radar | F33: Cherry Brook is a wilder Dartmoor river spot with plenty of stretches of shallow water right alongside the open moorland. It is a beautiful spot for a picnic, or a quiet paddle, and being one of the lesser known spots it's rarely crowded. It's informal, slightly uneven grass and much more rustic than many river spots, but with Dartmoor ponies often grazing nearby, and access to the Bellever circular route from the car park, it can work well as a quick stop at the end of a walk, or as a visit in its own right if you're looking for somewhere to cool off. With hard-standing parking directly across the road, it doesn't feel like a big effort to stop and enjoy a break by the stream, and the slower, shallow water in summer months means it's well suited to smaller children and inexperienced river waders! It's worth noting that there isn't much shade, so do plan ahead in the heat. | G33: Lower Cherrybrook Bridge | I33: Yelverton | J33: PL20 6SA | K33: 50.557138 | L33: -3.9335283 | N33: Monday, Tuesday, Wednesday, Thursday, Friday, Saturday, Sunday | O33: TRUE | P33: 0 | Q33: 24:00 | R33: - | S33: - | T33: - | U33: - | V33: - | W33: - | X33: - | Y33: - | Z33: - | AA33: - | AB33: - | AC33: - | AD33: - | AE33: - | AF33: Open | AI33: FALSE | AJ33: FALSE | AK33: Open (Free) Access | AM33: - | AN33: - | AO33: - | AP33: - | AQ33: - | AR33: - | AS33: - | AT33: - | AU33: - | AV33: - | AW33: - | AX33: - | AY33: - | AZ33: - | BA33: Free Car Park | BB33: BYO Picnic, Dogs Allowed | BF33: FALSE | BG33: TRUE | BH33: TRUE | BI33: TRUE | BJ33: TRUE | BK33: TRUE | BL33: TRUE | BM33: Outside | BN33: Sunshine, Dry & warm, Dry & hot, Dry & mild | BO33: 30-60mins, 1-2hrs | BP33: swimming, river beach, ponies, Dartmoor views, paddling, picnic spot | BQ33: Summer | BR33: Dragonflies & Damselflies, Autumn Leaves, Seasonal water fun, River wildlife spotting, Kingfisher Spotting, Butterflies | BS33: Shallow water, Natural Swimming Spots, Splash-friendly areas, Wildlife spotting, River Beach, Rivers or estuaries, National Park, Paddling spots | BT33: Water shoes, Towels | BU33: Cherry Brook River.JPG | BV33: Lois | BW33: VEN-00150 | BX33: CREATE | BY33: 46287.611 | BZ33: 1 | CA33: 1 | CC33: FALSE | CD33: FALSE

Sheet Old Events
A1: Essential Info | E1: Event Descriptors | H1: Event Venue | P1: Scheduling | V1: Single-Day (one session) Event Schedule | X1: Single-Day (multi-session) Event Schedule | Z1: Multi-Day Event With Fixed Daily Times Schedule | AB1: Multi-Day Event With Mixed Daily Times | AP1: Event Ticketing Types, Dates & Costs | BH1: Facilities | BM1: Age Suitability | BT1: Useful Info | BV1: Additional Details | CA1: Skill Requirements | CH1: Admin Panel
AP2: Ticket Requirements + Types | AT2: Baby Tickets | AV2: Child Tickets | AX2: Young Child Tickets | AZ2: Older Child Tickets | BB2: Adult Tickets | BD2: Concession Tickets | BF2: Group Tickets
A3: Opportunity Type | B3: Event Setting | C3: Opportunity Theme Variant | D3: Event Name | E3: How would you group it? | F3: Event Type | G3: Description | H3: Address | I3: Address line 2 | J3: City/Town | K3: State/Region/Province | L3: Postcode | M3: Country | N3: Latitude | O3: Longitude | P3: Event Start Date | Q3: Event End Date | R3: Event Days Total | S3: Are there Multiple Sessions in one day? | T3: Event Schedule Pattern (Which days of the week will the event be running?) | U3: Are there fixed timings that are the same each day? | V3: Daily Start Time | W3: Daily Finish Time | X3: Total number of sessions within the day | Y3: Times of those multi-sessions | Z3: Daily Timings Start Time | AA3: Daily Timings End Time | AB3: Monday Start Time | AC3: Monday End Time | AD3: Tuesday Start Time | AE3: Tuesday End Time | AF3: Wednesday Start Time | AG3: Wednesday End Time | AH3: Thursday Start Time | AI3: Thursday End Time | AJ3: Friday Start Time | AK3: Friday End Time | AL3: Saturday Start Time | AM3: Saturday End Time | AN3: Sunday Start Time | AO3: Sunday End Time | AP3: Ticket Sales Start Date | AQ3: Is there an Entry Cost? | AR3: Booking Types | AS3: Ticketing Types | AT3: Baby Ticket Age Range | AU3: Baby Ticket Price | AV3: Fixed Child Ticket Age Range | AW3: Fixed Child Ticket Price | AX3: Young Child Ticket Age Range | AY3: Young Child Ticket Price | AZ3: Older Child Ticket Age Range | BA3: Older Child Ticket Price | BB3: Adult Ticket Age Range | BC3: Adult Ticket Price | BD3: Concession Ticket Age Range | BE3: Concession Ticket Price | BF3: Group Ticket Definition | BG3: Group Ticket Price | BH3: Parking Provision | BI3: General Facilities | BJ3: Kids Facilities | BK3: Parent Facilities | BL3: Dog Facilities | BM3: <1s | BN3: 1-2yrs | BO3: 3-4yrs | BP3: 5-7yrs | BQ3: 8-12yrs | BR3: 13+yrs | BS3: Adults | BT3: Inside or Outside | BU3: Weather Suitability | BV3: Interest Tags | BW3: Seasonal Tag | BX3: Seasonal Highlights | BY3: Highlights (Attractions) | BZ3: Extra Kit | CA3: Skill Area | CB3: Skill Area Variant | CC3: Ability Level | CD3: Image Name | CE3: Photo Contributor | CF3: Partner Code | CG3: Regular Timetabled Event | CH3: Record ID | CI3: Developer Action | CJ3: Added to Queue | CK3: Proposed Version | CL3: Change Summary | CM3: AWS Action Complete? | CN3: Return to WORKING? | CO3: Cancel Removal?
A4: opportunity_type | B4: event_opportunity_theme | C4: event_opportunity_theme_variant | D4: event_name | E4: event_activity_group | F4: event_type | G4: event_description | H4: event_address_line_1 | I4: event_address_line_2 | J4: event_city | K4: event_region | L4: event_postcode | M4: event_country | N4: latitude | O4: longitude | P4: event_start_date | Q4: event_end_date | R4: event_days_total | S4: event_daily_multi_session | T4: event_timetable_weekly | U4: event_daily_fixed_timings | V4: event_daily_fixed_start_time | W4: event_daily_fixed_end_time | X4: event_daily_multi_session_total | Y4: event_daily_multi_session_timings | Z4: event_weekly_fixed_start_time | AA4: event_weekly_fixed_end_time | AB4: event_mixed_timings_monday_start_time | AC4: event_mixed_timings_monday_end_time | AD4: event_mixed_timings_tuesday_start_time | AE4: event_mixed_timings_tuesday_end_time | AF4: event_mixed_timings_wednesday_start_time | AG4: event_mixed_timings_wednesday_end_time | AH4: event_mixed_timings_thursday_start_time | AI4: event_mixed_timings_thursday_end_time | AJ4: event_mixed_timings_friday_start_time | AK4: event_mixed_timings_friday_end_time | AL4: event_mixed_timings_saturday_start_time | AM4: event_mixed_timings_saturday_end_time | AN4: event_mixed_timings_sunday_start_time | AO4: event_mixed_timings_sunday_end_time | AP4: ticket_sales_start_date | AQ4: event_entry_cost | AR4: event_booking_type | AS4: ticketing_variants | AT4: ticket_variant_definition_baby | AU4: ticket_variant_baby_price | AV4: ticket_variant_definition_fixed_child | AW4: ticket_variant_fixed_child_price | AX4: ticket_variant_definition_young_child | AY4: ticket_variant_young_child_price | AZ4: ticket_variant_definition_older_child | BA4: ticket_variant_older_child_price | BB4: ticket_variant_definition_adult | BC4: ticket_variant_adult_price | BD4: ticket_variant_definition_concession | BE4: ticket_variant_concession_price | BF4: ticket_variant_definition_group | BG4: ticket_variant_group_price | BH4: event_parking_provision | BI4: event_general_facilities | BJ4: event_child_facilities | BK4: event_adult_facilities | BL4: event_dog_facilities | BM4: event_age_suitability_under_1_s | BN4: event_age_suitability_1_to_2_years | BO4: event_age_suitability_3_to_4_years | BP4: event_age_suitability_5_to_7_years | BQ4: event_age_suitability_8_to_12_years | BR4: event_age_suitability_over_13_years | BS4: event_age_suitability_adults | BT4: event_physical_setting | BU4: event_detailed_weather_suitability | BV4: event_interest_tags | BW4: event_seasonal_tags | BX4: event_seasonal_highlights | BY4: event_highlights | BZ4: event_extra_kit | CA4: event_skill_area | CB4: event_skill_area_variant | CC4: event_ability_level | CD4: image | CE4: contributor_first_name | CF4: partner_code | CG4: regular_timetabled | CH4: record_id | CI4: developer_action | CJ4: added_to_queue_at | CK4: queued_version | CL4: change_summary | CM4: actioned_in_aws | CN4: return_to_working | CO4: cancel_removal
A5: event | B5: Seasonal | C5: Patch or Field | D5: Greendale Pumpkin Patch | E5: Special Day Out | F5: PYO, Themed | G5: Greendale’s Pumpkin Patch turns the farm shop into a seasonal autumn stop, with pumpkins to choose, photo spots around the patch and the wider Greendale site close by for food, animals and the Farm Trail. The pumpkin picking itself is simple and open-ended: visitors can wander, compare shapes and sizes, choose one to take home and make the visit feel part of the build-up to Halloween rather than a big-ticket day out. Unlike some pumpkin experiences that charge for every element, this one is genuinely free to walk around — you choose your pumpkin and pay only for what you take home and the pricing is clear and upfront. The free Pumpkin Trail adds a second layer, with clue sheets from Oscar’s and pumpkins hidden around the Farm Trail and Farm Shop, ending with a sweet treat once the challenge is complete. Entry to the pumpkin patch is free and works really well alongside a wander around to look at the animal pens. | H5: Sidmouth Road | I5: Farringdon | J5: Exeter | L5: EX5 2JU | N5: 50.70417 | O5: -3.3986618 | P5: 46306 | Q5: 46327 | S5: - | T5: Monday, Tuesday, Wednesday, Thursday, Friday, Saturday, Sunday | U5: TRUE | V5: 0.33333333 | W5: 0.83333333 | AB5: - | AC5: - | AD5: - | AE5: - | AF5: - | AG5: - | AH5: - | AI5: - | AJ5: - | AK5: - | AL5: - | AM5: - | AN5: - | AO5: - | AP5: 46294 | AQ5: FALSE | AR5: FALSE | AS5: Open (Free) Access | AT5: - | AU5: - | AV5: - | AW5: - | AX5: - | AY5: - | AZ5: - | BA5: - | BB5: - | BC5: - | BD5: - | BE5: - | BF5: - | BG5: - | BH5: Free Car Park | BI5: Toilets, Disabled toilets, Baby changing, Picnic Benches, BYO Picnic, Buggy Friendly, Indoor Seating, Dogs Allowed, Outdoor Seating | BJ5: Activity Sheets or Signs, "Swings, Slides, Climbing Frames", Outdoor play equipment, Children's Menu, Children’s trail, Colouring | BK5: Hot Drinks, Hot & Cold food, Clear Sightlines, Snacks, Sweet treats, Giftshop, Outdoor terrace | BM5: TRUE | BN5: TRUE | BO5: TRUE | BP5: TRUE | BQ5: TRUE | BR5: TRUE | BS5: TRUE | BT5: Outside | BU5: Sunshine, Overcast / cloudy, Dry & warm, Dry & hot, Dry & mild | BV5: Pumpkin picking, Pumpkin patch, Halloween, Autumn, Seasonal event, Photo opportunities, Pumpkin trail, Clue sheets, Farm trails, Farm animals, Animal spotting, Sweet treat, Family challenge, Outdoor exploring, Farm shop, Farm café, Local produce, Halloween treats, Autumn food | BW5: Halloween, Autumn | BX5: Pumpkin Patch | BY5: Festive Displays, Themed Food, Seasonal Hot Chocolates | BZ5: Wellies | CD5: Greendale Pumpkin Patch.JPG | CE5: Lois | CH5: EVT-00041 | CI5: CREATE | CJ5: 46294.549 | CK5: 1 | CM5: FALSE | CN5: FALSE
A6: event | B6: Seasonal | C6: PYO Farm | D6: Amelia's Flowers | E6: Moment of Peace | F6: Nature-based | G6: Run by Amelia and Giles, who are raising their own three children on the farm, there's a relaxed and genuinely welcoming atmosphere here that's hard to manufacture and easy to feel the moment you arrive. The farm sits in a quiet valley between Newton Abbot and Shaldon, with fields of pesticide-free heirloom flowers — dahlias, sweet peas, sunflowers and scented varieties that change through the season — grown slowly and available to pick at your own pace with a pair of snips. Children who are unmoved by the flowers tend to find their own reasons to stay: miniature ponies, pigs (including the much-loved Cris-P-Bacon), swings that even pre-teens apparently can't resist, and the simple freedom of roaming a working farm without a fixed route. The Flower Barn café does homemade cakes and good coffee with views across the fields, and a short walk through the farm brings you down to the River Teign if legs need stretching further. | H6: Amelias Flower Farm, | I6: Combeinteignhead | J6: Newton Abbot | K6: Devon | L6: TQ12 4RG | N6: 50.535436 | O6: -3.5589237 | P6: 46165 | Q6: 46326 | S6: - | T6: Monday, Tuesday, Wednesday, Thursday, Friday, Sunday, Saturday | U6: TRUE | V6: 0.41666667 | W6: 0.66666667 | AB6: - | AC6: - | AD6: - | AE6: - | AF6: - | AG6: - | AH6: - | AI6: - | AJ6: - | AK6: - | AL6: - | AM6: - | AN6: - | AO6: - | AP6: 46165 | AQ6: TRUE | AR6: FALSE | AS6: Pay On Arrival | AT6: - | AU6: - | AV6: - | AW6: - | AX6: - | AY6: - | AZ6: 12-16 | BA6: 25 | BB6: 16+ | BC6: 25 | BD6: - | BE6: - | BF6: - | BG6: - | BH6: Free Car Park, Bike racks / bays, Horse “parking” | BI6: Toilets, Disabled toilets, Baby changing, Indoor Seating, Dogs Allowed, Outdoor Seating | BJ6: Colouring, Ice creams, Rope Swings, Ride on Vehicles, "Swings, Slides, Climbing Frames", Outdoor play equipment | BK6: Hot Drinks, Comfy Seating / Sofas, Snacks, Sweet treats, Giftshop | BM6: FALSE | BN6: FALSE | BO6: TRUE | BP6: TRUE | BQ6: TRUE | BR6: TRUE | BS6: TRUE | BT6: Outside | BU6: Windy (> X mph), Sunshine, Overcast / cloudy, Dry & mild, Dry & cold, Dry & warm | BV6: Flower picking, Pick your own, Cut flower farm, Seasonal flowers, Heirloom flowers, Scented flowers, Unusual flowers, Colour, Nature, Gardening, Plant nursery, Flower arranging, Outdoor creativity, Hands-on activity, Slow exploring, Sensory nature, Countryside, River Teign, Local produce, Sustainable growing, Pesticide-free growing, Chemical-free growing, Workshops, Educational talks, Group visits, School visits, South Devon | BW6: Summer | BX6: PYO Flowers, Wildflower Meadows, Butterflies | BY6: Flower collecting or displays, Wildlife Spotting | BZ6: XC Buggy, Sling / baby carrier, Infant / toddler carrier | CD6: Amelias Flower Farm PYO.JPEG | CE6: Lois | CH6: EVT-00039 | CI6: CREATE | CJ6: 46294.515 | CK6: 1 | CM6: FALSE | CN6: FALSE
CG7: FALSE

Sheet Events
A1: Essential Info | E1: Event Descriptors | H1: Event Venue Details | P1: Weather-Related Context | R1: Event Scheduling (Timings, Sessions) | AV1: Event Ticketing Types, Dates & Costs | BO1: Facilities | BS1: Age Suitability | BZ1: Additional Details | CE1: Skill Requirements | CI1: Image | CM1: Admin Panel
R2: Event Dates | V2: Event Days | X2: Same timings every day | Z2: Event Timings Each Day | AN2: Multi-Sessions | AO2: Daily Session Times | AV2: Ticket Requirements + Types | BA2: Baby Tickets | BC2: Child Tickets | BE2: Young Child Tickets | BG2: Older Child Tickets | BI2: Adult Tickets | BK2: Concession Tickets | BM2: Group Tickets
A3: Opportunity Type | B3: Event Setting | C3: Opportunity Theme Variant | D3: Event Name | E3: How would you group it? | F3: Event Type | G3: Description | H3: Address | I3: Address line 2 | J3: City/Town | K3: State/Region/Province | L3: Postcode | M3: Country | N3: Latitude | O3: Longitude | P3: Inside or Outside | Q3: Weather Suitability | R3: Multi-Day Event? | S3: Event Start Date | T3: Event End Date | U3: Event Days Total | V3: Which day/s of the week does it fall on? | W3: Does the event start / end at the same time across each day? | X3: What time does it start? | Y3: What time does it end? | Z3: Monday Start Time | AA3: Monday End Time | AB3: Tuesday Start Time | AC3: Tuesday End Time | AD3: Wednesday Start Time | AE3: Wednesday End Time | AF3: Thursday Start Time | AG3: Thursday End Time | AH3: Friday Start Time | AI3: Friday End Time | AJ3: Saturday Start Time | AK3: Saturday End Time | AL3: Sunday Start Time | AM3: Sunday End Time | AN3: Are there multiple bookable sessions throughout the day? | AO3: Monday Session Times | AP3: Tuesday Session Times | AQ3: Wednesday Session Times | AR3: Thursday Session Times | AS3: Friday Session Times | AT3: Saturday Session Times | AU3: Sunday Session Times | AV3: Ticket Sales Start Date | AW3: Is there an Entry Cost? | AX3: Ticketing Requirement | AY3: Booking Types | AZ3: Ticket Types | BA3: Baby Ticket Age Range | BB3: Price | BC3: Fixed Child Ticket Age Range | BD3: Price | BE3: Young Child Ticket Age Range | BF3: Price | BG3: Older Child Ticket Age Range | BH3: Price | BI3: Adult Ticket Age Range | BJ3: Price | BK3: Concession Ticket Age Range | BL3: Price | BM3: Group Ticket Definition | BN3: Price | BO3: Parking Provision | BP3: General Facilities | BQ3: Kids Facilities | BR3: Parent Facilities | BS3: <1s | BT3: 1-2yrs | BU3: 3-4yrs | BV3: 5-7yrs | BW3: 8-12yrs | BX3: 13+yrs | BY3: Adults | BZ3: Interest Tags | CA3: Seasonal Tag | CB3: Seasonal Highlights | CC3: Highlights (Attractions) | CD3: Extra Kit | CE3: Are there any specific skills needed to participate fully? | CF3: Skill Area | CG3: Skill Area Variant | CH3: Ability Level | CI3: Image Name | CJ3: Photo Contributor | CK3: Partner Code | CL3: Regular Timetabled Event | CM3: Record ID | CN3: Developer Action | CO3: Added to Queue | CP3: Upload Batch No. | CQ3: Proposed Version | CR3: Change Summary | CS3: AWS Action Complete? | CT3: Return to WORKING? | CU3: Cancel Removal?
A4: opportunity_type | B4: event_opportunity_theme | C4: event_opportunity_theme_variant | D4: event_name | E4: event_activity_group | F4: event_type | G4: event_description | H4: event_address_line_1 | I4: event_address_line_2 | J4: event_city | K4: event_region | L4: event_postcode | M4: event_country | N4: latitude | O4: longitude | P4: event_physical_setting | Q4: event_detailed_weather_suitability | R4: event_multiple_days_confirmed | S4: event_start_date | T4: event_end_date | U4: event_days_total | V4: event_timetable_weekly | W4: event_daily_fixed_timings | X4: event_daily_fixed_start_time | Y4: event_daily_fixed_end_time | Z4: event_mixed_timings_monday_start_time | AA4: event_mixed_timings_monday_end_time | AB4: event_mixed_timings_tuesday_start_time | AC4: event_mixed_timings_tuesday_end_time | AD4: event_mixed_timings_wednesday_start_time | AE4: event_mixed_timings_wednesday_end_time | AF4: event_mixed_timings_thursday_start_time | AG4: event_mixed_timings_thursday_end_time | AH4: event_mixed_timings_friday_start_time | AI4: event_mixed_timings_friday_end_time | AJ4: event_mixed_timings_saturday_start_time | AK4: event_mixed_timings_saturday_end_time | AL4: event_mixed_timings_sunday_start_time | AM4: event_mixed_timings_sunday_end_time | AN4: event_daily_multi_session | AO4: event_monday_session_timings | AP4: event_tuesday_session_timings | AQ4: event_wednesday_session_timings | AR4: event_thursday_session_timings | AS4: event_friday_session_timings | AT4: event_saturday_session_timings | AU4: event_sunday_session_timings | AV4: ticket_sales_start_date | AW4: event_entry_cost | AX4: ticketing_requirement | AY4: event_booking_type | AZ4: ticketing_variants | BA4: ticket_variant_definition_baby | BB4: ticket_variant_baby_price | BC4: ticket_variant_definition_fixed_child | BD4: ticket_variant_fixed_child_price | BE4: ticket_variant_definition_young_child | BF4: ticket_variant_young_child_price | BG4: ticket_variant_definition_older_child | BH4: ticket_variant_older_child_price | BI4: ticket_variant_definition_adult | BJ4: ticket_variant_adult_price | BK4: ticket_variant_definition_concession | BL4: ticket_variant_concession_price | BM4: ticket_variant_definition_group | BN4: ticket_variant_group_price | BO4: event_parking_provision | BP4: event_general_facilities | BQ4: event_child_facilities | BR4: event_adult_facilities | BS4: event_age_suitability_under_1_s | BT4: event_age_suitability_1_to_2_years | BU4: event_age_suitability_3_to_4_years | BV4: event_age_suitability_5_to_7_years | BW4: event_age_suitability_8_to_12_years | BX4: event_age_suitability_over_13_years | BY4: event_age_suitability_adults | BZ4: event_interest_tags | CA4: event_seasonal_tags | CB4: event_seasonal_highlights | CC4: event_highlights | CD4: event_extra_kit | CE4: event_skill_requirement | CF4: event_skill_area | CG4: event_skill_area_variant | CH4: event_ability_level | CI4: image | CJ4: contributor_first_name | CK4: partner_code | CL4: regular_timetabled | CM4: record_id | CN4: developer_action | CO4: added_to_queue_at | CP4: admin_version | CQ4: queued_version | CR4: change_summary | CS4: actioned_in_aws | CT4: return_to_working | CU4: cancel_removal
A5: event | B5: Seasonal | C5: Patch or Field | D5: Darts Farm Pumpkin Fest - Half Term Fun | E5: Special Day Out | F5: Themed | G5: Every October, Darts Farm transforms into something quite different from its usual self — tens of thousands of homegrown pumpkins filling the fields in every shape, size and shade of orange imaginable, with enough going on around them to make a proper afternoon of it. Magic shows, game shows, live music, roaming performers, marshmallow toasting, face painting and s’mores are all part of the mix, with the farm’s natural backdrop doing a lot of the atmospheric heavy lifting. They do go all out, and it certainly provides the pumpkin-patch fix most families are looking for - with the world's 3rd biggest pumpkin in residence no less! With the usual Darts playarea directly opposite, and all the amenities of the farm shop and cafes, and quick access to the Exe Estuary trail for a walk, it's a classic take on a Pumpkin Patch but with lots you can add on easily. Like most pumpkin patches, the ticket price covers entry but not the pumpkin itself, which you choose and pay for separately on the day; some activities carry an additional charge and tend to sit at a price point similar to others (the standard eye-watering extras, but hard to avoid when they're placed under children's noses). The farm runs on booked arrival slots throughout October, with the busiest dates around half term selling out well in advance — worth getting tickets sorted early if you have a specific weekend in mind. | H5: Darts Farm Shopping Village | I5: Topsham | J5: Clyst St George | K5: Devon | L5: EX3 0QH | N5: 50.685768 | O5: -3.4490059 | P5: Outside | Q5: Windy (> X mph), Sunshine, Overcast / cloudy, Dry & mild, Dry & cold, Dry & warm, Dry & hot | R5: TRUE | S5: 46321 | T5: 46326 | U5: 6 | V5: Monday, Tuesday, Wednesday, Thursday, Friday, Saturday | W5: TRUE | X5: 0.41666667 | Y5: 0.6875 | Z5: - | AA5: - | AB5: - | AC5: - | AD5: - | AE5: - | AF5: - | AG5: - | AH5: - | AI5: - | AJ5: - | AK5: - | AL5: - | AM5: - | AN5: TRUE | AV5: 46310 | AW5: TRUE | AX5: TRUE | AY5: Advance Book | AZ5: Baby, (Fixed) Child, Adult | BA5: 0-0.9 | BB5: 0 | BC5: 1-15 | BD5: 5 | BE5: - | BF5: - | BG5: - | BH5: - | BI5: 16+ | BJ5: 5 | BK5: - | BL5: - | BM5: - | BN5: - | BO5: Free Car Park | BP5: Toilets, Disabled toilets, Baby changing, Bench Seating, Picnic Benches, BYO Picnic, Buggy Friendly, Dogs Allowed, Outdoor Seating, Water Refill | BQ5: Ice creams, Activity trail, Children’s trail, "Swings, Slides, Climbing Frames", Outdoor play equipment | BR5: Hot Drinks, Snacks, Drinks stand, Sweet treats | BS5: TRUE | BT5: TRUE | BU5: TRUE | BV5: TRUE | BW5: TRUE | BX5: TRUE | BY5: TRUE | BZ5: Pumpkin picking, Pumpkin patch, Halloween, Autumn festival, Seasonal event, Giant pumpkins, Pumpkin displays, Magic shows, Game shows, Live music, Roaming entertainers, Marshmallow toasting, S'mores, Face painting, Family entertainment, Pumpkin photography, Outdoor festival, Street food, Sweet treats, Darts Farm, Topsham | CA5: Autumn, Halloween | CB5: Pumpkin Patch, Autumnal Drinks, Festive Displays | CC5: Seasonal Hot Chocolates, Festive Displays, Themed Food, Themed Areas, Roasting Marshmallows | CD5: Cashless - bring a bank card, XC Buggy, Wellies | CE5: FALSE | CI5: Darts Farm Pumpkins.JPG | CJ5: Lois | CM5: EVT-00063 | CN5: CREATE | CO5: 46311.426 | CP5: 1 | CQ5: 1 | CS5: FALSE | CT5: FALSE
A6: event | B6: Seasonal | C6: Patch or Field | D6: Darts Farm Pumpkin Fest - Weekend | E6: Special Day Out | F6: Themed | G6: Every October, Darts Farm transforms into something quite different from its usual self — tens of thousands of homegrown pumpkins filling the fields in every shape, size and shade of orange imaginable, with enough going on around them to make a proper afternoon of it. Magic shows, game shows, live music, roaming performers, marshmallow toasting, face painting and s’mores are all part of the mix, with the farm’s natural backdrop doing a lot of the atmospheric heavy lifting. They do go all out, and it certainly provides the pumpkin-patch fix most families are looking for - with the world's 3rd biggest pumpkin in residence no less! With the usual Darts playarea directly opposite, and all the amenities of the farm shop and cafes, and quick access to the Exe Estuary trail for a walk, it's a classic take on a Pumpkin Patch but with lots you can add on easily. Like most pumpkin patches, the ticket price covers entry but not the pumpkin itself, which you choose and pay for separately on the day; some activities carry an additional charge and tend to sit at a price point similar to others (the standard eye-watering extras, but hard to avoid when they're placed under children's noses). The farm runs on booked arrival slots throughout October, with the busiest dates around half term selling out well in advance — worth getting tickets sorted early if you have a specific weekend in mind. | H6: Darts Farm Shopping Village | I6: Topsham | J6: Clyst St George | K6: Devon | L6: EX3 0QH | N6: 50.685768 | O6: -3.4490059 | P6: Outside | Q6: Windy (> X mph), Sunshine, Overcast / cloudy, Dry & mild, Dry & cold, Dry & warm, Dry & hot | R6: TRUE | S6: 46305 | T6: 46320 | U6: 6 | V6: Saturday, Sunday | W6: TRUE | X6: 0.41666667 | Y6: 0.6875 | Z6: - | AA6: - | AB6: - | AC6: - | AD6: - | AE6: - | AF6: - | AG6: - | AH6: - | AI6: - | AJ6: - | AK6: - | AL6: - | AM6: - | AN6: TRUE | AV6: 46310 | AW6: TRUE | AX6: TRUE | AY6: Advance Book | AZ6: Baby, (Fixed) Child, Adult | BA6: 0-0.9 | BB6: 0 | BC6: 1-15 | BD6: 5 | BE6: - | BF6: - | BG6: - | BH6: - | BI6: 16+ | BJ6: 5 | BK6: - | BL6: - | BM6: - | BN6: - | BO6: Free Car Park | BP6: Toilets, Disabled toilets, Baby changing, Bench Seating, Picnic Benches, BYO Picnic, Buggy Friendly, Dogs Allowed, Outdoor Seating, Water Refill | BQ6: Ice creams, Activity trail, Children’s trail, "Swings, Slides, Climbing Frames", Outdoor play equipment | BR6: Hot Drinks, Snacks, Drinks stand, Sweet treats | BS6: TRUE | BT6: TRUE | BU6: TRUE | BV6: TRUE | BW6: TRUE | BX6: TRUE | BY6: TRUE | BZ6: Pumpkin picking, Pumpkin patch, Halloween, Autumn festival, Seasonal event, Giant pumpkins, Pumpkin displays, Magic shows, Game shows, Live music, Roaming entertainers, Marshmallow toasting, S'mores, Face painting, Family entertainment, Pumpkin photography, Outdoor festival, Street food, Sweet treats, Darts Farm, Topsham | CA6: Autumn, Halloween | CB6: Pumpkin Patch, Autumnal Drinks, Festive Displays | CC6: Seasonal Hot Chocolates, Festive Displays, Themed Food, Themed Areas, Roasting Marshmallows | CD6: Cashless - bring a bank card, XC Buggy, Wellies | CE6: FALSE | CI6: Darts Farm Pumpkins.JPG | CJ6: Lois | CM6: EVT-00062 | CN6: CREATE | CO6: 46311.409 | CP6: 1 | CQ6: 1 | CS6: FALSE | CT6: FALSE
A7: event | B7: Nature & Wildlife Exploration | D7: Halloween Family Fun at Drakes Farm | E7: Under the Radar | F7: Family Funday | G7: Happy Halloween at Drake’s Farm is a small-scale Halloween session aimed at children up to the age of 8, with crafts, messy play, themed challenges, stories around the Drake’s Farm Cauldron and a Halloween treasure hunt. It feels more like a playful farm-school morning than a large pumpkin-patch event, with activities ranging from crafty making, playing, dressing up and exploring the site. Fancy dress is encouraged, but the activities are designed to get messy, so it has a relaxed, hands-on feel rather than a polished costume-party one. The café is open for drinks, cakes, cookies and snacks, and there are all the usual play and snack options too. | H7: Higher Fingle Farm | I7: Crockernwell | J7: Exeter | L7: EX6 6NP | N7: 50.715318 | O7: -3.7805463 | P7: Outside | Q7: Windy (> X mph), Sunshine, Overcast / cloudy, Dry & mild, Dry & cold, Dry & warm | R7: TRUE | S7: 46322 | T7: 46325 | V7: Tuesday, Thursday, Friday | W7: TRUE | X7: 0.41666667 | Y7: 0.5 | Z7: - | AA7: - | AB7: - | AC7: - | AD7: - | AE7: - | AF7: - | AG7: - | AH7: - | AI7: - | AJ7: - | AK7: - | AL7: - | AM7: - | AN7: FALSE | AV7: 46310 | AW7: TRUE | AX7: TRUE | AY7: Advance Book | AZ7: Baby, (Fixed) Child, Adult | BA7: 0-1.9 | BB7: 0 | BC7: 46236 | BD7: 13.5 | BE7: - | BF7: - | BG7: - | BH7: - | BI7: 16+ | BJ7: 0 | BK7: - | BL7: - | BM7: - | BN7: - | BO7: Free Car Park | BP7: Toilets, Baby changing, Disabled toilets, Bench Seating, Buggy Friendly, Highchairs, Indoor Seating, Outdoor Seating, Water Refill | BQ7: Colouring, Clues / games, "Indoor games (puzzles, boards)", Sandpit, Children's Menu, Indoor Play Space, Outdoor play equipment | BR7: Hot Drinks, Hot & Cold food, Clear Sightlines, Snacks, Sweet treats | BS7: TRUE | BT7: TRUE | BU7: TRUE | BV7: TRUE | BW7: FALSE | BX7: FALSE | BY7: FALSE | BZ7: Halloween, Halloween crafts, Messy play, Themed challenges, Treasure hunt, Stories, Cauldron stories, Fancy dress, Dressing up, Glow sticks, Treats, Farm session, Farm school, Outdoor play, Preschool play, Younger children, Family event, Seasonal events | CA7: Autumn, Halloween | CB7: Pumpkin Patch, Autumnal Drinks, Festive Displays | CC7: "Sand, soil, and loose materials", Children’s Activity Trails, Immersive natural surroundings, Enclosed or defined play zones | CD7: Waterproof clothing, Wellies, Change of clothes | CE7: FALSE | CI7: Drakes Farm.jpg | CJ7: Lois | CM7: EVT-00052 | CN7: CREATE | CO7: 46295.603 | CP7: 1 | CQ7: 1 | CS7: FALSE | CT7: FALSE
A8: event | B8: Seasonal | C8: Patch or Field | D8: Pumpkin Fest Half Term | E8: Special Day Out | F8: Themed | G8: Pumpkin Fest at Strawberry Fields is one of the most involved autumn pumpkin-themed events in Devon, built around homegrown pumpkins, seasonal displays and family entertainment (and everything pumpkin-themed you can possibly think of!) rather than just a quick pick-your-own stop. The pumpkin patch gives children the simple job of choosing their own pumpkin, while the wider site adds barrel train rides, photo displays, acoustic live music, magic shows, circus shows and plenty of autumn food. There are marshmallows to roast (additional cost), countless photo opportunities, lots of tasty autumnal food, face painting (additional cost) as well as lots more. Most things do include an additional cost on top of your entry ticket, but there is enough going on to make the visit feel like a seasonal day out, moving between pumpkins, performances, food stalls and the wider farm shop setting. Arrival time slots should be booked online ahead of time (they book up quickly) but there isn't a fixed limit on how long visitors can stay once inside, but you likely want to allow a couple of hours minimum to make the most of the trip. The ground is mainly woodchip-covered, with the pumpkin patch in a field, so mud and uneven surfaces are part of the experience after wet weather. Food is a big part of the event, with options including loaded fries, burgers, pizzas, ice cream, donuts, bakery treats, pick and mix, coffee stations and a bar. | H8: Strawberry Fields | I8: Lifton | L8: PL16 0DH | N8: 50.645803 | O8: -4.2976096 | P8: Outside | Q8: Windy (> X mph), Sunshine, Overcast / cloudy, Dry & mild, Dry & cold, Dry & warm, Dry & hot | R8: TRUE | S8: 46321 | T8: 46326 | V8: Monday, Tuesday, Wednesday, Thursday, Friday, Saturday | W8: TRUE | X8: 0.375 | Y8: 0.60416667 | Z8: - | AA8: - | AB8: - | AC8: - | AD8: - | AE8: - | AF8: - | AG8: - | AH8: - | AI8: - | AJ8: - | AK8: - | AL8: - | AM8: - | AN8: TRUE | AV8: 46294 | AW8: TRUE | AX8: TRUE | AY8: Advance Book | AZ8: Baby, (Fixed) Child, Adult | BA8: 0-1 | BB8: 0 | BC8: 1-15 | BD8: 5.95 | BE8: - | BF8: - | BG8: - | BH8: - | BI8: 16+ | BJ8: 5.95 | BK8: - | BL8: - | BM8: - | BN8: - | BO8: Free Car Park | BP8: Toilets, Disabled toilets, Baby changing, Bench Seating, Picnic Benches, BYO Picnic, Buggy Friendly, Highchairs, Dogs Allowed, Indoor Seating, Outdoor Seating | BQ8: Ice creams, Activity Sheets or Signs, Activity trail, Children’s trail, Children's Menu, "Swings, Slides, Climbing Frames", Outdoor play equipment | BR8: Hot Drinks, Comfy Seating / Sofas, WiFi, Hot & Cold food, Clear Sightlines, Snacks, Drinks stand, Sweet treats, Giftshop, Outdoor terrace | BS8: FALSE | BT8: TRUE | BU8: TRUE | BV8: TRUE | BW8: TRUE | BX8: TRUE | BY8: TRUE | BZ8: Pumpkin picking, Pumpkin patch, Halloween, Autumn event, Seasonal event, Maize maze, Barrel train, Magic show, Circus show, Live music, Photo opportunities, Homegrown pumpkins, Farm shop, Food barn, Autumn food, Sweet treats, Family entertainment, Outdoor event, Muddy play, PYO Pumpkin | CA8: Autumn, Halloween | CB8: Pumpkin Patch, Autumnal Drinks, Festive Displays | CC8: Festive Shows, Singing figures or characters, Seasonal Hot Chocolates, Festive Displays, Themed Areas, Themed Food, Seasonal Fruit Picking, Roasting Marshmallows, Bonfires | CD8: Cashless - bring a bank card, Wellies | CE8: FALSE | CI8: Pumpkinfest.jpg | CJ8: Rochelle | CM8: EVT-00048 | CN8: CREATE | CO8: 46294.623 | CP8: 1 | CQ8: 1 | CS8: FALSE | CT8: FALSE
A9: event | B9: Seasonal | C9: Patch or Field | D9: Pumpkin Fest - Strawberry Fields | E9: Special Day Out | F9: Themed | G9: Pumpkin Fest at Strawberry Fields is one of the most involved autumn pumpkin-themed events in Devon, built around homegrown pumpkins, seasonal displays and family entertainment (and everything pumpkin-themed you can possibly think of!) rather than just a quick pick-your-own stop. The pumpkin patch gives children the simple job of choosing their own pumpkin, while the wider site adds barrel train rides, photo displays, acoustic live music, magic shows, circus shows and plenty of autumn food. There are marshmallows to roast (additional cost), countless photo opportunities, lots of tasty autumnal food, face painting (additional cost) as well as lots more. Most things do include an additional cost on top of your entry ticket, but there is enough going on to make the visit feel like a seasonal day out, moving between pumpkins, performances, food stalls and the wider farm shop setting. Arrival time slots should be booked online ahead of time (they book up quickly) but there isn't a fixed limit on how long visitors can stay once inside, but you likely want to allow a couple of hours minimum to make the most of the trip. The ground is mainly woodchip-covered, with the pumpkin patch in a field, so mud and uneven surfaces are part of the experience after wet weather. Food is a big part of the event, with options including loaded fries, burgers, pizzas, ice cream, donuts, bakery treats, pick and mix, coffee stations and a bar. | H9: Strawberry Fields | I9: Lifton | L9: PL16 0DH | N9: 50.645803 | O9: -4.2976096 | P9: Outside | Q9: Windy (> X mph), Sunshine, Overcast / cloudy, Dry & mild, Dry & cold, Dry & warm, Dry & hot | R9: TRUE | S9: 46298 | T9: 46320 | V9: Saturday, Sunday | W9: TRUE | X9: 0.375 | Y9: 0.60416667 | Z9: - | AA9: - | AB9: - | AC9: - | AD9: - | AE9: - | AF9: - | AG9: - | AH9: - | AI9: - | AJ9: - | AK9: - | AL9: - | AM9: - | AN9: TRUE | AV9: 46294 | AW9: TRUE | AX9: TRUE | AY9: Advance Book | AZ9: Baby, (Fixed) Child, Adult | BA9: 0-1 | BB9: 0 | BC9: 1-15 | BD9: 5.95 | BE9: - | BF9: - | BG9: - | BH9: - | BI9: 16+ | BJ9: 5.95 | BK9: - | BL9: - | BM9: - | BN9: - | BO9: Free Car Park | BP9: Toilets, Disabled toilets, Baby changing, Bench Seating, Picnic Benches, BYO Picnic, Buggy Friendly, Highchairs, Dogs Allowed, Indoor Seating, Outdoor Seating | BQ9: Ice creams, Activity Sheets or Signs, Activity trail, Children’s trail, Children's Menu, "Swings, Slides, Climbing Frames", Outdoor play equipment | BR9: Hot Drinks, Comfy Seating / Sofas, WiFi, Hot & Cold food, Clear Sightlines, Snacks, Drinks stand, Sweet treats, Giftshop, Outdoor terrace | BS9: FALSE | BT9: TRUE | BU9: TRUE | BV9: TRUE | BW9: TRUE | BX9: TRUE | BY9: TRUE | BZ9: Pumpkin picking, Pumpkin patch, Halloween, Autumn event, Seasonal event, Maize maze, Barrel train, Magic show, Circus show, Live music, Photo opportunities, Homegrown pumpkins, Farm shop, Food barn, Autumn food, Sweet treats, Family entertainment, Outdoor event, Muddy play, PYO Pumpkin | CA9: Autumn, Halloween | CB9: Pumpkin Patch, Autumnal Drinks, Festive Displays | CC9: Festive Shows, Singing figures or characters, Seasonal Hot Chocolates, Festive Displays, Themed Areas, Themed Food, Seasonal Fruit Picking, Roasting Marshmallows, Bonfires | CD9: Cashless - bring a bank card, Wellies | CE9: FALSE | CI9: Pumpkinfest.jpg | CJ9: Rochelle | CM9: EVT-00043 | CN9: CREATE | CO9: 46294.622 | CP9: 1 | CQ9: 1 | CS9: FALSE | CT9: FALSE
A10: event | B10: Seasonal | C10: PYO Farm | D10: Sanctuary Flowers | E10: Moment of Peace | F10: Nature-based | G10: Sanctuary flower farm and pick-your-own tucked within the Froginwell Estate, is a wonderful new addition to East Devon and is open on Sundays and Mondays from May through to October. Entry is £5 per adult (under 12's and over 70's go free) and covers both the flower farm and 20 acres of meadow walks across the estate itself. The rows of cut flowers — dahlias, sweet peas, sunflowers, zinnias and seasonal blooms — are there to be wandered through and picked from at your own pace (for an additional cost of £25 per bucket), with stems wrapped in paper to take home or transported in a refillable bucket (incl. in the cost), which keeps them fresh for the journey. The CoffeeBox on site covers coffee, hot drinks and snacks, set under a large bell-tent canopy with views across the flower fields; it's a very pretty, photogenic setting with friendly staff on-hand who are genuinely passionate about floristry and helping you build a beautiful bouquet. A seasonal pass for £20 gives unlimited access on open days throughout the season with 10% off flowers - potentially handy if you live locally and can imagine coming back across the summer with friends, or to treat someone for a special occasion. | H10: Sanctuary Flowers | I10: Froginwell Estate | L10: EX5 1EP | N10: 50.705406 | O10: -3.3808044 | P10: Outside | Q10: Sunshine, Overcast / cloudy, Dry & warm, Dry & hot, Dry & mild | R10: TRUE | S10: 46170 | T10: 46306 | V10: Sunday, Monday | W10: TRUE | X10: 0.41666667 | Y10: 0.625 | Z10: - | AA10: - | AB10: - | AC10: - | AD10: - | AE10: - | AF10: - | AG10: - | AH10: - | AI10: - | AJ10: - | AK10: - | AL10: - | AM10: - | AN10: FALSE | AV10: 46170 | AW10: TRUE | AX10: FALSE | AY10: Pay On Arrival | AZ10: Baby, (Fixed) Child, Adult, Concession | BA10: 0-11 | BB10: 0 | BC10: 12-18 | BD10: 5 | BE10: - | BF10: - | BG10: - | BH10: - | BI10: 18+ | BJ10: 5 | BK10: 70+ | BL10: 0 | BM10: - | BN10: - | BO10: Free Car Park | BP10: Picnic Benches, Dogs Allowed, Outdoor Seating, BYO Picnic | BQ10: Activity Sheets or Signs, Activity trail, Ice creams | BR10: Hot Drinks, Snacks, Drinks stand, Sweet treats | BS10: FALSE | BT10: FALSE | BU10: TRUE | BV10: TRUE | BW10: TRUE | BX10: TRUE | BY10: TRUE | BZ10: PYO flowers, flowers, bouquets, floristry, seasonal flowers, flower farm, wildlife pond, wildflower meadow, Flower picking, Pick your own, Cut flower farm, Seasonal flowers, Flower arranging, Colour, Scent, Nature, Gardening, Meadow walks, Picnic, Wildlife, Creative activity, Outdoor creativity, Hands-on activity, Slow exploring, Sensory nature, Countryside, Local produce, Sustainable flowers, UK-grown flowers, Froginwell Estate, East Devon | CA10: Summer | CB10: PYO Flowers, Wildflower Meadows, Butterflies | CC10: Flower collecting or displays, Wildlife Spotting | CD10: XC Buggy, Sling / baby carrier | CE10: FALSE | CI10: Sanctuary Flowers.JPG | CJ10: Provider | CM10: EVT-00038 | CN10: CREATE | CO10: 46294.577 | CP10: 1 | CQ10: 1 | CS10: FALSE | CT10: FALSE
A11: event | B11: Seasonal | C11: Patch or Field | D11: Greendale Pumpkin Patch | E11: Special Day Out | F11: PYO, Themed | G11: Greendale’s Pumpkin Patch turns the farm shop into a seasonal autumn stop, with pumpkins to choose, photo spots around the patch and the wider Greendale site close by for food, animals and the Farm Trail. The pumpkin picking itself is simple and open-ended: visitors can wander, compare shapes and sizes, choose one to take home and make the visit feel part of the build-up to Halloween rather than a big-ticket day out. Unlike some pumpkin experiences that charge for every element, this one is genuinely free to walk around — you choose your pumpkin and pay only for what you take home and the pricing is clear and upfront. The free Pumpkin Trail adds a second layer, with clue sheets from Oscar’s and pumpkins hidden around the Farm Trail and Farm Shop, ending with a sweet treat once the challenge is complete. Entry to the pumpkin patch is free and works really well alongside a wander around to look at the animal pens. | H11: Sidmouth Road | I11: Farringdon | J11: Exeter | L11: EX5 2JU | N11: 50.70417 | O11: -3.3986618 | P11: Outside | Q11: Sunshine, Overcast / cloudy, Dry & warm, Dry & hot, Dry & mild | R11: TRUE | S11: 46306 | T11: 46327 | V11: Monday, Tuesday, Wednesday, Thursday, Friday, Saturday, Sunday | W11: TRUE | X11: 0.33333333 | Y11: 0.83333333 | Z11: - | AA11: - | AB11: - | AC11: - | AD11: - | AE11: - | AF11: - | AG11: - | AH11: - | AI11: - | AJ11: - | AK11: - | AL11: - | AM11: - | AN11: FALSE | AV11: 46294 | AW11: FALSE | AX11: FALSE | AY11: Open (Free) Access | BA11: - | BB11: - | BC11: - | BD11: - | BE11: - | BF11: - | BG11: - | BH11: - | BI11: - | BJ11: - | BK11: - | BL11: - | BM11: - | BN11: - | BO11: Free Car Park | BP11: Toilets, Disabled toilets, Baby changing, Picnic Benches, BYO Picnic, Buggy Friendly, Indoor Seating, Dogs Allowed, Outdoor Seating, Pushchair Friendly | BQ11: Activity Sheets or Signs, "Swings, Slides, Climbing Frames", Outdoor play equipment, Children's Menu, Children’s trail, Colouring | BR11: Hot Drinks, Hot & Cold food, Clear Sightlines, Snacks, Sweet treats, Giftshop, Outdoor terrace | BS11: TRUE | BT11: TRUE | BU11: TRUE | BV11: TRUE | BW11: TRUE | BX11: TRUE | BY11: TRUE | BZ11: Pumpkin picking, Pumpkin patch, Halloween, Autumn, Seasonal event, Photo opportunities, Pumpkin trail, Clue sheets, Farm trails, Farm animals, Animal spotting, Sweet treat, Family challenge, Outdoor exploring, Farm shop, Farm café, Local produce, Halloween treats, Autumn food | CA11: Halloween, Autumn | CB11: Pumpkin Patch | CC11: Festive Displays, Themed Food, Seasonal Hot Chocolates | CD11: Wellies | CE11: FALSE | CI11: Greendale Pumpkin Patch.JPG | CJ11: Lois | CM11: EVT-00041 | CN11: CREATE | CO11: 46294.549 | CP11: 1 | CQ11: 1 | CS11: FALSE | CT11: FALSE
A12: event | B12: Seasonal | C12: PYO Farm | D12: Amelia's Flowers | E12: Moment of Peace | F12: Nature-based | G12: Run by Amelia and Giles, who are raising their own three children on the farm, there's a relaxed and genuinely welcoming atmosphere here that's hard to manufacture and easy to feel the moment you arrive. The farm sits in a quiet valley between Newton Abbot and Shaldon, with fields of pesticide-free heirloom flowers — dahlias, sweet peas, sunflowers and scented varieties that change through the season — grown slowly and available to pick at your own pace with a pair of snips. Children who are unmoved by the flowers tend to find their own reasons to stay: miniature ponies, pigs (including the much-loved Cris-P-Bacon), swings that even pre-teens apparently can't resist, and the simple freedom of roaming a working farm without a fixed route. The Flower Barn café does homemade cakes and good coffee with views across the fields, and a short walk through the farm brings you down to the River Teign if legs need stretching further. | H12: Amelias Flower Farm, | I12: Combeinteignhead | J12: Newton Abbot | K12: Devon | L12: TQ12 4RG | N12: 50.535436 | O12: -3.5589237 | P12: Outside | Q12: Windy (> X mph), Sunshine, Overcast / cloudy, Dry & mild, Dry & cold, Dry & warm | R12: TRUE | S12: 46165 | T12: 46326 | V12: Monday, Tuesday, Wednesday, Thursday, Friday, Sunday, Saturday | W12: TRUE | X12: 0.41666667 | Y12: 0.66666667 | Z12: - | AA12: - | AB12: - | AC12: - | AD12: - | AE12: - | AF12: - | AG12: - | AH12: - | AI12: - | AJ12: - | AK12: - | AL12: - | AM12: - | AN12: FALSE | AV12: 46165 | AW12: TRUE | AX12: FALSE | AY12: Pay On Arrival | AZ12: Older Child, Adult | BA12: - | BB12: - | BC12: - | BD12: - | BE12: - | BF12: - | BG12: 12-16 | BH12: 25 | BI12: 16+ | BJ12: 25 | BK12: - | BL12: - | BM12: - | BN12: - | BO12: Free Car Park, Bike racks / bays, Horse “parking” | BP12: Toilets, Disabled toilets, Baby changing, Indoor Seating, Dogs Allowed, Outdoor Seating | BQ12: Colouring, Ice creams, Rope Swings, Ride on Vehicles, "Swings, Slides, Climbing Frames", Outdoor play equipment | BR12: Hot Drinks, Comfy Seating / Sofas, Snacks, Sweet treats, Giftshop | BS12: FALSE | BT12: FALSE | BU12: TRUE | BV12: TRUE | BW12: TRUE | BX12: TRUE | BY12: TRUE | BZ12: Flower picking, Pick your own, Cut flower farm, Seasonal flowers, Heirloom flowers, Scented flowers, Unusual flowers, Colour, Nature, Gardening, Plant nursery, Flower arranging, Outdoor creativity, Hands-on activity, Slow exploring, Sensory nature, Countryside, River Teign, Local produce, Sustainable growing, Pesticide-free growing, Chemical-free growing, Workshops, Educational talks, Group visits, School visits, South Devon | CA12: Summer | CB12: PYO Flowers, Wildflower Meadows, Butterflies | CC12: Flower collecting or displays, Wildlife Spotting | CD12: XC Buggy, Sling / baby carrier, Infant / toddler carrier | CE12: FALSE | CI12: Amelias Flower Farm PYO.JPEG | CJ12: Lois | CM12: EVT-00039 | CN12: CREATE | CO12: 46294.515 | CP12: 1 | CQ12: 1 | CS12: FALSE | CT12: FALSE

Sheet Clubs
A1: Essential Info | I1: Club Venue Address | Q1: Dates | S1: School Holiday Schedule | T1: Club Running times | BH1: Ticketing | BY1: Facilities | CC1: Age Suitability | CJ1: Useful Info | CL1: Skill Requirements | CO1: Additional Info | CX1: Admin Panel
T2: Multiple Sessions Daily | Y2: Fixed Start / End Times | AA2: Daily Start / End times | AO2: Multi-Sessions Per Day | BC2: Monthly Fixed Date | BH2: Ticket Needed? | BI2: How to Book | BJ2: Ticket Types | BK2: Baby Tickets | BM2: Child Tickets | BO2: Young Child Tickets | BQ2: Older Child Tickets | BS2: Adult Tickets | BU2: Concession Tickets | BW2: Group Tickets
A3: Opportunity Type | B3: Club Setting | C3: Club Setting (More Specifically) | D3: Club Name | E3: Description | F3: Club Format | G3: Commitment | H3: Frequency | I3: Address | J3: Address line 2 | K3: City/Town | L3: Region | M3: Postcode | N3: Country | O3: Latitude | P3: Longitude | Q3: Confirm the start date | R3: Confirm the end date | T3: Multiple sessions Daily? | U3: Multiple sessions Daily - Total per day | V3: Fixed Daily Multi-Session Times | W3: Which days of the week does it run? | X3: Fixed Daily Start / End Times? | Y3: Fixed Daily start time: | Z3: Fixed Daily end time: | AA3: Monday Start time | AB3: Monday End time | AC3: Tuesday Start time | AD3: Tuesday End time | AE3: Wednesday Start time | AF3: Wednesday End time | AG3: Thursday Start time | AH3: Thursday End time | AI3: Friday Start time | AJ3: Friday End time | AK3: Saturday Start time | AL3: Saturday End time | AM3: Sunday Start time | AN3: Sunday End time | AO3: Multi-Session Monday - No. of sessions | AP3: Monday session times | AQ3: Multi-Session Tuesday - No. of sessions | AR3: Tuesday session times | AS3: Multi-Session Wednesday - No. of sessions | AT3: Wednesday session times | AU3: Multi-Session Thursday - No. of sessions | AV3: Thursday session times | AW3: Multi-Session Friday - No. of sessions | AX3: Friday session times | AY3: Multi-Session Saturday - No. of sessions | AZ3: Saturday session times | BA3: Multi-Session Sunday - No. of sessions | BB3: Sunday session times | BC3: Which day of the week does it occur? | BD3: Do you have a fixed week within the month | BE3: Which week does your club occur? | BF3: Please confirm any upcoming Monthly dates: | BG3: Club Cost? | BH3: Ticketing Requirements | BI3: Booking Type | BJ3: Ticketing Types | BK3: Baby Ticket Definition | BL3: Baby Ticket Price | BM3: Fixed Child Ticket Definition | BN3: Fixed Child Ticket Price | BO3: Young Child Ticket Definition | BP3: Young Child Ticket Price | BQ3: Older Child Ticket Definition | BR3: Older Child Ticket Price | BS3: Adult Ticket Definition | BT3: Adult Ticket Price | BU3: Concession Ticket Definition | BV3: Concession Ticket Price | BW3: Group Ticket Definition | BX3: Group Ticket Price | BY3: Parking Provision | BZ3: General Facilities | CA3: Kids Facilities | CB3: Parent Facilities | CC3: <1s | CD3: 1-2yrs | CE3: 3-4yrs | CF3: 5-7yrs | CG3: 8-12yrs | CH3: 13+yrs | CI3: Adults | CJ3: Activity Group | CK3: Inside or Outside | CL3: Skill Area | CM3: Skill Area Variant | CN3: Ability Level | CO3: Interest Tags | CP3: Seasonal Tag | CQ3: Seasonal Highlights | CR3: Highlights (Attractions) | CS3: Extra Kit | CT3: Image Name | CU3: Photo Contributor | CV3: Partner Code | CW3: Regular Timetabled Club | CX3: Record ID | CY3: Developer Action | CZ3: Added to Queue | DA3: Upload Batch No. | DB3: Proposed Version | DC3: Change Summary | DD3: AWS Action Complete? | DE3: Return to WORKING? | DF3: Cancel Removal?
A4: opportunity_type | B4: club_opportunity_theme | C4: club_opportunity_theme_variant | D4: club_name | E4: club_description | F4: club_format | G4: club_commitment | H4: club_frequency | I4: club_address_line_1 | J4: club_address_line_2 | K4: club_city_town | L4: club_state_region_province | M4: club_postcode | N4: club_country | O4: latitude | P4: longitude | Q4: club_start_date | R4: club_end_date | S4: club_break_schedule | T4: club_repeat_session | U4: club_daily_fixed_session_total | V4: club_daily_fixed_session_schedule | W4: club_daily_schedule | X4: club_fixed_daily_timings | Y4: club_daily_start_time | Z4: club_daily_end_time | AA4: club_mixed_timings_monday_start_time | AB4: club_mixed_timings_monday_end_time | AC4: club_mixed_timings_tuesday_start_time | AD4: club_mixed_timings_tuesday_end_time | AE4: club_mixed_timings_wednesday_start_time | AF4: club_mixed_timings_wednesday_end_time | AG4: club_mixed_timings_thursday_start_time | AH4: club_mixed_timings_thursday_end_time | AI4: club_mixed_timings_friday_start_time | AJ4: club_mixed_timings_friday_end_time | AK4: club_mixed_timings_saturday_start_time | AL4: club_mixed_timings_saturday_end_time | AM4: club_mixed_timings_sunday_start_time | AN4: club_mixed_timings_sunday_end_time | AO4: club_multi_session_monday_session_total | AP4: club_multi_session_monday_schedule | AQ4: club_multi_session_tuesday_session_total | AR4: club_multi_session_tuesday_schedule | AS4: club_multi_session_wednesday_session_total | AT4: club_multi_session_wednesday_schedule | AU4: club_multi_session_thursday_session_total | AV4: club_multi_session_thursday_schedule | AW4: club_multi_session_friday_session_total | AX4: club_multi_session_friday_schedule | AY4: club_multi_session_saturday_session_total | AZ4: club_multi_session_saturday_schedule | BA4: club_multi_session_sunday_session_total | BB4: club_multi_session_sunday_schedule | BC4: club_monthly_schedule | BD4: club_fixed_month_occurance | BE4: club_monthly_occurance | BF4: club_monthly_fixed_dates | BG4: club_entry_cost | BH4: ticketing_requirement | BI4: club_booking_provision | BJ4: ticketing_variants | BK4: ticket_variant_definition_baby | BL4: ticket_variant_baby_price | BM4: ticket_variant_definition_fixed_child | BN4: ticket_variant_fixed_child_price | BO4: ticket_variant_definition_young_child | BP4: ticket_variant_young_child_price | BQ4: ticket_variant_definition_older_child | BR4: ticket_variant_older_child_price | BS4: ticket_variant_definition_adult | BT4: ticket_variant_adult_price | BU4: ticket_variant_definition_concession | BV4: ticket_variant_concession_price | BW4: ticket_variant_definition_group | BX4: ticket_variant_group_price | BY4: club_parking_provision | BZ4: club_general_facilities | CA4: club_child_facilities | CB4: club_adult_facilities | CC4: club_age_suitability_under_1_s | CD4: club_age_suitability_1_to_2_years | CE4: club_age_suitability_3_to_4_years | CF4: club_age_suitability_5_to_7_years | CG4: club_age_suitability_8_to_12_years | CH4: club_age_suitability_over_13_years | CI4: club_age_suitability_adults | CJ4: club_activity_group | CK4: club_physical_setting | CL4: club_skill_area | CM4: club_skill_area_variant | CN4: club_ability_level | CO4: club_interest_tags | CP4: club_seasonal_tag | CQ4: club_seasonal_highlights | CR4: club_attractions | CS4: club_extra_kit | CT4: image | CU4: contributor_first_name | CV4: partner_code | CW4: regular_timetabled | CX4: record_id | CY4: developer_action | CZ4: added_to_queue_at | DA4: admin_version | DB4: queued_version | DC4: change_summary | DD4: actioned_in_aws | DE4: return_to_working | DF4: cancel_removal
A5: club | B5: Community Groups | C5: Playgroup | D5: Little Gems Playgroup | E5: Gems is Christ Church Woodbury’s weekly toddler group that runs on Friday mornings during term time. A lovely, local group where you can genuinely arrive knowing no one and be assured of an uplifting welcome by the friendly volunteers that run it; women, mothers and grandparents that 'get it' and a more than happy to get stuck in playing so you can enjoy a cup of tea. A small soft play area, lots of toys, fancy dress, stories, tea, coffee (and usually a lovely homemade cake) will be waiting for you, along with a semi-structured session that allows for free play and flexible activities you'd expect at a toddler group, followed by a story and snacktime. | F5: Stay-and-play (supervised) | G5: One-off (pay as you go) | H5: Weekly | I5: Christ Church Woodbury | J5: Parsonage Way | K5: Woodbury | M5: EX5 1HY | O5: 50.677377 | P5: -3.399791 | Q5: 46332 | R5: 46374 | S5: Term-time Only | T5: FALSE | W5: Friday | X5: TRUE | Y5: 0.39583333 | Z5: 0.45833333 | AA5: - | AB5: - | AC5: - | AD5: - | AE5: - | AF5: - | AG5: - | AH5: - | AI5: - | AJ5: - | AK5: - | AL5: - | AM5: - | AN5: - | AO5: - | AP5: - | AQ5: - | AR5: - | AS5: - | AT5: - | AU5: - | AV5: - | AW5: - | AX5: - | AY5: - | AZ5: - | BA5: - | BB5: - | BG5: FALSE | BH5: FALSE | BI5: Pay On Arrival | BJ5: Group | BK5: - | BL5: - | BM5: - | BN5: - | BO5: - | BP5: - | BQ5: - | BR5: - | BS5: - | BT5: - | BU5: - | BV5: - | BW5: 1 adult, 1 child | BX5: 2 | BY5: Free Car Park | BZ5: Toilets, Baby changing, Disabled toilets, Buggy Friendly, Indoor Seating, Water Refill | CA5: Colouring, Clues / games, "Indoor games (puzzles, boards)", Indoor Play Space | CB5: Hot Drinks, Comfy Seating / Sofas, Sweet treats, Clear Sightlines | CC5: TRUE | CD5: TRUE | CE5: TRUE | CF5: FALSE | CG5: FALSE | CH5: FALSE | CI5: FALSE | CJ5: Simple Reset | CK5: Inside | CO5: local playgroup, cake, toddler group, craft, toys, soft play, dressing up, fancy dress, storytime, stories, mums groups | CR5: Welcoming space, Storytelling, "Toys, toy corners", Refreshments Provided, Local parent hangout, "Relaxed, child-friendly setting", Play areas or equipment, Flexible timings (relaxed start/end times), Newbie-friendly! | CT5: Little Gems.JPG | CU5: Livi | CX5: CLU-00118 | CY5: CREATE | CZ5: 46311.43 | DA5: 1 | DB5: 1 | DD5: FALSE | DE5: FALSE
A6: club | B6: Community Groups | C6: Playgroup | D6: Little Gems Playgroup | E6: Gems is Christ Church Woodbury’s weekly toddler group that runs on Friday mornings during term time. A lovely, local group where you can genuinely arrive knowing no one and be assured of an uplifting welcome by the friendly volunteers that run it; women, mothers and grandparents that 'get it' and a more than happy to get stuck in playing so you can enjoy a cup of tea. A small soft play area, lots of toys, fancy dress, stories, tea, coffee (and usually a lovely homemade cake) will be waiting for you, along with a semi-structured session that allows for free play and flexible activities you'd expect at a toddler group, followed by a story and snacktime. | F6: Stay-and-play (supervised) | G6: One-off (pay as you go) | H6: Weekly | I6: Christ Church Woodbury | J6: Parsonage Way | K6: Woodbury | M6: EX5 1HY | O6: 50.677377 | P6: -3.399791 | Q6: 46276 | R6: 46318 | S6: Term-time Only | T6: FALSE | W6: Friday | X6: TRUE | Y6: 0.39583333 | Z6: 0.45833333 | AA6: - | AB6: - | AC6: - | AD6: - | AE6: - | AF6: - | AG6: - | AH6: - | AI6: - | AJ6: - | AK6: - | AL6: - | AM6: - | AN6: - | AO6: - | AP6: - | AQ6: - | AR6: - | AS6: - | AT6: - | AU6: - | AV6: - | AW6: - | AX6: - | AY6: - | AZ6: - | BA6: - | BB6: - | BG6: FALSE | BH6: FALSE | BI6: Pay On Arrival | BJ6: Group | BK6: - | BL6: - | BM6: - | BN6: - | BO6: - | BP6: - | BQ6: - | BR6: - | BS6: - | BT6: - | BU6: - | BV6: - | BW6: 1 adult, 1 child | BX6: 2 | BY6: Free Car Park | BZ6: Toilets, Baby changing, Disabled toilets, Buggy Friendly, Indoor Seating, Water Refill | CA6: Colouring, Clues / games, "Indoor games (puzzles, boards)", Indoor Play Space | CB6: Hot Drinks, Comfy Seating / Sofas, Sweet treats, Clear Sightlines | CC6: TRUE | CD6: TRUE | CE6: TRUE | CF6: FALSE | CG6: FALSE | CH6: FALSE | CI6: FALSE | CJ6: Simple Reset | CK6: Inside | CO6: local playgroup, cake, toddler group, craft, toys, soft play, dressing up, fancy dress, storytime, stories, mums groups | CR6: Welcoming space, Storytelling, "Toys, toy corners", Refreshments Provided, Local parent hangout, "Relaxed, child-friendly setting", Play areas or equipment, Flexible timings (relaxed start/end times), Newbie-friendly! | CT6: Little Gems.JPG | CU6: Livi | CX6: CLU-00092 | CY6: CREATE | CZ6: 46311.428 | DA6: 1 | DB6: 1 | DD6: FALSE | DE6: FALSE
A7: club | B7: Community Groups | C7: Social Club | D7: Kingdom Club | E7: Kingdom Club is a friendly after-school session at Lympstone Parish Church, with crafts, stories, games, snacks and a simple children’s tea built into the afternoon. It is designed for children to enjoy a mix of creative, playful and social activities after school, without being a drop-off club; grown-ups stay on site too, with tea, coffee and time to chat while the children join in nearby. The session has a gentle community feel, shaped by the church setting and regular local families, making it a useful midweek option for children who enjoy making things, listening to stories, playing games and spending time with familiar faces in a low-key, relaxed environment after school pick-up. It gives families something more relaxed than a formal class, but with more shape (and shelter!) than simply meeting up after school. It's a great opportunity to meet other local parents and the friendly team within the village parish. | F7: Stay-and-play (supervised) | G7: One-off (pay as you go) | H7: Weekly | I7: Lympstone Parish Church | J7: 1 Church Road | K7: Lympstone | M7: EX8 5JU | O7: 50.649616 | P7: -3.4256137 | Q7: 46332 | R7: 46374 | S7: Term-time Only | T7: FALSE | W7: Tuesday | X7: TRUE | Y7: 0.64583333 | Z7: 0.70833333 | AA7: - | AB7: - | AC7: - | AD7: - | AE7: - | AF7: - | AG7: - | AH7: - | AI7: - | AJ7: - | AK7: - | AL7: - | AM7: - | AN7: - | AO7: - | AP7: - | AQ7: - | AR7: - | AS7: - | AT7: - | AU7: - | AV7: - | AW7: - | AX7: - | AY7: - | AZ7: - | BA7: - | BB7: - | BG7: FALSE | BH7: FALSE | BI7: Open (Free) Access | BJ7: Group | BK7: - | BL7: - | BM7: - | BN7: - | BO7: - | BP7: - | BQ7: - | BR7: - | BS7: - | BT7: - | BU7: - | BV7: - | BW7: 1 adult, 3 children | BX7: 3 | BY7: Free Car Park | BZ7: Toilets, Baby changing, Buggy Friendly, Water Refill | CA7: Colouring, Clues / games, Indoor Play Space, "Indoor games (puzzles, boards)" | CB7: Hot Drinks, Snacks | CC7: FALSE | CD7: FALSE | CE7: TRUE | CF7: TRUE | CG7: TRUE | CH7: FALSE | CI7: FALSE | CJ7: Simple Reset | CK7: Inside | CO7: afterschool club, craft, local meet up, local group | CR7: Welcoming space, Craft Tables or Activities, Refreshments Provided, Local parent hangout, "Relaxed, child-friendly setting", Flexible timings (relaxed start/end times), Newbie-friendly! | CT7: Kingdom Club.jpeg | CU7: Abigail | CX7: CLU-00117 | CY7: CREATE | CZ7: 46310.9 | DA7: 1 | DB7: 1 | DD7: FALSE | DE7: FALSE
A8: club | B8: Community Groups | C8: Social Club | D8: Kingdom Club | E8: Kingdom Club is a friendly after-school session at Lympstone Parish Church, with crafts, stories, games, snacks and a simple children’s tea built into the afternoon. It is designed for children to enjoy a mix of creative, playful and social activities after school, without being a drop-off club; grown-ups stay on site too, with tea, coffee and time to chat while the children join in nearby. The session has a gentle community feel, shaped by the church setting and regular local families, making it a useful midweek option for children who enjoy making things, listening to stories, playing games and spending time with familiar faces in a low-key, relaxed environment after school pick-up. It gives families something more relaxed than a formal class, but with more shape (and shelter!) than simply meeting up after school. It's a great opportunity to meet other local parents and the friendly team within the village parish. | F8: Stay-and-play (supervised) | G8: One-off (pay as you go) | H8: Weekly | I8: Lympstone Parish Church | J8: 1 Church Road | K8: Lympstone | M8: EX8 5JU | O8: 50.649616 | P8: -3.4256137 | Q8: 46276 | R8: 46318 | S8: Term-time Only | T8: FALSE | W8: Tuesday | X8: TRUE | Y8: 0.64583333 | Z8: 0.70833333 | AA8: - | AB8: - | AC8: - | AD8: - | AE8: - | AF8: - | AG8: - | AH8: - | AI8: - | AJ8: - | AK8: - | AL8: - | AM8: - | AN8: - | AO8: - | AP8: - | AQ8: - | AR8: - | AS8: - | AT8: - | AU8: - | AV8: - | AW8: - | AX8: - | AY8: - | AZ8: - | BA8: - | BB8: - | BG8: FALSE | BH8: FALSE | BI8: Open (Free) Access | BJ8: Group | BK8: - | BL8: - | BM8: - | BN8: - | BO8: - | BP8: - | BQ8: - | BR8: - | BS8: - | BT8: - | BU8: - | BV8: - | BW8: 1 adult, 3 children | BX8: 3 | BY8: Free Car Park | BZ8: Toilets, Baby changing, Buggy Friendly, Water Refill | CA8: Colouring, Clues / games, Indoor Play Space, "Indoor games (puzzles, boards)" | CB8: Hot Drinks, Snacks | CC8: FALSE | CD8: FALSE | CE8: TRUE | CF8: TRUE | CG8: TRUE | CH8: FALSE | CI8: FALSE | CJ8: Simple Reset | CK8: Inside | CO8: afterschool club, craft, local meet up, local group | CR8: Welcoming space, Craft Tables or Activities, Refreshments Provided, Local parent hangout, "Relaxed, child-friendly setting", Flexible timings (relaxed start/end times), Newbie-friendly! | CT8: Kingdom Club.jpeg | CU8: Abigail | CX8: CLU-00106 | CY8: CREATE | CZ8: 46310.9 | DA8: 1 | DB8: 1 | DD8: FALSE | DE8: FALSE
A9: club | B9: Nature & Wildlife Exploration | C9: Forest School | D9: Teenager Tuesday at Robin Wood | E9: Teenager Tuesday gives 13–16 year olds a rare kind of outdoor space: relaxed, practical and shaped with their input. Held at Robin Wood Forest School, Liz’s sloping woodland site has the feel of a hidden outdoor workshop, with fire, tools, trees, mud, natural materials and plenty of corners to settle into. Rather than following a fixed activity plan, the group helps steer what happens, from cooking and woodworking to seasonal foraging, games and bushcraft. It is especially suited to teens who still enjoy being outdoors but want something with more independence, purpose and ownership than a younger children’s forest school session. | F9: Workshop | G9: One-off (pay as you go), Termly blocks | H9: Weekly | I9: Robin Wood Forest School | K9: Venn Ottery | M9: EX11 1SG | O9: 50.710978 | P9: -3.3221894 | Q9: 46308 | R9: 46371 | S9: Term-time Only | T9: FALSE | W9: Tuesday | X9: TRUE | Y9: 0.41666667 | Z9: 0.5 | AA9: - | AB9: - | AC9: - | AD9: - | AE9: - | AF9: - | AG9: - | AH9: - | AI9: - | AJ9: - | AK9: - | AL9: - | AM9: - | AN9: - | AO9: - | AP9: - | AQ9: - | AR9: - | AS9: - | AT9: - | AU9: - | AV9: - | AW9: - | AX9: - | AY9: - | AZ9: - | BA9: - | BB9: - | BC9: - | BD9: - | BE9: - | BF9: - | BG9: TRUE | BH9: TRUE | BI9: Advance Book | BJ9: Older Child | BK9: - | BL9: - | BM9: - | BN9: - | BO9: - | BP9: - | BQ9: 8-13 | BR9: 10 | BS9: - | BT9: - | BU9: - | BV9: - | BW9: - | BX9: - | BY9: Free Car Park | BZ9: Toilets, Picnic Benches, Outdoor Seating, Water Refill | CA9: Activity trail, Rope Swings, Outdoor play equipment, Colouring, Activity Sheets or Signs, Children’s trail | CB9: Hot Drinks, Snacks | CC9: FALSE | CD9: FALSE | CE9: FALSE | CF9: FALSE | CG9: TRUE | CH9: TRUE | CI9: FALSE | CJ9: Simple Reset, Under the Radar | CK9: Outside | CO9: Forest school, Woodland play, Outdoor learning, Nature play, Den building, Mud play, Bug hunting, Wildlife spotting, Seasonal nature, Natural materials, Bushcraft, Fire circle, Outdoor crafts, Sticks, Leaves, Trees, Open-ended play, Risky play, Child-led play, Sensory play, Home education, Preschool outdoor play, teenager outdoor activity, home education, home ed | CR9: Climbing Logs or balance beams, Mud kitchens, "Sand, soil, and loose materials", Den-building materials, Natural construction zones, Mud and puddles, Forest school activities, Children’s Activity Trails, Immersive natural surroundings, Quiet or low-intervention spaces, Guided outdoor learning prompts, Fire pits (when part of structured sessions) | CT9: Teenager Tuesdays.jpg | CU9: Liz | CX9: CLU-00108 | CY9: CREATE | CZ9: 46310.888 | DA9: 1 | DB9: 1 | DD9: FALSE | DE9: FALSE
A10: club | B10: Nature & Wildlife Exploration | C10: Forest School | D10: Make-It Monday at Robin Wood | E10: Make it Monday has a lively, hands-on feel, with children aged roughly 8–13 helping to shape what they make, cook, play and try next. Robin Wood’s woodland setting gives the group plenty to work with: seasonal materials, outdoor space, fire, mud, tools, trees and the freedom to let ideas grow as the session unfolds. A favourite is the woodland “bake off”, where children start with basic ingredients and then add their own twist, making outdoor cooking feel creative and a bit competitive. Drama, games and nature-based making give the sessions a sociable, imaginative energy, especially for children who like to do more than simply follow instructions. | F10: Workshop | G10: One-off (pay as you go), Termly blocks | H10: Weekly | I10: Robin Wood Forest School | K10: Venn Ottery | M10: EX11 1SG | O10: 50.710978 | P10: -3.3221894 | Q10: 46307 | R10: 46370 | S10: Term-time Only | T10: FALSE | W10: Monday | X10: TRUE | Y10: 0.52083333 | Z10: 0.60416667 | AA10: - | AB10: - | AC10: - | AD10: - | AE10: - | AF10: - | AG10: - | AH10: - | AI10: - | AJ10: - | AK10: - | AL10: - | AM10: - | AN10: - | AO10: - | AP10: - | AQ10: - | AR10: - | AS10: - | AT10: - | AU10: - | AV10: - | AW10: - | AX10: - | AY10: - | AZ10: - | BA10: - | BB10: - | BC10: - | BD10: - | BE10: - | BF10: - | BG10: TRUE | BH10: TRUE | BI10: Advance Book | BJ10: Older Child | BK10: - | BL10: - | BM10: - | BN10: - | BO10: - | BP10: - | BQ10: 8-13 | BR10: 10 | BS10: - | BT10: - | BU10: - | BV10: - | BW10: - | BX10: - | BY10: Free Car Park | BZ10: Toilets, Picnic Benches, Outdoor Seating, Water Refill | CA10: Activity trail, Rope Swings, Outdoor play equipment, Colouring, Activity Sheets or Signs, Children’s trail | CB10: Hot Drinks, Snacks | CC10: FALSE | CD10: FALSE | CE10: FALSE | CF10: FALSE | CG10: TRUE | CH10: TRUE | CI10: FALSE | CJ10: Simple Reset, Under the Radar | CK10: Outside | CO10: Forest school, Woodland play, Outdoor learning, Nature play, Den building, Mud play, Bug hunting, Wildlife spotting, Seasonal nature, Natural materials, Bushcraft, Fire circle, Outdoor crafts, Sticks, Leaves, Trees, Open-ended play, Risky play, Child-led play, Sensory play, Home education, Preschool outdoor play, | CR10: Climbing Logs or balance beams, Mud kitchens, "Sand, soil, and loose materials", Den-building materials, Natural construction zones, Mud and puddles, Forest school activities, Children’s Activity Trails, Immersive natural surroundings, Quiet or low-intervention spaces, Guided outdoor learning prompts, Fire pits (when part of structured sessions) | CT10: Make It Mondays.jpg | CU10: Liz | CX10: CLU-00109 | CY10: CREATE | CZ10: 46310.886 | DA10: 1 | DB10: 1 | DD10: FALSE | DE10: FALSE
A11: club | B11: Sporty Activities | C11: Swimming Pool | D11: Swim Devon Lessons - Stages 8-10 & Racers | E11: For confident swimmers ready to take their skills further, Swim Devon's advanced lessons focus on refining stroke technique, building stamina and developing greater speed, strength and efficiency in the water. Moving beyond the basics of learning to swim, these sessions introduce a more challenging, fitness-focused approach, helping older children improve their front crawl, backstroke, breaststroke and butterfly while developing the skills needed for longer distances and more competitive swimming. The Racers element adds another dimension for those who enjoy pushing themselves, working towards personal goals and seeing their times improve. It's a natural progression for capable swimmers who love being in the pool and want to develop their technique, endurance and confidence through more structured training. | F11: Lesson | G11: Termly blocks | H11: Weekly | I11: Commando Training Centre Royal Marines | J11: Exton | K11: Exmouth | M11: EX8 5AR | O11: 50.664506 | P11: -3.4347242 | Q11: 46273 | R11: 46343 | S11: Term-time Only | T11: FALSE | W11: Tuesday | X11: TRUE | Y11: 0.77083333 | Z11: 0.8125 | BG11: TRUE | BH11: TRUE | BI11: Pre-Register, Advance Book | BJ11: (Fixed) Child | BK11: - | BL11: - | BM11: - | BN11: - | BO11: - | BP11: - | BQ11: 10-16 | BR11: 72.5 | BS11: - | BT11: - | BU11: - | BV11: - | BW11: - | BX11: - | BY11: Free Car Park | BZ11: Toilets, Showers / changing facilities, Indoor Seating | CB11: Clear Sightlines | CC11: FALSE | CD11: FALSE | CE11: FALSE | CF11: FALSE | CG11: TRUE | CH11: TRUE | CI11: FALSE | CJ11: Energy Burner | CK11: Inside | CL11: Swimming | CN11: Expert | CO11: Swimming lessons, Learn to swim, Water confidence, Swim England stages, Stroke technique, Front crawl, Backstroke, Breaststroke, Butterfly, Water safety, Pool skills, Lane swimming, Group lessons, Structured lessons, Progression, Confidence building, Physical activity, Coordination, Fitness, Advanced swimming, Swimming lessons, Swim England Stage 8, Swim England Stage 9, Swim England Stage 10, Competitive swimming, Racing, Stroke technique, Front crawl, Backstroke, Breaststroke, Butterfly, Swimming endurance, Stamina, Speed, Fitness, Swimming skills, Personal bests, Lane swimming, Swimming progression, Sports training | CR11: Skill progression, Confidence building, Strength & agility, Structured coaching, Swimming | CS11: Swimming kit, Towels, Dry bags | CT11: Swim Devon.jpg | CU11: Lois | CX11: CLU-00111 | CY11: CREATE | CZ11: 46310.882 | DA11: 1 | DB11: 1 | DD11: FALSE | DE11: FALSE
A12: club | B12: Sporty Activities | C12: Swimming Pool | D12: Swim Devon Group Lesson - Stages 1-7 (Lympstone) | E12: Swim Devon offers children’s swimming lessons with a child-centred approach, focusing on water confidence, technique and steady progress through the Swim England stages. Lessons in Lympstone use the pool at the Royal Marines Base with lane-based groups, so children can build skills in a more structured swimming environment rather than a splash-style session. It is an ideal activity for parents looking to improve their children's water confidence and their capability in the water, but note they are lessons and, while made fun and interactive for younger swimmers, they're structuredwith a view to progression, so the sessions require a termly commitment. The teachers are incredibly well-regarded and, for the younger groups, are in the water with children which supports their confidence as they're getting more familiar with the water and a larger, noiser setting. Arrive ready to swim (while there are changing rooms, they're limited at this venue) so most children arrive in a dryrobe or with loose clothing over their swimwear. Changing facilities are limited as Swim Devon do not have exclusive use of the changing rooms. Parents will need to pre-register and bring ID with them each week; you'll be met at the main gate 10mins before the lessons start and escorted, in a group, to the pool. The pool is maintained at around 28 but does vary - it's not the warmest pool but children are kept active during the sessions; it's worth knowing if your child is a definite warm-water swimmer, or might struggle with a busier group. If so, the Budleigh Lessons are taught in a smaller, warmer pool may be better suited to children who prefer that sort of introduction to swimming. | F12: Lesson | G12: Termly blocks | H12: Weekly | I12: Commando Training Centre Royal Marines | J12: Exton | K12: Exmouth | M12: EX8 5AR | O12: 50.664506 | P12: -3.4347242 | Q12: 46273 | R12: 46343 | S12: Term-time Only | T12: TRUE | W12: Tuesday | X12: FALSE | AQ12: 3 | AR12: 17:00-17:40, 17:40-18:20 | BG12: TRUE | BH12: TRUE | BI12: Advance Book, Pre-Register | BJ12: (Fixed) Child | BK12: - | BL12: - | BM12: 46299 | BN12: 72.5 | BO12: - | BP12: - | BQ12: - | BR12: - | BS12: - | BT12: - | BU12: - | BV12: - | BW12: - | BX12: - | BY12: Free Car Park | BZ12: Toilets, Showers / changing facilities, Indoor Seating | CB12: Clear Sightlines | CC12: FALSE | CD12: FALSE | CE12: TRUE | CF12: TRUE | CG12: TRUE | CH12: FALSE | CI12: FALSE | CJ12: Energy Burner | CK12: Inside | CL12: Swimming | CN12: None / Novice | CO12: Swimming lessons, Learn to swim, Water confidence, Swim England stages, Stroke technique, Front crawl, Backstroke, Breaststroke, Butterfly, Water safety, Pool skills, Lane swimming, Group lessons, Structured lessons, Progression, Confidence building, Physical activity, Coordination, Fitness | CR12: Early access introduction, Skill progression, Confidence building, Strength & agility, Structured coaching, Mixed-ability sessions, Swimming | CS12: Swimming kit, Towels, Dry bags | CT12: Swim Devon.jpg | CU12: Lois | CX12: CLU-00100 | CY12: CREATE | CZ12: 46310.88 | DA12: 1 | DB12: 1 | DD12: FALSE | DE12: FALSE
A13: club | B13: Nature & Wildlife Exploration | C13: Forest School | D13: Family Home Ed at Robin Wood | E13: Family Home Ed is the most community-minded of the Robin Wood sessions, bringing home-educating families into the woods on Friday afternoons for making, seasonal projects and shared time outdoors. Because children come as families, different ages can take part alongside one another, with younger children joining in where they can and older children taking more responsibility. Sessions often use what the woodland offers at that time of year, from natural craft materials to small practical jobs that help improve the site. The honesty shop project adds a lovely real-world thread, giving children a reason to create forest school makes and understand how their work can help fund new equipment for the group. | F13: Workshop | G13: One-off (pay as you go), Termly blocks | H13: Weekly | I13: Robin Wood Forest School | K13: Venn Ottery | M13: EX11 1SG | O13: 50.710978 | P13: -3.3221894 | Q13: 46311 | R13: 46374 | S13: Term-time Only | T13: FALSE | W13: Friday | X13: TRUE | Y13: 0.54166667 | Z13: 0.625 | AA13: - | AB13: - | AC13: - | AD13: - | AE13: - | AF13: - | AG13: - | AH13: - | AI13: - | AJ13: - | AK13: - | AL13: - | AM13: - | AN13: - | AO13: - | AP13: - | AQ13: - | AR13: - | AS13: - | AT13: - | AU13: - | AV13: - | AW13: - | AX13: - | AY13: - | AZ13: - | BA13: - | BB13: - | BC13: - | BD13: - | BE13: - | BF13: - | BG13: TRUE | BH13: TRUE | BI13: Advance Book | BJ13: Group, (Fixed) Child | BK13: - | BL13: - | BM13: 3-15 | BN13: 10 | BO13: - | BP13: - | BQ13: - | BR13: - | BS13: - | BT13: - | BU13: - | BV13: - | BW13: 1 adult, 4 children | BX13: 15 | BY13: Free Car Park | BZ13: Toilets, Picnic Benches, Outdoor Seating, Water Refill | CA13: Activity trail, Rope Swings, Outdoor play equipment, Colouring, Activity Sheets or Signs, Children’s trail | CB13: Hot Drinks, Snacks | CC13: TRUE | CD13: TRUE | CE13: TRUE | CF13: TRUE | CG13: TRUE | CH13: TRUE | CI13: FALSE | CJ13: Simple Reset, Under the Radar | CK13: Outside | CO13: Forest school, Woodland play, Outdoor learning, Nature play, Den building, Mud play, Bug hunting, Wildlife spotting, Seasonal nature, Natural materials, Bushcraft, Fire circle, Outdoor crafts, Sticks, Leaves, Trees, Open-ended play, Risky play, Child-led play, Sensory play, Home education, Preschool outdoor play, teenager outdoor activity, home education, home ed | CR13: Climbing Logs or balance beams, Mud kitchens, "Sand, soil, and loose materials", Den-building materials, Natural construction zones, Mud and puddles, Forest school activities, Children’s Activity Trails, Immersive natural surroundings, Quiet or low-intervention spaces, Guided outdoor learning prompts, Fire pits (when part of structured sessions) | CT13: Robin Wood Home Ed.JPG | CU13: Lois | CX13: CLU-00110 | CY13: CREATE | CZ13: 46308.408 | DA13: 1 | DB13: 1 | DD13: FALSE | DE13: FALSE
A14: club | B14: Creative Activities | D14: Tick Tock - Lympstone Playgroup | E14: Tick-Tock Toddlers is a Friday morning playgroup in the heart of Lympstone village, giving babies, toddlers and preschool children a familiar place to play while parents and carers catch up over refreshments. Held inside the church during term time, it has the feel of a simple village toddler group rather than a formal class: toys out, little ones able to move between playtime and snacks, and grown-ups able to chat without needing to plan a whole morning around it. Its setting makes it especially useful for local families who want something regular, friendly and easy to fold into the week, with the church, village centre and nearby everyday stops all close together, ideally timed after school drop-off in the mornings. | F14: Stay-and-play (supervised) | G14: One-off (pay as you go) | H14: Weekly | I14: Lympstone Parish Church | J14: 1 Church Road | K14: Lympstone | M14: EX8 5JU | O14: 50.649616 | P14: -3.4256137 | Q14: 46332 | R14: 46374 | S14: Term-time Only | T14: FALSE | W14: Friday | X14: TRUE | Y14: 0.375 | Z14: 0.45833333 | AA14: - | AB14: - | AC14: - | AD14: - | AE14: - | AF14: - | AG14: - | AH14: - | AI14: - | AJ14: - | AK14: - | AL14: - | AM14: - | AN14: - | AO14: - | AP14: - | AQ14: - | AR14: - | AS14: - | AT14: - | AU14: - | AV14: - | AW14: - | AX14: - | AY14: - | AZ14: - | BA14: - | BB14: - | BG14: TRUE | BH14: FALSE | BI14: Open (Free) Access | BJ14: Group | BK14: - | BL14: - | BM14: - | BN14: - | BO14: - | BP14: - | BQ14: - | BR14: - | BS14: - | BT14: - | BU14: - | BV14: - | BW14: 1 adult, 2 children | BX14: 2 | BY14: Free Car Park | BZ14: Toilets, Baby changing, Wheelchair Friendly, Buggy Friendly, Water Refill | CA14: Colouring, Clues / games, "Indoor games (puzzles, boards)", Ride on Vehicles, Indoor Play Space | CB14: Hot Drinks, Snacks | CC14: TRUE | CD14: TRUE | CE14: TRUE | CF14: FALSE | CG14: FALSE | CH14: FALSE | CI14: FALSE | CJ14: Simple Reset | CK14: Inside | CO14: local playgroup, toddler group, craft, toys, soft play, dressing up, fancy dress, storytime, stories, mums groups | CR14: Confidence-building environments, Imaginative freedom, "Informal, welcoming environments" | CT14: Lympstone Church Playgroup.JPG | CU14: Lois | CX14: CLU-00116 | CY14: CREATE | CZ14: 46307.894 | DA14: 1 | DB14: 1 | DD14: FALSE | DE14: FALSE
A15: club | B15: Creative Activities | D15: Tick Tock - Lympstone Playgroup | E15: Tick-Tock Toddlers is a Friday morning playgroup in the heart of Lympstone village, giving babies, toddlers and preschool children a familiar place to play while parents and carers catch up over refreshments. Held inside the church during term time, it has the feel of a simple village toddler group rather than a formal class: toys out, little ones able to move between playtime and snacks, and grown-ups able to chat without needing to plan a whole morning around it. Its setting makes it especially useful for local families who want something regular, friendly and easy to fold into the week, with the church, village centre and nearby everyday stops all close together, ideally timed after school drop-off in the mornings. | F15: Stay-and-play (supervised) | G15: One-off (pay as you go) | H15: Weekly | I15: Lympstone Parish Church | J15: 1 Church Road | K15: Lympstone | M15: EX8 5JU | O15: 50.649616 | P15: -3.4256137 | Q15: 46276 | R15: 46318 | S15: Term-time Only | T15: FALSE | W15: Friday | X15: TRUE | Y15: 0.375 | Z15: 0.45833333 | AA15: - | AB15: - | AC15: - | AD15: - | AE15: - | AF15: - | AG15: - | AH15: - | AI15: - | AJ15: - | AK15: - | AL15: - | AM15: - | AN15: - | AO15: - | AP15: - | AQ15: - | AR15: - | AS15: - | AT15: - | AU15: - | AV15: - | AW15: - | AX15: - | AY15: - | AZ15: - | BA15: - | BB15: - | BG15: TRUE | BH15: FALSE | BI15: Open (Free) Access | BJ15: Group | BK15: - | BL15: - | BM15: - | BN15: - | BO15: - | BP15: - | BQ15: - | BR15: - | BS15: - | BT15: - | BU15: - | BV15: - | BW15: 1 adult, 2 children | BX15: 2 | BY15: Free Car Park | BZ15: Toilets, Baby changing, Wheelchair Friendly, Buggy Friendly, Water Refill | CA15: Colouring, Clues / games, "Indoor games (puzzles, boards)", Ride on Vehicles, Indoor Play Space | CB15: Hot Drinks, Snacks | CC15: TRUE | CD15: TRUE | CE15: TRUE | CF15: FALSE | CG15: FALSE | CH15: FALSE | CI15: FALSE | CJ15: Simple Reset | CK15: Inside | CO15: local playgroup, toddler group, craft, toys, soft play, dressing up, fancy dress, storytime, stories, mums groups | CR15: Confidence-building environments, Imaginative freedom, "Informal, welcoming environments" | CT15: Lympstone Church Playgroup.JPG | CU15: Lois | CX15: CLU-00105 | CY15: CREATE | CZ15: 46307.894 | DA15: 1 | DB15: 1 | DD15: FALSE | DE15: FALSE
A16: club | B16: Sporty Activities | C16: Community Centre | D16: Little Yammas Martial Arts Exmouth | E16: The Lil YAMA’s programme offers children a great blend of fun & discipline whilst learning martial arts-based drills and games. Classes focus on building valuable life skills and developing a budding sense of discipline and concentration. High-energy, friendly and fun, instructors encourage enable children to take pride in developing their technique and discover the rewards of practice. | F16: Training / Skill Development | G16: Monthly | H16: Weekly | I16: Withycombe Raleigh Primary School | J16: 187 Withycombe Village Road | K16: Exmouth | M16: EX8 3BA | O16: 50.630023 | P16: -3.3989743 | Q16: 46023 | R16: 46388 | S16: Term-time Only | T16: FALSE | W16: Monday, Tuesday, Thursday | X16: TRUE | Y16: 0.69791667 | Z16: 0.72569444 | AA16: - | AB16: - | AC16: - | AD16: - | AE16: - | AF16: - | AG16: - | AH16: - | AI16: - | AJ16: - | AK16: - | AL16: - | AM16: - | AN16: - | AO16: - | AP16: - | AQ16: - | AR16: - | AS16: - | AT16: - | AU16: - | AV16: - | AW16: - | AX16: - | AY16: - | AZ16: - | BA16: - | BB16: - | BD16: - | BE16: - | BF16: - | BG16: TRUE | BH16: TRUE | BI16: Advance Book, Pre-Register | BJ16: (Fixed) Child | BK16: - | BL16: - | BM16: 46207 | BN16: 29 | BO16: - | BP16: - | BQ16: - | BR16: - | BS16: - | BT16: - | BU16: - | BV16: - | BW16: - | BX16: - | BY16: Free Car Park | BZ16: Toilets | CC16: FALSE | CD16: FALSE | CE16: TRUE | CF16: TRUE | CG16: FALSE | CH16: FALSE | CI16: FALSE | CJ16: Energy Burner, Low Effort | CK16: Inside | CL16: Martial Arts | CN16: None / Novice | CO16: Martial arts, confidence, skills development, ninja training | CR16: Early access introduction, Confidence building, Coordination & balance, Mixed-ability sessions, Friendly competition, Martial Arts | CS16: Activity-specific clothing | CT16: Little Yammas Martial Arts Exmouth.JPG | CU16: Lois | CX16: CLU-00005 | CY16: UPDATE | CZ16: 46307.88 | DA16: 1 | DB16: 2 | DD16: FALSE | DE16: FALSE
A17: club | B17: Sporty Activities | C17: Climbing Centre | D17: Rockstars Climbing Club | E17: Rockstars is the Quay Climbing Centre's club for young climbing enthusiasts where confidence, coordination and balance is developed on the walls within the Clip 'n Climb arena. A starting point for children keen to develop the skills that will help them to move onto the bigger, roped climbing area with confidence. Run by experienced climbers who pass along their enthusiasm for the sport and teach through fun activities designed to develop technique and agility. | F17: Training / Skill Development | G17: Monthly | H17: Weekly | I17: The Quay Climbing Centre | J17: Haven Road | K17: Exeter | M17: EX2 8AX | O17: 50.716826 | P17: -3.5308304 | Q17: 46023 | R17: 46388 | S17: Term-time Only | T17: FALSE | W17: Tuesday, Wednesday, Thursday | X17: TRUE | Y17: 0.6875 | Z17: 0.72916667 | AA17: - | AB17: - | AC17: - | AD17: - | AE17: - | AF17: - | AG17: - | AH17: - | AI17: - | AJ17: - | AK17: - | AL17: - | AM17: - | AN17: - | AO17: - | AP17: - | AQ17: - | AR17: - | AS17: - | AT17: - | AU17: - | AV17: - | AW17: - | AX17: - | AY17: - | AZ17: - | BA17: - | BB17: - | BD17: - | BE17: - | BF17: - | BG17: TRUE | BH17: TRUE | BI17: Advance Book, Pre-Register | BJ17: Young Child | BK17: - | BL17: - | BM17: - | BN17: - | BO17: 46207 | BP17: 32 | BQ17: - | BR17: - | BS17: - | BT17: - | BU17: - | BV17: - | BW17: - | BX17: - | BY17: Paid Car Park, On-street / nearby parking | BZ17: Toilets, Showers / changing facilities, Indoor Seating | CB17: Hot Drinks, Comfy Seating / Sofas, Hot & Cold food, Snacks, Sweet treats | CC17: FALSE | CD17: FALSE | CE17: TRUE | CF17: TRUE | CG17: FALSE | CH17: FALSE | CI17: FALSE | CJ17: Energy Burner, Low Effort, Moment of Peace | CK17: Inside | CL17: Climbing | CN17: None / Novice | CO17: Rock climbing, balance, strength, agility, confidence | CR17: Early access introduction, Confidence building, Coordination & balance, Strength & agility, Structured coaching, Mixed-ability sessions, Purpose-built facilities, Climbing, All-weather options | CS17: Activity-specific clothing | CT17: Rockstars Climbing Club.JPG | CU17: Lois | CX17: CLU-00004 | CY17: UPDATE | CZ17: 46307.88 | DA17: 1 | DB17: 2 | DD17: FALSE | DE17: FALSE
A18: club | B18: Sporty Activities | C18: Climbing Centre | D18: Monquays Climbing Club | E18: Monquays is a climbing club for primary school children in years 3-6 that will develop the core skills they need to become confident climbers and boulders. Based in the main climbing arena, children progress through a range of technical and physical challenges, all taught in a fun, engaging way that develops technique and physicial agility on the wall. | F18: Training / Skill Development | G18: Monthly | H18: Weekly | I18: The Quay Climbing Centre | J18: Haven Road | K18: Exeter | M18: EX2 8AX | O18: 50.716826 | P18: -3.5308304 | Q18: 46023 | R18: 46388 | S18: Term-time Only | T18: TRUE | W18: Monday, Tuesday, Wednesday, Thursday, Friday, Saturday, Sunday | X18: FALSE | AA18: 0.6875 | AB18: 0.72916667 | AC18: 0.6875 | AD18: 0.72916667 | AE18: 0.6875 | AF18: 0.72916667 | AG18: 0.6875 | AH18: 0.72916667 | AI18: 0.6875 | AJ18: 0.72916667 | AK18: - | AL18: - | AM18: - | AN18: - | AO18: - | AP18: - | AQ18: - | AR18: - | AS18: - | AT18: - | AU18: - | AV18: - | AW18: - | AX18: - | AY18: 4 | AZ18: 09:10-10:10, 10:20-11:20, 11:30-12:30, 18:00-19:00 | BA18: 2 | BB18: 10:00-11:00, 11:15-12:15 | BC18: - | BD18: - | BE18: - | BF18: - | BG18: TRUE | BH18: TRUE | BI18: Advance Book, Pre-Register | BJ18: (Fixed) Child | BK18: - | BL18: - | BM18: 46333 | BN18: 32 | BO18: - | BP18: - | BQ18: - | BR18: - | BS18: - | BT18: - | BU18: - | BV18: - | BW18: - | BX18: - | BY18: Paid Car Park, On-street / nearby parking | BZ18: Toilets, Showers / changing facilities, Indoor Seating | CB18: Hot Drinks, Comfy Seating / Sofas, Hot & Cold food, Snacks, Sweet treats | CC18: FALSE | CD18: FALSE | CE18: FALSE | CF18: TRUE | CG18: TRUE | CH18: FALSE | CI18: FALSE | CJ18: Energy Burner, Low Effort, Moment of Peace | CK18: Inside | CL18: Climbing | CN18: Beginner | CO18: Rock climbing, strength, agility, confidence | CR18: Confidence building, Coordination & balance, Strength & agility, Structured coaching, Mixed-ability sessions, Purpose-built facilities, Climbing, All-weather options, Skill progression, Non-competitive options | CS18: Activity-specific clothing | CT18: Monquays Climbing Club.JPG | CU18: Lois | CX18: CLU-00003 | CY18: UPDATE | CZ18: 46307.879 | DA18: 1 | DB18: 2 | DD18: FALSE | DE18: FALSE
A19: club | B19: Sporty Activities | C19: Climbing Centre | D19: Youth Climbing Club | E19: The Youth Climbing Club is designed for young adults who want to develop existing climbing skills and progress through the National Indoor Climbing Award Scheme. You can expect exiting and challenging sessions from experienced climbing instructors in a group that is sure to refine technique and confidence. | F19: Training / Skill Development | G19: Monthly | H19: Weekly | I19: The Quay Climbing Centre | J19: Haven Road | K19: Exeter | M19: EX2 8AX | O19: 50.716826 | P19: -3.5308304 | Q19: 46023 | R19: 46388 | S19: Term-time Only | T19: TRUE | W19: Monday, Tuesday, Wednesday, Thursday, Friday, Saturday, Sunday | X19: FALSE | AA19: 0.70833333 | AB19: 0.77083333 | AC19: 0.70833333 | AD19: 0.77083333 | AE19: 0.70833333 | AF19: 0.77083333 | AG19: 0.70833333 | AH19: 0.77083333 | AI19: 0.70833333 | AJ19: 0.77083333 | AK19: - | AL19: - | AM19: - | AN19: - | AO19: - | AP19: - | AQ19: - | AR19: - | AS19: - | AT19: - | AU19: - | AV19: - | AW19: - | AX19: - | AY19: 3 | AZ19: 09:15-10:45, 11:00-12:30, 18:00-19:30 | BA19: 2 | BB19: 09:15-10:45, 11:00-12:30 | BC19: - | BD19: - | BE19: - | BF19: - | BG19: TRUE | BH19: TRUE | BI19: Pre-Register, Advance Book, Members Only | BJ19: Older Child | BK19: - | BL19: - | BM19: - | BN19: - | BO19: - | BP19: - | BQ19: 11-17 | BR19: 36 | BS19: - | BT19: - | BU19: - | BV19: - | BW19: - | BX19: - | BY19: Paid Car Park, On-street / nearby parking | BZ19: Toilets, Showers / changing facilities, Indoor Seating | CB19: Hot Drinks, Comfy Seating / Sofas, Hot & Cold food, Snacks, Sweet treats | CC19: FALSE | CD19: FALSE | CE19: FALSE | CF19: FALSE | CG19: TRUE | CH19: TRUE | CI19: FALSE | CJ19: Energy Burner, Low Effort, Moment of Peace | CK19: Inside | CL19: Climbing | CN19: Intermediate | CO19: Rock climbing, strength, agility, confidence | CR19: Confidence building, Strength & agility, Structured coaching, Purpose-built facilities, Climbing, All-weather options, Skill progression, Non-competitive options | CS19: Activity-specific clothing | CT19: Youth Climbing Club.JPG | CU19: Lois | CX19: CLU-00002 | CY19: UPDATE | CZ19: 46307.879 | DA19: 1 | DB19: 2 | DD19: FALSE | DE19: FALSE
A20: club | B20: Nature & Wildlife Exploration | C20: Forest School | D20: Robin Wood Forest School Under 5's | E20: Run by Liz, Robin Wood Forest School is an outdoor nature-based session built around woodland play, exploring, making and learning through the seasons with the warmest welcome waiting for you. The appeal is obvious the moment you arrive; a natural, thoughtfully created woodland wonderland for children and teens that reveals new corners and activities as you explore it. Set on a sloping woodland, it's not well suited to buggies for smaller visitors, so bring a sling if they're not yet walking; but you can look forward to unstructured, free-roaming activities, that usually wrap up with a snack around the covered fitpit area. There is den building, mud kitchens, sticks, leaves, bug hunting, simple tools or crafts, creative and crafty activities, and the kind of open-ended play that changes with the weather and the site. It is likely to suit families who enjoy getting muddy, following their own ideas, noticing wildlife and being given more freedom than a standard indoor class or play session. Sessions run weekly during term-time with a host of lovely themed activities during half-term holidays. It's the sort of place you meet and make friends at; while many drop-in, the digital presence is limited, so it thrives through word of mouth recommendation; a gem to pass along to a friend. | F20: Stay-and-play (supervised) | G20: One-off (pay as you go), Termly blocks | H20: Weekly | I20: Robin Wood Forest School | K20: Venn Ottery | M20: EX11 1SG | O20: 50.710978 | P20: -3.3221894 | Q20: 46276 | R20: 46318 | S20: Term-time Only | T20: FALSE | W20: Monday, Thursday, Friday | X20: FALSE | Y20: - | Z20: - | AA20: 0.39583333 | AB20: 0.47916667 | AC20: - | AD20: - | AE20: - | AF20: - | AG20: 0.41666667 | AH20: 0.5 | AI20: 0.41666667 | AJ20: 0.5 | AK20: - | AL20: - | AM20: - | AN20: - | BG20: TRUE | BH20: TRUE | BI20: Advance Book | BJ20: (Fixed) Child, Baby | BK20: 0-1 | BL20: 0 | BM20: 46143 | BN20: 10 | BO20: - | BP20: - | BQ20: - | BR20: - | BS20: - | BT20: - | BU20: - | BV20: - | BW20: - | BX20: - | BY20: Free Car Park | BZ20: Toilets, Picnic Benches, Outdoor Seating, Water Refill | CA20: Activity trail, Rope Swings, Outdoor play equipment, Colouring, Activity Sheets or Signs, Children’s trail | CB20: Hot Drinks, Snacks | CC20: TRUE | CD20: TRUE | CE20: TRUE | CF20: FALSE | CG20: FALSE | CH20: FALSE | CI20: FALSE | CJ20: Simple Reset, Under the Radar | CK20: Outside | CO20: Forest school, Woodland play, Outdoor learning, Nature play, Den building, Mud play, Bug hunting, Wildlife spotting, Seasonal nature, Natural materials, Bushcraft, Fire circle, Outdoor crafts, Sticks, Leaves, Trees, Open-ended play, Risky play, Child-led play, Sensory play, Home education, Preschool outdoor play, | CR20: Climbing Logs or balance beams, Mud kitchens, "Sand, soil, and loose materials", Den-building materials, Natural construction zones, Mud and puddles, Forest school activities, Children’s Activity Trails, Immersive natural surroundings, Quiet or low-intervention spaces | CT20: Robin Wood.JPG | CU20: Lois | CX20: CLU-00093 | CY20: CREATE | CZ20: 46297.648 | DA20: 1 | DB20: 1 | DD20: FALSE | DE20: FALSE
A21: club | B21: Nature & Wildlife Exploration | C21: Natural Play Area, Forest School, Den-Building & Nature Craft | D21: Little Farmers - Drake's Farm | E21: Little Farmers at Drake’s Farm is a weekly farm session for young children and their grown-ups, based around animal care, outdoor play, crafts and messy activities. The rhythm of the session gives children a hands-on connection with the farm: feeding and caring for animals first, then moving into a weekly learning theme with related craft and sensory play. It feels more purposeful than a standard stay-and-play because the animals, setting and seasonal farm life shape what children are doing each week and it's structured format gives it a predictable rhythm. The site is lovely, and includes a sandpit, play tractor and play park area, giving children more space to play after the structured farm activities alongside the cafe facilities that are available for the club-attendees. Sessions run for an hour 15mins but families are welcomed to arrive from 9:30am and stay longer after the session to meet other parents, and for children to play on-site and enjoy the setting. | F21: Stay-and-play (supervised) | G21: Termly blocks | H21: Weekly | I21: Higher Fingle Farm | J21: Crockernwell | K21: Exeter | M21: EX6 6NP | O21: 50.715318 | P21: -3.7805463 | Q21: 46273 | R21: 46301 | S21: Term-time Only | T21: FALSE | W21: Tuesday, Wednesday, Thursday, Friday | X21: FALSE | Y21: 0.41666667 | Z21: 0.46875 | AA21: - | AB21: - | AC21: - | AD21: - | AE21: - | AF21: - | AG21: - | AH21: - | AI21: - | AJ21: - | AK21: - | AL21: - | AM21: - | AN21: - | AO21: - | AP21: - | AQ21: - | AR21: - | AS21: - | AT21: - | AU21: - | AV21: - | AW21: - | AX21: - | AY21: - | AZ21: - | BA21: - | BB21: - | BG21: TRUE | BH21: TRUE | BI21: Advance Book | BJ21: (Fixed) Child | BK21: 0-1.9 | BL21: 0 | BM21: 46144 | BN21: 10.25 | BO21: - | BP21: - | BQ21: - | BR21: - | BS21: - | BT21: - | BU21: - | BV21: - | BW21: - | BX21: - | BY21: Free Car Park | BZ21: Toilets, Baby changing, Disabled toilets, Bench Seating, Buggy Friendly, Highchairs, Indoor Seating, Outdoor Seating, Water Refill | CA21: Colouring, Clues / games, "Indoor games (puzzles, boards)", Sandpit, Children's Menu, Indoor Play Space, Outdoor play equipment | CB21: Hot Drinks, Hot & Cold food, Clear Sightlines, Snacks, Sweet treats | CC21: TRUE | CD21: TRUE | CE21: TRUE | CF21: TRUE | CG21: FALSE | CH21: FALSE | CI21: FALSE | CJ21: Under the Radar, Simple Reset | CK21: Mixed | CO21: Farm animals, Animal care, Animal feeding, Farm session, Little farmers, Outdoor play, Messy play, Crafts, Sensory play, Weekly theme, Farm learning, Sandpit, Play tractor, Play park, Preschool play, Toddler play, Baby play, Nature play, Seasonal farm life, Hands-on learning, Dartmoor | CR21: Mud kitchens, "Sand, soil, and loose materials", Farming school activities, Immersive natural surroundings, Quiet or low-intervention spaces, Enclosed or defined play zones | CS21: XC Buggy, Sling / baby carrier, Infant / toddler carrier, Waterproof clothing, Wellies, Change of clothes | CT21: Drakes Farm.jpg | CU21: Website | CX21: CLU-00097 | CY21: CREATE | CZ21: 46295.59 | DA21: 1 | DB21: 1 | DD21: FALSE | DE21: FALSE
A22: club | B22: Indoor Entertainment | C22: Laser Tag | D22: Tenpin Tuesdays Laser Tag | E22: Tenpin Laser Tag is a great activity choice when children are too old for soft play but still need to move and want something exciting to perk up a wet or dreary Tuesday. While this isn't an official club, it's 50% off every Tuesday, so if you've got laser tag in your wishlist, then Tuesdays are the most cost effective day for a battle! It’s a small indoor arena with LED lighting, sound effects, a smoke machine and infrared guns, so expect noise, a dark maze-feel, running about and a bit of competitive chaos. Brilliant fun for kids that love playing team based games, or in small group (min 2 people) and want to play 1:1. One to avoid for children who dislike dark, loud or high-energy spaces, and is worth check booking slots before heading over during peak party season, but there's lots to keep everyone occupied if it's a spontaneous trip and you need to wait for another booking to finish; bookings are usually 30mins long and a further discount is applied if you book for 2 x 30mins. There isn't an age limit as such, it's based on height; children need to be over 4ft (120cm) to play. | F22: Free play (unsupervised) | G22: One-off (pay as you go) | H22: Weekly | I22: 4 - 4 Havenbanks Retail Park | J22: Water Lane | K22: Exeter | M22: EX2 8BY | O22: 50.71621 | P22: -3.5310634 | Q22: 46287 | R22: 46378 | S22: All-year Around | T22: FALSE | W22: Tuesday | X22: FALSE | AC22: 0.41666667 | AD22: 1 | BG22: TRUE | BH22: TRUE | BI22: Pay On Arrival, Advance Book | BJ22: (Fixed) Child, Adult | BK22: - | BL22: - | BM22: 7-16 | BN22: 3 | BO22: - | BP22: - | BQ22: - | BR22: - | BS22: - | BT22: - | BU22: - | BV22: - | BW22: - | BX22: - | BY22: Paid Car Park, Disabled parking bays | BZ22: Toilets, Disabled toilets, Indoor Seating, Pushchair Friendly | CA22: Ice creams, Children's Menu, Indoor Play Space | CB22: Hot Drinks, WiFi, Hot & Cold food, Clear Sightlines, Snacks, Drinks stand, Sweet treats | CC22: FALSE | CD22: FALSE | CE22: FALSE | CF22: FALSE | CG22: TRUE | CH22: TRUE | CI22: FALSE | CJ22: Energy Burner | CK22: Inside | CO22: laser tag, flashing lights, smoke machine, hunter games, team games, laser tag, team battles, multi-player arena | CR22: Laser tag, Café or restaurant, Immersive experience | CT22: Tenpin Laser Tag.JPG | CU22: Lois | CX22: CLU-00089 | CY22: CREATE | CZ22: 46295.572 | DA22: 1 | DB22: 1 | DD22: FALSE | DE22: FALSE
A23: club | B23: Indoor Entertainment | C23: Bowling | D23: Tenpin Tuesdays Bowling | E23: Tenpin Bowling is a safe bet at Marsh Barton when you need an indoor activity that mixed ages can all do together. While not officially a 'club', Tenpin offers 50% off on a Tuesday for bowling, which makes it a cheap and fun after-school activity, or something lightly competitive for the daytime if you're homeschooling. Younger children can usually join in with lighter balls and help from adults, while older ones get the competition element and can challenge themselves. There are 15+ lanes, but it's worth calling ahead if you have specific timings in mind as their Tuesday discount is often popular. If you do arrive and it's busy, they also offer 50% off on Laser Tag on Tuesdays too, and the food/arcade setup nearby means there's plenty to keep everyone occupied until a lane becomes available. | F23: Free play (unsupervised) | G23: One-off (pay as you go) | H23: Weekly | I23: 3 - 4 Havenbanks Retail Park | J23: Water Lane | K23: Exeter | M23: EX2 8BY | O23: 50.71621 | P23: -3.5310634 | Q23: 46287 | R23: 46378 | S23: All-year Around | T23: FALSE | W23: Tuesday | X23: FALSE | AC23: 0.41666667 | AD23: 1 | BG23: TRUE | BH23: TRUE | BI23: Advance Book, Pay On Arrival | BJ23: (Fixed) Child, Adult | BK23: - | BL23: - | BM23: 0-16 | BN23: 4.25 | BO23: - | BP23: - | BQ23: - | BR23: - | BS23: 17+ | BT23: 4.98 | BU23: - | BV23: - | BW23: - | BX23: - | BY23: Paid Car Park, Disabled parking bays | BZ23: Toilets, Disabled toilets, Indoor Seating, Pushchair Friendly | CA23: Ice creams, Children's Menu, Indoor Play Space | CB23: Hot Drinks, WiFi, Hot & Cold food, Clear Sightlines, Snacks, Drinks stand, Sweet treats | CC23: FALSE | CD23: FALSE | CE23: TRUE | CF23: TRUE | CG23: TRUE | CH23: TRUE | CI23: TRUE | CJ23: Moment of Peace | CK23: Inside | CO23: bowling, team games, ten-pin bowling, lane bumpers, bowling ramps | CR23: Bowling lanes, Bar / licensed venue, Arcade games, Pool or snooker table, Laser tag, Café or restaurant | CT23: Tenpin Bowling.JPG | CU23: Lois | CX23: CLU-00088 | CY23: CREATE | CZ23: 46295.571 | DA23: 1 | DB23: 1 | DD23: FALSE | DE23: FALSE
A24: club | B24: Seasonal | D24: Mud-Ventures Halloween Special | E24: Mud-ventures' halloween-themed week of play; an outdoor stay-and-play session for children aged six months to five years, run in Greendale's dedicated outdoor space alongside the farm shop on the Sidmouth Road but with a themed-twist. The concept is built around getting properly messy — mud kitchens, water play stations, sensory trays and a range of activity stations that change week to week, all using natural materials and open-ended resources that children can move between freely. It's the kind of session where the best thing you can do is put children in their most expendable outfit, bring a change of clothes and let them get on with it. Adults supervise throughout, so it's a nice place to meet other local parents in a relaxed, playful environment. Sessions run pretty regularly and are ticketed online ahead of time, so booking ahead is essential (and checking the weather - while some areas are sheltered, it's an outdoor setting so if you and your children are weather-hardy it's ideal. | F24: Stay-and-play (supervised) | G24: One-off (pay as you go) | H24: Daily | I24: Mud-Ventures | J24: Greendale Farm Shop | K24: Exeter | M24: EX5 2JU | O24: 50.70319 | P24: -3.3990958 | Q24: 46321 | R24: 46326 | S24: Holidays Only | T24: FALSE | W24: Monday, Tuesday, Thursday, Friday, Saturday | X24: TRUE | Y24: 0.41666667 | Z24: 0.47916667 | BG24: TRUE | BH24: TRUE | BI24: Advance Book | BJ24: (Fixed) Child, Adult, Baby | BK24: 0-1 | BL24: 0 | BM24: 46143 | BN24: 13.5 | BO24: - | BP24: - | BQ24: - | BR24: - | BS24: 18+ | BT24: 0 | BU24: - | BV24: - | BW24: - | BX24: - | BY24: Free Car Park | BZ24: Toilets, Disabled toilets, Baby changing, Picnic Benches, BYO Picnic, Buggy Friendly, Indoor Seating | CA24: Clues / games, Sandpit, Ride on Vehicles, Outdoor play equipment | CB24: Clear Sightlines | CC24: TRUE | CD24: TRUE | CE24: TRUE | CF24: FALSE | CG24: FALSE | CH24: FALSE | CI24: FALSE | CJ24: Moment of Peace | CK24: Outside | CO24: muddy play, sensory play, outdoor activities, Messy play, Mud kitchen, Water play, Outdoor play, Stay and play, Sensory play, Loose parts, Natural materials, Crafts, Scooping, Pouring, Mixing, Collecting, Building, Open-ended play, Toddler play, Baby play, Preschool play, Farm setting, Greendale Farm, Farm trail nearby, halloween | CR24: Mud kitchens, "Sand, soil, and loose materials", Natural construction zones, Mud and puddles, Forest school activities, Guided outdoor learning prompts, Quiet or low-intervention spaces, Enclosed or defined play zones | CS24: Wellies, Waterproof clothing, Change of clothes | CT24: Mud Ventures.jpg | CU24: Lois | CX24: CLU-00107 | CY24: CREATE | CZ24: 46295.515 | DA24: 1 | DB24: 1 | DD24: FALSE | DE24: FALSE
A25: club | B25: Nature & Wildlife Exploration | C25: Natural Play Area | D25: Mud-Ventures Stay & Play | E25: Mud-ventures is an outdoor stay-and-play session for children aged six months to five years, run in Greendale's dedicated outdoor space alongside the farm shop on the Sidmouth Road. The idea is built around getting properly messy — mud kitchens, water play stations, sensory trays and a range of activity stations that change week to week, all using natural materials and open-ended resources that children can move between freely. It's the kind of session where the best thing you can do is put children in their most expendable outfit, bring a change of clothes and let them get on with it. Adults supervise throughout, so it's a nice place to meet other local parents in a relaxed, playful environment. Sessions run pretty regularly and are ticketed online ahead of time, so booking ahead is essential (and checking the weather - while some areas are sheltered, it's an outdoor setting so if you and your children are weather-hardy it's ideal. With enough pricing brackets to cater for every arrangement, the exact price varies a bit depending on what combination of adults / children / infants in your group. | F25: Stay-and-play (supervised) | G25: One-off (pay as you go) | H25: Weekly | I25: Mud-Ventures | J25: Greendale Farm Shop | K25: Exeter | M25: EX5 2JU | O25: 50.70319 | P25: -3.3990958 | Q25: 46296 | R25: 46320 | S25: Term-time Only | T25: FALSE | W25: Monday, Tuesday, Thursday, Friday, Sunday | X25: TRUE | Y25: 0.41666667 | Z25: 0.47916667 | BG25: TRUE | BH25: TRUE | BI25: Advance Book | BJ25: Group, Baby | BK25: 0-1 | BL25: 0 | BM25: 46143 | BN25: 7.85 | BO25: - | BP25: - | BQ25: - | BR25: - | BS25: - | BT25: - | BU25: - | BV25: - | BW25: 1 adult, 1 child | BX25: 9.85 | BY25: Free Car Park | BZ25: Toilets, Disabled toilets, Baby changing, Picnic Benches, BYO Picnic, Buggy Friendly, Indoor Seating | CA25: Clues / games, Sandpit, Ride on Vehicles, Outdoor play equipment | CB25: Clear Sightlines | CC25: TRUE | CD25: TRUE | CE25: TRUE | CF25: FALSE | CG25: FALSE | CH25: FALSE | CI25: FALSE | CJ25: Moment of Peace | CK25: Outside | CO25: muddy play, sensory play, outdoor activities, Messy play, Mud kitchen, Water play, Outdoor play, Stay and play, Sensory play, Loose parts, Natural materials, Crafts, Scooping, Pouring, Mixing, Collecting, Building, Open-ended play, Toddler play, Baby play, Preschool play, Farm setting, Greendale Farm, Farm trail nearby | CR25: Mud kitchens, "Sand, soil, and loose materials", Natural construction zones, Mud and puddles, Forest school activities, Guided outdoor learning prompts, Quiet or low-intervention spaces, Enclosed or defined play zones | CS25: Wellies, Waterproof clothing, Change of clothes | CT25: Mud Ventures.jpg | CU25: Lois | CX25: CLU-00101 | CY25: CREATE | CZ25: 46295.513 | DA25: 1 | DB25: 1 | DD25: FALSE | DE25: FALSE
A26: club | B26: Community Groups | C26: Playgroup | D26: Cake At The Castle | E26: A drop-in stay-and-play for children of all ages, with enough variety that everyone tends to find something to make or play with fairly quickly. Cushioned mats and sensory toys give the littlest ones a gentler space, while older children have soft play, crafts, games and the outdoor park to keep them moving and engaged. Drop in whenever suits you, there's always cake and a hot drink waiting, and the chance to spend some time with other local military families. | F26: Stay-and-play (supervised) | G26: One-off (pay as you go) | H26: Daily | I26: The Families Room at the Gordon Messenger Centre | J26: Exmouth Road | K26: Lympstone | M26: EX8 5AR | O26: 50.664676 | P26: -3.4326855 | Q26: 46294.042 | R26: 46374 | S26: All Year Around | T26: FALSE | W26: Tuesday, Wednesday, Thursday, Friday | X26: TRUE | Y26: 0.41666667 | Z26: 0.5 | AA26: - | AB26: - | AC26: - | AD26: - | AE26: - | AF26: - | AG26: - | AH26: - | AI26: - | AJ26: - | AK26: - | AL26: - | AM26: - | AN26: - | AO26: - | AP26: - | AQ26: - | AR26: - | AS26: - | AT26: - | AU26: - | AV26: - | AW26: - | AX26: - | AY26: - | AZ26: - | BA26: - | BB26: - | BC26: - | BG26: FALSE | BH26: FALSE | BI26: Open (Free) Access | BK26: - | BL26: - | BM26: - | BN26: - | BO26: - | BP26: - | BQ26: - | BR26: - | BS26: - | BT26: - | BU26: - | BV26: - | BW26: - | BX26: - | BY26: Free Car Park | BZ26: Toilets, Disabled toilets, Baby changing, Highchairs, Indoor Seating, Water Refills | CA26: Colouring, Indoor games (puzzles, boards), Swings, Slides, Climbing Frames, Indoor Play Space | CB26: Hot Drinks, Comfy Seating / Sofas, WiFi, Snacks, Sweet treats | CC26: TRUE | CD26: TRUE | CE26: TRUE | CF26: FALSE | CG26: FALSE | CH26: FALSE | CI26: FALSE | CJ26: Simple Reset | CK26: Inside | CL26: FALSE | CO26: crafting, soft play, free play, playground, cake, coffee, socialising, local mum's groups | CR26: Welcoming space, "Toys, toy corners", Refreshments Provided, Local parent hangout, Like-minded families, "Relaxed, child-friendly setting", Play areas or equipment, Craft Tables or Activities, Newbie-friendly! | CT26: Cake At Castle GMC.JPG | CU26: Lois | CV26: P001 | CW26: TRUE | CX26: P001-CLU-00004 | CY26: CREATE | CZ26: 46313 | DA26: 1 | DB26: 1 | DD26: FALSE | DE26: FALSE
A27: club | B27: Community Groups | C27: Social Club | D27: Fun At The Fort | E27: An after-school drop-in club for school-aged children from military families, built around the simple idea that sometimes children just need somewhere to run around, be themselves and spend time with others whose lives look a bit like theirs. There are toys, soft play, crafts and the outdoor park to keep everyone moving, and a hot snack tea is included so nobody arrives home hungry. Younger and older siblings are always welcome, which means the whole family can come along without anyone being left out. While the children do their thing, the adults around them get a brew and the particular ease that comes from being with people who genuinely understand military and family life and need a quick reprieve before heading home for the evening routine! | F27: Stay-and-play (supervised) | G27: One-off (pay as you go) | H27: Weekly | I27: The Families Room at the Gordon Messenger Centre | J27: Exmouth Road | K27: Lympstone | M27: EX8 5AR | O27: 50.664676 | P27: -3.4326855 | Q27: 46293.042 | R27: 46314.042 | S27: Term-time Only | T27: FALSE | W27: Monday | X27: TRUE | Y27: 0.64583333 | Z27: 0.70833333 | AA27: - | AB27: - | AC27: - | AD27: - | AE27: - | AF27: - | AG27: - | AH27: - | AI27: - | AJ27: - | AK27: - | AL27: - | AM27: - | AN27: - | AO27: - | AP27: - | AQ27: - | AR27: - | AS27: - | AT27: - | AU27: - | AV27: - | AW27: - | AX27: - | AY27: - | AZ27: - | BA27: - | BB27: - | BC27: - | BG27: FALSE | BH27: FALSE | BI27: Open (Free) Access | BK27: - | BL27: - | BM27: - | BN27: - | BO27: - | BP27: - | BQ27: - | BR27: - | BS27: - | BT27: - | BU27: - | BV27: - | BW27: - | BX27: - | BY27: Free Car Park | BZ27: Toilets, Disabled toilets, Baby changing, Highchairs, Indoor Seating, Water Refills | CA27: Colouring, Indoor games (puzzles, boards), Swings, Slides, Climbing Frames, Indoor Play Space | CB27: Hot Drinks, Comfy Seating / Sofas, WiFi, Snacks | CC27: FALSE | CD27: FALSE | CE27: TRUE | CF27: TRUE | CG27: TRUE | CH27: FALSE | CI27: FALSE | CJ27: Simple Reset | CK27: Inside | CL27: TRUE | CO27: after school, energy burn off, kids clubs, afterschool clubs, softplay, playgrounds, parks, coffee, cake | CR27: Welcoming space, Craft Tables or Activities, "Toys, toy corners", Refreshments Provided, Local parent hangout, "Relaxed, child-friendly setting", Play areas or equipment, Parent-child activities, Newbie-friendly! | CT27: Fun At The Fort.jpg | CU27: Charley | CV27: P001 | CW27: TRUE | CX27: P001-CLU-00005 | CY27: CREATE | CZ27: 46313 | DA27: 1 | DB27: 1 | DD27: FALSE | DE27: FALSE
A28: club | B28: Sporty Activities | C28: Swimming Pool | D28: Family Swim | E28: A relaxed family swim session giving serving personnel and their families the chance to use the camp pool together. It is a simple way to add swimming into the week without needing to travel far and in an environment that will be familiar to many; whether children want to practise confidence in the water, burn off energy, play together or just enjoy time in the pool with a parent close by it's a great opportunity to use the pool facilities and bring whatever water toys the kids want! The session is not a formal swimming lesson, so the pace can follow the family: younger children can splash, float and build familiarity with the water while it's quieter, while more confident swimmers can move, play and practise skills in a familiar setting - if the lifeguards are happy, there's also the diving boards to build confidence on. | F28: Training / Skill Development | G28: One-off (pay as you go) | H28: Weekly | I28: Swimming Pool | J28: Commando Training Centre Royal Marines | K28: Exton | M28: EX8 5AR | O28: 50.664416 | P28: -3.4346757 | Q28: 46305 | R28: 46307 | S28: All Year Around | T28: FALSE | W28: Saturday | X28: TRUE | Y28: 0.57291667 | Z28: 0.60416667 | AA28: - | AB28: - | AC28: - | AD28: - | AE28: - | AF28: - | AG28: - | AH28: - | AI28: - | AJ28: - | AK28: - | AL28: - | AM28: - | AN28: - | AO28: - | AP28: - | AQ28: - | AR28: - | AS28: - | AT28: - | AU28: - | AV28: - | AW28: - | AX28: - | AY28: - | AZ28: - | BA28: - | BB28: - | BC28: - | BG28: FALSE | BH28: FALSE | BI28: Open (Free) Access | BK28: - | BL28: - | BM28: - | BN28: - | BO28: - | BP28: - | BQ28: - | BR28: - | BS28: - | BT28: - | BU28: - | BV28: - | BW28: - | BX28: - | BY28: Free Car Park, Bike racks / bays | BZ28: Toilets, Showers / changing facilities, BYO Picnic | CC28: TRUE | CD28: TRUE | CE28: TRUE | CF28: TRUE | CG28: TRUE | CH28: TRUE | CI28: TRUE | CJ28: Energy Burner | CK28: Inside | CL28: TRUE | CM28: Swimming | CN28: None / Novice | CO28: swimming, family swim, indoor swimming, lifeguarded swim, diving boards, floats, swimming practice, swimming confidence, free play | CR28: Confidence building, Non-competitive options, All-weather options, Swimming | CS28: Swimming kit, Towels | CT28: Family Swim.jpg | CU28: Lois | CV28: P001 | CW28: TRUE | CX28: P001-CLU-00006 | CY28: CREATE | CZ28: 46313 | DA28: 1 | DB28: 1 | DD28: FALSE | DE28: FALSE
A29: club | B29: Sporty Activities | C29: Swimming Pool | D29: Family Swim | E29: A relaxed family swim session giving serving personnel and their families the chance to use the camp pool together. It is a simple way to add swimming into the week without needing to travel far and in an environment that will be familiar to many; whether children want to practise confidence in the water, burn off energy, play together or just enjoy time in the pool with a parent close by it's a great opportunity to use the pool facilities and bring whatever water toys the kids want! The session is not a formal swimming lesson, so the pace can follow the family: younger children can splash, float and build familiarity with the water while it's quieter, while more confident swimmers can move, play and practise skills in a familiar setting - if the lifeguards are happy, there's also the diving boards to build confidence on. | F29: Training / Skill Development | G29: One-off (pay as you go) | H29: Weekly | I29: Swimming Pool | J29: Commando Training Centre Royal Marines | K29: Exton | M29: EX8 5AR | O29: 50.664416 | P29: -3.4346757 | Q29: 46396 | R29: 46487 | S29: All Year Around | T29: FALSE | W29: Saturday | X29: TRUE | Y29: 0.57291667 | Z29: 0.60416667 | AA29: - | AB29: - | AC29: - | AD29: - | AE29: - | AF29: - | AG29: - | AH29: - | AI29: - | AJ29: - | AK29: - | AL29: - | AM29: - | AN29: - | AO29: - | AP29: - | AQ29: - | AR29: - | AS29: - | AT29: - | AU29: - | AV29: - | AW29: - | AX29: - | AY29: - | AZ29: - | BA29: - | BB29: - | BC29: - | BG29: FALSE | BH29: FALSE | BI29: Open (Free) Access | BK29: - | BL29: - | BM29: - | BN29: - | BO29: - | BP29: - | BQ29: - | BR29: - | BS29: - | BT29: - | BU29: - | BV29: - | BW29: - | BX29: - | BY29: Free Car Park, Bike racks / bays | BZ29: Toilets, Showers / changing facilities, BYO Picnic | CC29: TRUE | CD29: TRUE | CE29: TRUE | CF29: TRUE | CG29: TRUE | CH29: TRUE | CI29: TRUE | CJ29: Energy Burner | CK29: Inside | CL29: TRUE | CM29: Swimming | CN29: None / Novice | CO29: swimming, family swim, indoor swimming, lifeguarded swim, diving boards, floats, swimming practice, swimming confidence, free play | CR29: Confidence building, Non-competitive options, All-weather options, Swimming | CS29: Swimming kit, Towels | CT29: Family Swim.jpg | CU29: Lois | CV29: P001 | CW29: TRUE | CX29: P001-CLU-00007 | CY29: CREATE | CZ29: 46313 | DA29: 1 | DB29: 1 | DD29: FALSE | DE29: FALSE
